Workbook

Sheet Summary
A1: Oregon LIHTC off-market sourcing: lead tracker
A2: ="As of "&TEXT(Scoring!B3,"mmmm d, yyyy")&". Universe: HUD LIHTC database extract for Oregon (uploaded LIHTC.xlsx). Scores are provisional until the yellow columns on the Leads tab are filled in." -> As of October 2, 2026. Universe: HUD LIHTC database extract for Oregon (uploaded LIHTC.xlsx). Scores are provisional until the yellow columns on the Leads tab are filled in.
A4: Search summary
A5: Metric | B5: Count | C5: Units
A6: Records scanned | B6: =COUNTA(Leads!$E$2:$E$755) -> 754 | C6: =SUM(Leads!$J$2:$J$755) -> 45401
A7: Superseded or duplicate records | B7: =COUNTIF(Leads!$T$2:$T$755,"Y") -> 12 | C7: =SUMIF(Leads!$T$2:$T$755,"Y",Leads!$J$2:$J$755) -> 711
A8: Unique leads scored | B8: =B6-B7 -> 742 | C8: =C6-C7 -> 44690
A9: Out of LIHTC program (HUD: no longer monitored) | B9: =COUNTIF(Leads!$D$2:$D$755,"Out of program") -> 105 | C9: =SUMIF(Leads!$D$2:$D$755,"Out of program",Leads!$J$2:$J$755) -> 2339
A10: Below the 5-unit PuSH-CP threshold | B10: =COUNTIF(Leads!$R$2:$R$755,"No (under 5 units)") -> 73 | C10: =SUMIF(Leads!$R$2:$R$755,"No (under 5 units)",Leads!$J$2:$J$755) -> 110
A11: Verified expiration dates entered | B11: =COUNT(Leads!$U$2:$U$755) -> 0
A13: Pipeline actions by tier
A14: Tier | B14: Leads | C14: Units | D14: Share of leads | E14: Action
A15: Immediate | B15: =COUNTIF(Leads!$B$2:$B$755,A15) -> 8 | C15: =SUMIF(Leads!$B$2:$B$755,A15,Leads!$J$2:$J$755) -> 706 | D15: =IF($B$19=0,0,B15/$B$19) -> 0.010781671 | E15: Verify the restriction end date and owner this week; open direct owner or GP outreach.
A16: This week | B16: =COUNTIF(Leads!$B$2:$B$755,A16) -> 361 | C16: =SUMIF(Leads!$B$2:$B$755,A16,Leads!$J$2:$J$755) -> 21917 | D16: =IF($B$19=0,0,B16/$B$19) -> 0.48652291 | E16: Pull the OHCS expiration forecast and county ownership records; fill the yellow columns; re-rank.
A17: Nurture | B17: =COUNTIF(Leads!$B$2:$B$755,A17) -> 285 | C17: =SUMIF(Leads!$B$2:$B$755,A17,Leads!$J$2:$J$755) -> 14234 | D17: =IF($B$19=0,0,B17/$B$19) -> 0.38409704 | E17: Add to a quarterly watch list; re-score when vintage ages into a window.
A18: Low | B18: =COUNTIF(Leads!$B$2:$B$755,A18) -> 88 | C18: =SUMIF(Leads!$B$2:$B$755,A18,Leads!$J$2:$J$755) -> 7833 | D18: =IF($B$19=0,0,B18/$B$19) -> 0.11859838 | E18: No action; inside the credit period or no signal.
A19: Total | B19: =SUM(B15:B18) -> 742 | C19: =SUM(C15:C18) -> 44690 | E19: =IF(B19=B8,"Ties to unique leads scored","CHECK: does not tie to unique leads") -> Ties to unique leads scored
A21: Signal distribution by play
A22: Play / lifecycle stage | B22: Leads | C22: Units | D22: Avg score | E22: What it means
A23: Expiring: notice window (verified) | B23: =COUNTIF(Leads!$D$2:$D$755,A23) -> 0 | C23: =SUMIF(Leads!$D$2:$D$755,A23,Leads!$J$2:$J$755) -> 0 | D23: =IFERROR(AVERAGEIF(Leads!$D$2:$D$755,A23,Leads!$C$2:$C$755),0) -> 0 | E23: Verified affordability end date inside the Oregon owner-notice window. Highest-priority outreach.
A24: Expired (verified) | B24: =COUNTIF(Leads!$D$2:$D$755,A24) -> 0 | C24: =SUMIF(Leads!$D$2:$D$755,A24,Leads!$J$2:$J$755) -> 0 | D24: =IFERROR(AVERAGEIF(Leads!$D$2:$D$755,A24,Leads!$C$2:$C$755),0) -> 0 | E24: Verified end date has passed; tenant safe-harbour and any recorded right of first refusal may still apply.
A25: Expiring: 10-yr horizon (verified) | B25: =COUNTIF(Leads!$D$2:$D$755,A25) -> 0 | C25: =SUMIF(Leads!$D$2:$D$755,A25,Leads!$J$2:$J$755) -> 0 | D25: =IFERROR(AVERAGEIF(Leads!$D$2:$D$755,A25,Leads!$C$2:$C$755),0) -> 0 | E25: Verified end date inside the 10-year forecast horizon.
A26: 30-yr mark: notice window (est.) | B26: =COUNTIF(Leads!$D$2:$D$755,A26) -> 83 | C26: =SUMIF(Leads!$D$2:$D$755,A26,Leads!$J$2:$J$755) -> 5724 | D26: =IFERROR(AVERAGEIF(Leads!$D$2:$D$755,A26,Leads!$C$2:$C$755),0) -> 70.674699 | E26: Federal minimum 30-year period closes within the notice window. Confirm the REUA term; many run longer.
A27: Past 30-yr mark (verify) | B27: =COUNTIF(Leads!$D$2:$D$755,A27) -> 105 | C27: =SUMIF(Leads!$D$2:$D$755,A27,Leads!$J$2:$J$755) -> 6849 | D27: =IFERROR(AVERAGEIF(Leads!$D$2:$D$755,A27,Leads!$C$2:$C$755),0) -> 64.2 | E27: Older than the federal 30-year minimum but still listed as monitored: either a longer state restriction or a recent expiry.
A28: Year-15 window | B28: =COUNTIF(Leads!$D$2:$D$755,A28) -> 110 | C28: =SUMIF(Leads!$D$2:$D$755,A28,Leads!$J$2:$J$755) -> 5917 | D28: =IFERROR(AVERAGEIF(Leads!$D$2:$D$755,A28,Leads!$C$2:$C$755),0) -> 56.4 | E28: Compliance period closing; limited partner exit, GP buyout or third-party sale in play.
A29: Recap window | B29: =COUNTIF(Leads!$D$2:$D$755,A29) -> 206 | C29: =SUMIF(Leads!$D$2:$D$755,A29,Leads!$J$2:$J$755) -> 13926 | D29: =IFERROR(AVERAGEIF(Leads!$D$2:$D$755,A29,Leads!$C$2:$C$755),0) -> 47.669903 | E29: Years 18 and later of extended use; recapitalisation or resyndication candidate.
A30: Out of program | B30: =COUNTIF(Leads!$D$2:$D$755,A30) -> 105 | C30: =SUMIF(Leads!$D$2:$D$755,A30,Leads!$J$2:$J$755) -> 2339 | D30: =IFERROR(AVERAGEIF(Leads!$D$2:$D$755,A30,Leads!$C$2:$C$755),0) -> 44.666667 | E30: HUD shows no longer monitored. Treat as a conventional asset and confirm current ownership.
A31: Pre-1990, still listed | B31: =COUNTIF(Leads!$D$2:$D$755,A31) -> 18 | C31: =SUMIF(Leads!$D$2:$D$755,A31,Leads!$J$2:$J$755) -> 259 | D31: =IFERROR(AVERAGEIF(Leads!$D$2:$D$755,A31,Leads!$C$2:$C$755),0) -> 52 | E31: Pre-1990 allocation (15-year compliance only) still shown as active; likely stale data or another subsidy layer.
A32: Late compliance | B32: =COUNTIF(Leads!$D$2:$D$755,A32) -> 27 | C32: =SUMIF(Leads!$D$2:$D$755,A32,Leads!$J$2:$J$755) -> 1750 | D32: =IFERROR(AVERAGEIF(Leads!$D$2:$D$755,A32,Leads!$C$2:$C$755),0) -> 33.740741 | E32: Years 11 to 12; too early for an exit conversation.
A33: Credit period | B33: =COUNTIF(Leads!$D$2:$D$755,A33) -> 85 | C33: =SUMIF(Leads!$D$2:$D$755,A33,Leads!$J$2:$J$755) -> 7853 | D33: =IFERROR(AVERAGEIF(Leads!$D$2:$D$755,A33,Leads!$C$2:$C$755),0) -> 24.388235 | E33: Inside the 10-year credit period; not a lead.
A34: Unknown vintage | B34: =COUNTIF(Leads!$D$2:$D$755,A34) -> 3 | C34: =SUMIF(Leads!$D$2:$D$755,A34,Leads!$J$2:$J$755) -> 73 | D34: =IFERROR(AVERAGEIF(Leads!$D$2:$D$755,A34,Leads!$C$2:$C$755),0) -> 29 | E34: HUD ID carries no year.
A35: Superseded record | B35: =COUNTIF(Leads!$D$2:$D$755,A35) -> 12 | C35: =SUMIF(Leads!$D$2:$D$755,A35,Leads!$J$2:$J$755) -> 711 | D35: =IFERROR(AVERAGEIF(Leads!$D$2:$D$755,A35,Leads!$C$2:$C$755),0) -> 0 | E35: Replaced by a later allocation at the same address, or a duplicate row.
A36: Total | B36: =SUM(B23:B35) -> 754 | C36: =SUM(C23:C35) -> 45401 | E36: =IF(B36=B6,"Ties to records scanned","CHECK: does not tie to records scanned") -> Ties to records scanned
A38: Top 40 leads (live ranking; ties broken by unit count)
A39: Rank | B39: Project name | C39: City | D39: Units | E39: Play / lifecycle stage | F39: Vintage | G39: Score | H39: Tier | I39: HUD ID
A40: 1 | B40: =INDEX(Leads!$F$2:$F$755,MATCH($A40,Leads!$A$2:$A$755,0)) -> VILLAGE AT LOVEJOY FOUNTAIN | C40: =INDEX(Leads!$H$2:$H$755,MATCH($A40,Leads!$A$2:$A$755,0)) -> PORTLAND | D40: =INDEX(Leads!$J$2:$J$755,MATCH($A40,Leads!$A$2:$A$755,0)) -> 198 | E40: =INDEX(Leads!$D$2:$D$755,MATCH($A40,Leads!$A$2:$A$755,0)) -> 30-yr mark: notice window (est.) | F40: =INDEX(Leads!$N$2:$N$755,MATCH($A40,Leads!$A$2:$A$755,0)) -> 1999 | G40: =INDEX(Leads!$C$2:$C$755,MATCH($A40,Leads!$A$2:$A$755,0)) -> 77 | H40: =INDEX(Leads!$B$2:$B$755,MATCH($A40,Leads!$A$2:$A$755,0)) -> Immediate | I40: =INDEX(Leads!$E$2:$E$755,MATCH($A40,Leads!$A$2:$A$755,0)) -> ORA19990155
A41: 2 | B41: =INDEX(Leads!$F$2:$F$755,MATCH($A41,Leads!$A$2:$A$755,0)) -> ST ANTHONY VILLAGE | C41: =INDEX(Leads!$H$2:$H$755,MATCH($A41,Leads!$A$2:$A$755,0)) -> PORTLAND | D41: =INDEX(Leads!$J$2:$J$755,MATCH($A41,Leads!$A$2:$A$755,0)) -> 128 | E41: =INDEX(Leads!$D$2:$D$755,MATCH($A41,Leads!$A$2:$A$755,0)) -> 30-yr mark: notice window (est.) | F41: =INDEX(Leads!$N$2:$N$755,MATCH($A41,Leads!$A$2:$A$755,0)) -> 1999 | G41: =INDEX(Leads!$C$2:$C$755,MATCH($A41,Leads!$A$2:$A$755,0)) -> 77 | H41: =INDEX(Leads!$B$2:$B$755,MATCH($A41,Leads!$A$2:$A$755,0)) -> Immediate | I41: =INDEX(Leads!$E$2:$E$755,MATCH($A41,Leads!$A$2:$A$755,0)) -> ORA19990140
A42: 3 | B42: =INDEX(Leads!$F$2:$F$755,MATCH($A42,Leads!$A$2:$A$755,0)) -> PARKWAY VILLAGE APTS - SALEM | C42: =INDEX(Leads!$H$2:$H$755,MATCH($A42,Leads!$A$2:$A$755,0)) -> SALEM | D42: =INDEX(Leads!$J$2:$J$755,MATCH($A42,Leads!$A$2:$A$755,0)) -> 124 | E42: =INDEX(Leads!$D$2:$D$755,MATCH($A42,Leads!$A$2:$A$755,0)) -> 30-yr mark: notice window (est.) | F42: =INDEX(Leads!$N$2:$N$755,MATCH($A42,Leads!$A$2:$A$755,0)) -> 1997 | G42: =INDEX(Leads!$C$2:$C$755,MATCH($A42,Leads!$A$2:$A$755,0)) -> 77 | H42: =INDEX(Leads!$B$2:$B$755,MATCH($A42,Leads!$A$2:$A$755,0)) -> Immediate | I42: =INDEX(Leads!$E$2:$E$755,MATCH($A42,Leads!$A$2:$A$755,0)) -> ORA19970141
A43: 4 | B43: =INDEX(Leads!$F$2:$F$755,MATCH($A43,Leads!$A$2:$A$755,0)) -> FIFTH AVE COURTS | C43: =INDEX(Leads!$H$2:$H$755,MATCH($A43,Leads!$A$2:$A$755,0)) -> PORTLAND | D43: =INDEX(Leads!$J$2:$J$755,MATCH($A43,Leads!$A$2:$A$755,0)) -> 96 | E43: =INDEX(Leads!$D$2:$D$755,MATCH($A43,Leads!$A$2:$A$755,0)) -> 30-yr mark: notice window (est.) | F43: =INDEX(Leads!$N$2:$N$755,MATCH($A43,Leads!$A$2:$A$755,0)) -> 1999 | G43: =INDEX(Leads!$C$2:$C$755,MATCH($A43,Leads!$A$2:$A$755,0)) -> 77 | H43: =INDEX(Leads!$B$2:$B$755,MATCH($A43,Leads!$A$2:$A$755,0)) -> Immediate | I43: =INDEX(Leads!$E$2:$E$755,MATCH($A43,Leads!$A$2:$A$755,0)) -> ORA19990055
A44: 5 | B44: =INDEX(Leads!$F$2:$F$755,MATCH($A44,Leads!$A$2:$A$755,0)) -> FLOYD LIGHT APTS | C44: =INDEX(Leads!$H$2:$H$755,MATCH($A44,Leads!$A$2:$A$755,0)) -> PORTLAND | D44: =INDEX(Leads!$J$2:$J$755,MATCH($A44,Leads!$A$2:$A$755,0)) -> 51 | E44: =INDEX(Leads!$D$2:$D$755,MATCH($A44,Leads!$A$2:$A$755,0)) -> 30-yr mark: notice window (est.) | F44: =INDEX(Leads!$N$2:$N$755,MATCH($A44,Leads!$A$2:$A$755,0)) -> 1997 | G44: =INDEX(Leads!$C$2:$C$755,MATCH($A44,Leads!$A$2:$A$755,0)) -> 77 | H44: =INDEX(Leads!$B$2:$B$755,MATCH($A44,Leads!$A$2:$A$755,0)) -> Immediate | I44: =INDEX(Leads!$E$2:$E$755,MATCH($A44,Leads!$A$2:$A$755,0)) -> ORA19970035
A45: 6 | B45: =INDEX(Leads!$F$2:$F$755,MATCH($A45,Leads!$A$2:$A$755,0)) -> COLUMBIA VIEW APTS | C45: =INDEX(Leads!$H$2:$H$755,MATCH($A45,Leads!$A$2:$A$755,0)) -> HOOD RIVER | D45: =INDEX(Leads!$J$2:$J$755,MATCH($A45,Leads!$A$2:$A$755,0)) -> 48 | E45: =INDEX(Leads!$D$2:$D$755,MATCH($A45,Leads!$A$2:$A$755,0)) -> 30-yr mark: notice window (est.) | F45: =INDEX(Leads!$N$2:$N$755,MATCH($A45,Leads!$A$2:$A$755,0)) -> 1999 | G45: =INDEX(Leads!$C$2:$C$755,MATCH($A45,Leads!$A$2:$A$755,0)) -> 77 | H45: =INDEX(Leads!$B$2:$B$755,MATCH($A45,Leads!$A$2:$A$755,0)) -> Immediate | I45: =INDEX(Leads!$E$2:$E$755,MATCH($A45,Leads!$A$2:$A$755,0)) -> ORA19990040
A46: 7 | B46: =INDEX(Leads!$F$2:$F$755,MATCH($A46,Leads!$A$2:$A$755,0)) -> AMES CREEK COURT | C46: =INDEX(Leads!$H$2:$H$755,MATCH($A46,Leads!$A$2:$A$755,0)) -> SWEET HOME | D46: =INDEX(Leads!$J$2:$J$755,MATCH($A46,Leads!$A$2:$A$755,0)) -> 31 | E46: =INDEX(Leads!$D$2:$D$755,MATCH($A46,Leads!$A$2:$A$755,0)) -> 30-yr mark: notice window (est.) | F46: =INDEX(Leads!$N$2:$N$755,MATCH($A46,Leads!$A$2:$A$755,0)) -> 1999 | G46: =INDEX(Leads!$C$2:$C$755,MATCH($A46,Leads!$A$2:$A$755,0)) -> 77 | H46: =INDEX(Leads!$B$2:$B$755,MATCH($A46,Leads!$A$2:$A$755,0)) -> Immediate | I46: =INDEX(Leads!$E$2:$E$755,MATCH($A46,Leads!$A$2:$A$755,0)) -> ORA19990005
A47: 8 | B47: =INDEX(Leads!$F$2:$F$755,MATCH($A47,Leads!$A$2:$A$755,0)) -> RONDEL COURT | C47: =INDEX(Leads!$H$2:$H$755,MATCH($A47,Leads!$A$2:$A$755,0)) -> MOLALLA | D47: =INDEX(Leads!$J$2:$J$755,MATCH($A47,Leads!$A$2:$A$755,0)) -> 30 | E47: =INDEX(Leads!$D$2:$D$755,MATCH($A47,Leads!$A$2:$A$755,0)) -> 30-yr mark: notice window (est.) | F47: =INDEX(Leads!$N$2:$N$755,MATCH($A47,Leads!$A$2:$A$755,0)) -> 1999 | G47: =INDEX(Leads!$C$2:$C$755,MATCH($A47,Leads!$A$2:$A$755,0)) -> 77 | H47: =INDEX(Leads!$B$2:$B$755,MATCH($A47,Leads!$A$2:$A$755,0)) -> Immediate | I47: =INDEX(Leads!$E$2:$E$755,MATCH($A47,Leads!$A$2:$A$755,0)) -> ORA19990130
A48: 9 | B48: =INDEX(Leads!$F$2:$F$755,MATCH($A48,Leads!$A$2:$A$755,0)) -> TWELFTH AVENUE TERRACE | C48: =INDEX(Leads!$H$2:$H$755,MATCH($A48,Leads!$A$2:$A$755,0)) -> PORTLAND | D48: =INDEX(Leads!$J$2:$J$755,MATCH($A48,Leads!$A$2:$A$755,0)) -> 119 | E48: =INDEX(Leads!$D$2:$D$755,MATCH($A48,Leads!$A$2:$A$755,0)) -> Past 30-yr mark (verify) | F48: =INDEX(Leads!$N$2:$N$755,MATCH($A48,Leads!$A$2:$A$755,0)) -> 1994 | G48: =INDEX(Leads!$C$2:$C$755,MATCH($A48,Leads!$A$2:$A$755,0)) -> 71 | H48: =INDEX(Leads!$B$2:$B$755,MATCH($A48,Leads!$A$2:$A$755,0)) -> This week | I48: =INDEX(Leads!$E$2:$E$755,MATCH($A48,Leads!$A$2:$A$755,0)) -> ORA19949091
A49: 10 | B49: =INDEX(Leads!$F$2:$F$755,MATCH($A49,Leads!$A$2:$A$755,0)) -> ST JAMES | C49: =INDEX(Leads!$H$2:$H$755,MATCH($A49,Leads!$A$2:$A$755,0)) -> PORTLAND | D49: =INDEX(Leads!$J$2:$J$755,MATCH($A49,Leads!$A$2:$A$755,0)) -> 109 | E49: =INDEX(Leads!$D$2:$D$755,MATCH($A49,Leads!$A$2:$A$755,0)) -> Past 30-yr mark (verify) | F49: =INDEX(Leads!$N$2:$N$755,MATCH($A49,Leads!$A$2:$A$755,0)) -> 1994 | G49: =INDEX(Leads!$C$2:$C$755,MATCH($A49,Leads!$A$2:$A$755,0)) -> 71 | H49: =INDEX(Leads!$B$2:$B$755,MATCH($A49,Leads!$A$2:$A$755,0)) -> This week | I49: =INDEX(Leads!$E$2:$E$755,MATCH($A49,Leads!$A$2:$A$755,0)) -> ORA19940065
A50: 11 | B50: =INDEX(Leads!$F$2:$F$755,MATCH($A50,Leads!$A$2:$A$755,0)) -> STONEYBROOK | C50: =INDEX(Leads!$H$2:$H$755,MATCH($A50,Leads!$A$2:$A$755,0)) -> REDMOND | D50: =INDEX(Leads!$J$2:$J$755,MATCH($A50,Leads!$A$2:$A$755,0)) -> 50 | E50: =INDEX(Leads!$D$2:$D$755,MATCH($A50,Leads!$A$2:$A$755,0)) -> Past 30-yr mark (verify) | F50: =INDEX(Leads!$N$2:$N$755,MATCH($A50,Leads!$A$2:$A$755,0)) -> 1993 | G50: =INDEX(Leads!$C$2:$C$755,MATCH($A50,Leads!$A$2:$A$755,0)) -> 71 | H50: =INDEX(Leads!$B$2:$B$755,MATCH($A50,Leads!$A$2:$A$755,0)) -> This week | I50: =INDEX(Leads!$E$2:$E$755,MATCH($A50,Leads!$A$2:$A$755,0)) -> ORA19930062
A51: 12 | B51: =INDEX(Leads!$F$2:$F$755,MATCH($A51,Leads!$A$2:$A$755,0)) -> BERRY RIDGE APTS | C51: =INDEX(Leads!$H$2:$H$755,MATCH($A51,Leads!$A$2:$A$755,0)) -> GRESHAM | D51: =INDEX(Leads!$J$2:$J$755,MATCH($A51,Leads!$A$2:$A$755,0)) -> 248 | E51: =INDEX(Leads!$D$2:$D$755,MATCH($A51,Leads!$A$2:$A$755,0)) -> 30-yr mark: notice window (est.) | F51: =INDEX(Leads!$N$2:$N$755,MATCH($A51,Leads!$A$2:$A$755,0)) -> 1998 | G51: =INDEX(Leads!$C$2:$C$755,MATCH($A51,Leads!$A$2:$A$755,0)) -> 70 | H51: =INDEX(Leads!$B$2:$B$755,MATCH($A51,Leads!$A$2:$A$755,0)) -> This week | I51: =INDEX(Leads!$E$2:$E$755,MATCH($A51,Leads!$A$2:$A$755,0)) -> ORA19980020
... A79: 40 | B79: =INDEX(Leads!$F$2:$F$755,MATCH($A79,Leads!$A$2:$A$755,0)) -> JACOBS LANE | C79: =INDEX(Leads!$H$2:$H$755,MATCH($A79,Leads!$A$2:$A$755,0)) -> EUGENE | D79: =INDEX(Leads!$J$2:$J$755,MATCH($A79,Leads!$A$2:$A$755,0)) -> 63 | E79: =INDEX(Leads!$D$2:$D$755,MATCH($A79,Leads!$A$2:$A$755,0)) -> 30-yr mark: notice window (est.) | F79: =INDEX(Leads!$N$2:$N$755,MATCH($A79,Leads!$A$2:$A$755,0)) -> 1999 | G79: =INDEX(Leads!$C$2:$C$755,MATCH($A79,Leads!$A$2:$A$755,0)) -> 70 | H79: =INDEX(Leads!$B$2:$B$755,MATCH($A79,Leads!$A$2:$A$755,0)) -> This week | I79: =INDEX(Leads!$E$2:$E$755,MATCH($A79,Leads!$A$2:$A$755,0)) -> ORA19990075

Sheet Leads
A1: Rank | B1: Tier | C1: Score | D1: Play / lifecycle stage | E1: HUD ID | F1: Project name | G1: Address | H1: City | I1: ZIP | J1: Total units | K1: Low-income units | L1: Market-rate units | M1: HUD monitoring status | N1: Vintage (HUD ID year) | O1: Age (yrs) | P1: Year-15 close (est.) | Q1: 30-yr mark, federal minimum (est.) | R1: PuSH-CP size test (5+ units) | S1: Record flag | T1: Superseded? (Y) | U1: Verified expiration date | V1: Last transfer year | W1: Owner type | X1: Est. equity % | Y1: Distress flag (Y) | Z1: Other verified signals (0-3) | AA1: Years to expiration | AB1: Signals (count) | AC1: Stacking pts | AD1: Equity pts | AE1: Time pts | AF1: Tenure pts | AG1: Condition pts | AH1: Owner pts | AI1: Sort key | AJ1: Owner / GP entity | AK1: Contact | AL1: Outreach status | AM1: Notes / next step
A2: =RANK(AI2,$AI$2:$AI$755) -> 1 | B2: =IF(T2="Y","Superseded",IF(C2>=Scoring!$B$16,"Immediate",IF(C2>=Scoring!$B$17,"This week",IF(C2>=Scoring!$B$18,"Nurture","Low")))) -> Immediate | C2: =SUM(AC2:AH2) -> 77 | D2: =IF(T2="Y","Superseded record",IF(AND(U2<>"",AA2<0),"Expired (verified)",IF(AND(U2<>"",AA2<=Scoring!$B$5),"Expiring: notice window (verified)",IF(AND(U2<>"",AA2<=Scoring!$B$6),"Expiring: 10-yr horizon (verified)",IF(M2="No Longer Monitored","Out of program",IF(N2="","Unknown vintage",IF(N2<Scoring!$B$12,"Pre-1990, still listed",IF(AND(U2="",AA2<0),"Past 30-yr mark (verify)",IF(AND(U2="",AA2<=Scoring!$B$5),"30-yr mark: notice window (est.)",IF(AND(O2>=Scoring!$B$7,O2<=Scoring!$B$8),"Year-15 window",IF(O2>=Scoring!$B$9,"Recap window",IF(O2>=11,"Late compliance","Credit period")))))))))))) -> 30-yr mark: notice window (est.) | E2: ORA19990155 | F2: VILLAGE AT LOVEJOY FOUNTAIN | G2: 245 SW LINCOLN ST | H2: PORTLAND | I2: 97201 | J2: 198 | K2: 40 | L2: =IF(OR(J2="",K2=""),"",MAX(J2-K2,0)) -> 158 | M2: Not Indicated | N2: 1999 | O2: =IF(N2="","",Scoring!$B$4-N2) -> 27 | P2: =IF(N2="","",N2+14) -> 2013 | Q2: =IF(N2="","",IF(N2<Scoring!$B$12,"n/a (pre-1990)",N2+Scoring!$B$13)) -> 2028 | R2: =IF(J2="","Unknown",IF(J2>=5,"Yes","No (under 5 units)")) -> Yes | AA2: =IF(U2<>"",(U2-Scoring!$B$3)/365.25,IF(N2="","",IF(N2<Scoring!$B$12,"",(DATE(N2+Scoring!$B$13,12,31)-Scoring!$B$3)/365.25))) -> 2.2477755 | AB2: =IF(T2="Y",0,IF(OR(D2="Expired (verified)",D2="Expiring: notice window (verified)",D2="Expiring: 10-yr horizon (verified)",D2="Past 30-yr mark (verify)",D2="30-yr mark: notice window (est.)",D2="Year-15 window"),1,0)+IF(ISNUMBER(O2),IF(O2>=Scoring!$B$10,1,0),0)+IF(AND(ISNUMBER(L2),ISNUMBER(J2)),IF(J2>0,IF(L2/J2>=Scoring!$B$11,1,0),0),0)+IF(ISNUMBER(Z2),MIN(Z2,3),0)) -> 3 | AC2: =IF(AB2>=3,Scoring!$C$24,IF(AB2=2,Scoring!$C$23,IF(AB2=1,Scoring!$C$22,0))) -> 25 | AD2: =IF(T2="Y",0,IF(ISNUMBER(X2),IF(X2>0.7,Scoring!$C$25,IF(X2>=0.5,Scoring!$C$26,IF(X2>=0.3,Scoring!$C$27,Scoring!$C$28))),Scoring!$C$29)) -> 10 | AE2: =IF(D2="Expiring: notice window (verified)",Scoring!$C$30,IF(OR(D2="Expired (verified)",D2="30-yr mark: notice window (est.)",D2="Year-15 window"),Scoring!$C$31,IF(D2="Expiring: 10-yr horizon (verified)",Scoring!$C$32,IF(D2="Past 30-yr mark (verify)",Scoring!$C$33,IF(OR(D2="Credit period",D2="Superseded record"),Scoring!$C$35,Scoring!$C$34))))) -> 14 | AF2: =IF(T2="Y",0,IF(ISNUMBER(V2),IF(Scoring!$B$4-V2>15,Scoring!$C$36,IF(Scoring!$B$4-V2>=10,Scoring!$C$37,IF(Scoring!$B$4-V2>=5,Scoring!$C$38,Scoring!$C$39))),IF(OR(N2="",D2="Out of program"),Scoring!$C$40,IF(O2>15,Scoring!$C$36,IF(O2>=10,Scoring!$C$37,IF(O2>=5,Scoring!$C$38,Scoring!$C$39)))))) -> 15 | AG2: =IF(T2="Y",0,IF(Y2="Y",Scoring!$C$41,IF(ISNUMBER(O2),IF(O2>=25,Scoring!$C$42,IF(O2>=15,Scoring!$C$43,Scoring!$C$44)),Scoring!$C$44))) -> 8 | AH2: =IF(T2="Y",0,IF(W2="",Scoring!$C$49,IFERROR(VLOOKUP(W2,Scoring!$B$45:$C$48,2,FALSE()),Scoring!$C$49))) -> 5 | AI2: =C2+IF(ISNUMBER(J2),J2,0)/100000+(10000-ROW())/1000000000 -> 77.00199
A3: =RANK(AI3,$AI$2:$AI$755) -> 2 | B3: =IF(T3="Y","Superseded",IF(C3>=Scoring!$B$16,"Immediate",IF(C3>=Scoring!$B$17,"This week",IF(C3>=Scoring!$B$18,"Nurture","Low")))) -> Immediate | C3: =SUM(AC3:AH3) -> 77 | D3: =IF(T3="Y","Superseded record",IF(AND(U3<>"",AA3<0),"Expired (verified)",IF(AND(U3<>"",AA3<=Scoring!$B$5),"Expiring: notice window (verified)",IF(AND(U3<>"",AA3<=Scoring!$B$6),"Expiring: 10-yr horizon (verified)",IF(M3="No Longer Monitored","Out of program",IF(N3="","Unknown vintage",IF(N3<Scoring!$B$12,"Pre-1990, still listed",IF(AND(U3="",AA3<0),"Past 30-yr mark (verify)",IF(AND(U3="",AA3<=Scoring!$B$5),"30-yr mark: notice window (est.)",IF(AND(O3>=Scoring!$B$7,O3<=Scoring!$B$8),"Year-15 window",IF(O3>=Scoring!$B$9,"Recap window",IF(O3>=11,"Late compliance","Credit period")))))))))))) -> 30-yr mark: notice window (est.) | E3: ORA19990140 | F3: ST ANTHONY VILLAGE | G3: 3560 SE 79TH AVE | H3: PORTLAND | I3: 97206 | J3: 128 | K3: 106 | L3: =IF(OR(J3="",K3=""),"",MAX(J3-K3,0)) -> 22 | M3: Not Indicated | N3: 1999 | O3: =IF(N3="","",Scoring!$B$4-N3) -> 27 | P3: =IF(N3="","",N3+14) -> 2013 | Q3: =IF(N3="","",IF(N3<Scoring!$B$12,"n/a (pre-1990)",N3+Scoring!$B$13)) -> 2028 | R3: =IF(J3="","Unknown",IF(J3>=5,"Yes","No (under 5 units)")) -> Yes | AA3: =IF(U3<>"",(U3-Scoring!$B$3)/365.25,IF(N3="","",IF(N3<Scoring!$B$12,"",(DATE(N3+Scoring!$B$13,12,31)-Scoring!$B$3)/365.25))) -> 2.2477755 | AB3: =IF(T3="Y",0,IF(OR(D3="Expired (verified)",D3="Expiring: notice window (verified)",D3="Expiring: 10-yr horizon (verified)",D3="Past 30-yr mark (verify)",D3="30-yr mark: notice window (est.)",D3="Year-15 window"),1,0)+IF(ISNUMBER(O3),IF(O3>=Scoring!$B$10,1,0),0)+IF(AND(ISNUMBER(L3),ISNUMBER(J3)),IF(J3>0,IF(L3/J3>=Scoring!$B$11,1,0),0),0)+IF(ISNUMBER(Z3),MIN(Z3,3),0)) -> 3 | AC3: =IF(AB3>=3,Scoring!$C$24,IF(AB3=2,Scoring!$C$23,IF(AB3=1,Scoring!$C$22,0))) -> 25 | AD3: =IF(T3="Y",0,IF(ISNUMBER(X3),IF(X3>0.7,Scoring!$C$25,IF(X3>=0.5,Scoring!$C$26,IF(X3>=0.3,Scoring!$C$27,Scoring!$C$28))),Scoring!$C$29)) -> 10 | AE3: =IF(D3="Expiring: notice window (verified)",Scoring!$C$30,IF(OR(D3="Expired (verified)",D3="30-yr mark: notice window (est.)",D3="Year-15 window"),Scoring!$C$31,IF(D3="Expiring: 10-yr horizon (verified)",Scoring!$C$32,IF(D3="Past 30-yr mark (verify)",Scoring!$C$33,IF(OR(D3="Credit period",D3="Superseded record"),Scoring!$C$35,Scoring!$C$34))))) -> 14 | AF3: =IF(T3="Y",0,IF(ISNUMBER(V3),IF(Scoring!$B$4-V3>15,Scoring!$C$36,IF(Scoring!$B$4-V3>=10,Scoring!$C$37,IF(Scoring!$B$4-V3>=5,Scoring!$C$38,Scoring!$C$39))),IF(OR(N3="",D3="Out of program"),Scoring!$C$40,IF(O3>15,Scoring!$C$36,IF(O3>=10,Scoring!$C$37,IF(O3>=5,Scoring!$C$38,Scoring!$C$39)))))) -> 15 | AG3: =IF(T3="Y",0,IF(Y3="Y",Scoring!$C$41,IF(ISNUMBER(O3),IF(O3>=25,Scoring!$C$42,IF(O3>=15,Scoring!$C$43,Scoring!$C$44)),Scoring!$C$44))) -> 8 | AH3: =IF(T3="Y",0,IF(W3="",Scoring!$C$49,IFERROR(VLOOKUP(W3,Scoring!$B$45:$C$48,2,FALSE()),Scoring!$C$49))) -> 5 | AI3: =C3+IF(ISNUMBER(J3),J3,0)/100000+(10000-ROW())/1000000000 -> 77.00129
A4: =RANK(AI4,$AI$2:$AI$755) -> 3 | B4: =IF(T4="Y","Superseded",IF(C4>=Scoring!$B$16,"Immediate",IF(C4>=Scoring!$B$17,"This week",IF(C4>=Scoring!$B$18,"Nurture","Low")))) -> Immediate | C4: =SUM(AC4:AH4) -> 77 | D4: =IF(T4="Y","Superseded record",IF(AND(U4<>"",AA4<0),"Expired (verified)",IF(AND(U4<>"",AA4<=Scoring!$B$5),"Expiring: notice window (verified)",IF(AND(U4<>"",AA4<=Scoring!$B$6),"Expiring: 10-yr horizon (verified)",IF(M4="No Longer Monitored","Out of program",IF(N4="","Unknown vintage",IF(N4<Scoring!$B$12,"Pre-1990, still listed",IF(AND(U4="",AA4<0),"Past 30-yr mark (verify)",IF(AND(U4="",AA4<=Scoring!$B$5),"30-yr mark: notice window (est.)",IF(AND(O4>=Scoring!$B$7,O4<=Scoring!$B$8),"Year-15 window",IF(O4>=Scoring!$B$9,"Recap window",IF(O4>=11,"Late compliance","Credit period")))))))))))) -> 30-yr mark: notice window (est.) | E4: ORA19970141 | F4: PARKWAY VILLAGE APTS - SALEM | G4: 3143 SEVENTH PL NE | H4: SALEM | I4: 97303 | J4: 124 | K4: 100 | L4: =IF(OR(J4="",K4=""),"",MAX(J4-K4,0)) -> 24 | M4: Not Indicated | N4: 1997 | O4: =IF(N4="","",Scoring!$B$4-N4) -> 29 | P4: =IF(N4="","",N4+14) -> 2011 | Q4: =IF(N4="","",IF(N4<Scoring!$B$12,"n/a (pre-1990)",N4+Scoring!$B$13)) -> 2026 | R4: =IF(J4="","Unknown",IF(J4>=5,"Yes","No (under 5 units)")) -> Yes | AA4: =IF(U4<>"",(U4-Scoring!$B$3)/365.25,IF(N4="","",IF(N4<Scoring!$B$12,"",(DATE(N4+Scoring!$B$13,12,31)-Scoring!$B$3)/365.25))) -> 0.24640657 | AB4: =IF(T4="Y",0,IF(OR(D4="Expired (verified)",D4="Expiring: notice window (verified)",D4="Expiring: 10-yr horizon (verified)",D4="Past 30-yr mark (verify)",D4="30-yr mark: notice window (est.)",D4="Year-15 window"),1,0)+IF(ISNUMBER(O4),IF(O4>=Scoring!$B$10,1,0),0)+IF(AND(ISNUMBER(L4),ISNUMBER(J4)),IF(J4>0,IF(L4/J4>=Scoring!$B$11,1,0),0),0)+IF(ISNUMBER(Z4),MIN(Z4,3),0)) -> 3 | AC4: =IF(AB4>=3,Scoring!$C$24,IF(AB4=2,Scoring!$C$23,IF(AB4=1,Scoring!$C$22,0))) -> 25 | AD4: =IF(T4="Y",0,IF(ISNUMBER(X4),IF(X4>0.7,Scoring!$C$25,IF(X4>=0.5,Scoring!$C$26,IF(X4>=0.3,Scoring!$C$27,Scoring!$C$28))),Scoring!$C$29)) -> 10 | AE4: =IF(D4="Expiring: notice window (verified)",Scoring!$C$30,IF(OR(D4="Expired (verified)",D4="30-yr mark: notice window (est.)",D4="Year-15 window"),Scoring!$C$31,IF(D4="Expiring: 10-yr horizon (verified)",Scoring!$C$32,IF(D4="Past 30-yr mark (verify)",Scoring!$C$33,IF(OR(D4="Credit period",D4="Superseded record"),Scoring!$C$35,Scoring!$C$34))))) -> 14 | AF4: =IF(T4="Y",0,IF(ISNUMBER(V4),IF(Scoring!$B$4-V4>15,Scoring!$C$36,IF(Scoring!$B$4-V4>=10,Scoring!$C$37,IF(Scoring!$B$4-V4>=5,Scoring!$C$38,Scoring!$C$39))),IF(OR(N4="",D4="Out of program"),Scoring!$C$40,IF(O4>15,Scoring!$C$36,IF(O4>=10,Scoring!$C$37,IF(O4>=5,Scoring!$C$38,Scoring!$C$39)))))) -> 15 | AG4: =IF(T4="Y",0,IF(Y4="Y",Scoring!$C$41,IF(ISNUMBER(O4),IF(O4>=25,Scoring!$C$42,IF(O4>=15,Scoring!$C$43,Scoring!$C$44)),Scoring!$C$44))) -> 8 | AH4: =IF(T4="Y",0,IF(W4="",Scoring!$C$49,IFERROR(VLOOKUP(W4,Scoring!$B$45:$C$48,2,FALSE()),Scoring!$C$49))) -> 5 | AI4: =C4+IF(ISNUMBER(J4),J4,0)/100000+(10000-ROW())/1000000000 -> 77.00125
A5: =RANK(AI5,$AI$2:$AI$755) -> 4 | B5: =IF(T5="Y","Superseded",IF(C5>=Scoring!$B$16,"Immediate",IF(C5>=Scoring!$B$17,"This week",IF(C5>=Scoring!$B$18,"Nurture","Low")))) -> Immediate | C5: =SUM(AC5:AH5) -> 77 | D5: =IF(T5="Y","Superseded record",IF(AND(U5<>"",AA5<0),"Expired (verified)",IF(AND(U5<>"",AA5<=Scoring!$B$5),"Expiring: notice window (verified)",IF(AND(U5<>"",AA5<=Scoring!$B$6),"Expiring: 10-yr horizon (verified)",IF(M5="No Longer Monitored","Out of program",IF(N5="","Unknown vintage",IF(N5<Scoring!$B$12,"Pre-1990, still listed",IF(AND(U5="",AA5<0),"Past 30-yr mark (verify)",IF(AND(U5="",AA5<=Scoring!$B$5),"30-yr mark: notice window (est.)",IF(AND(O5>=Scoring!$B$7,O5<=Scoring!$B$8),"Year-15 window",IF(O5>=Scoring!$B$9,"Recap window",IF(O5>=11,"Late compliance","Credit period")))))))))))) -> 30-yr mark: notice window (est.) | E5: ORA19990055 | F5: FIFTH AVE COURTS | G5: 733 SW SECOND AVE | H5: PORTLAND | I5: 97204 | J5: 96 | K5: 48 | L5: =IF(OR(J5="",K5=""),"",MAX(J5-K5,0)) -> 48 | M5: Not Indicated | N5: 1999 | O5: =IF(N5="","",Scoring!$B$4-N5) -> 27 | P5: =IF(N5="","",N5+14) -> 2013 | Q5: =IF(N5="","",IF(N5<Scoring!$B$12,"n/a (pre-1990)",N5+Scoring!$B$13)) -> 2028 | R5: =IF(J5="","Unknown",IF(J5>=5,"Yes","No (under 5 units)")) -> Yes | AA5: =IF(U5<>"",(U5-Scoring!$B$3)/365.25,IF(N5="","",IF(N5<Scoring!$B$12,"",(DATE(N5+Scoring!$B$13,12,31)-Scoring!$B$3)/365.25))) -> 2.2477755 | AB5: =IF(T5="Y",0,IF(OR(D5="Expired (verified)",D5="Expiring: notice window (verified)",D5="Expiring: 10-yr horizon (verified)",D5="Past 30-yr mark (verify)",D5="30-yr mark: notice window (est.)",D5="Year-15 window"),1,0)+IF(ISNUMBER(O5),IF(O5>=Scoring!$B$10,1,0),0)+IF(AND(ISNUMBER(L5),ISNUMBER(J5)),IF(J5>0,IF(L5/J5>=Scoring!$B$11,1,0),0),0)+IF(ISNUMBER(Z5),MIN(Z5,3),0)) -> 3 | AC5: =IF(AB5>=3,Scoring!$C$24,IF(AB5=2,Scoring!$C$23,IF(AB5=1,Scoring!$C$22,0))) -> 25 | AD5: =IF(T5="Y",0,IF(ISNUMBER(X5),IF(X5>0.7,Scoring!$C$25,IF(X5>=0.5,Scoring!$C$26,IF(X5>=0.3,Scoring!$C$27,Scoring!$C$28))),Scoring!$C$29)) -> 10 | AE5: =IF(D5="Expiring: notice window (verified)",Scoring!$C$30,IF(OR(D5="Expired (verified)",D5="30-yr mark: notice window (est.)",D5="Year-15 window"),Scoring!$C$31,IF(D5="Expiring: 10-yr horizon (verified)",Scoring!$C$32,IF(D5="Past 30-yr mark (verify)",Scoring!$C$33,IF(OR(D5="Credit period",D5="Superseded record"),Scoring!$C$35,Scoring!$C$34))))) -> 14 | AF5: =IF(T5="Y",0,IF(ISNUMBER(V5),IF(Scoring!$B$4-V5>15,Scoring!$C$36,IF(Scoring!$B$4-V5>=10,Scoring!$C$37,IF(Scoring!$B$4-V5>=5,Scoring!$C$38,Scoring!$C$39))),IF(OR(N5="",D5="Out of program"),Scoring!$C$40,IF(O5>15,Scoring!$C$36,IF(O5>=10,Scoring!$C$37,IF(O5>=5,Scoring!$C$38,Scoring!$C$39)))))) -> 15 | AG5: =IF(T5="Y",0,IF(Y5="Y",Scoring!$C$41,IF(ISNUMBER(O5),IF(O5>=25,Scoring!$C$42,IF(O5>=15,Scoring!$C$43,Scoring!$C$44)),Scoring!$C$44))) -> 8 | AH5: =IF(T5="Y",0,IF(W5="",Scoring!$C$49,IFERROR(VLOOKUP(W5,Scoring!$B$45:$C$48,2,FALSE()),Scoring!$C$49))) -> 5 | AI5: =C5+IF(ISNUMBER(J5),J5,0)/100000+(10000-ROW())/1000000000 -> 77.00097
A6: =RANK(AI6,$AI$2:$AI$755) -> 5 | B6: =IF(T6="Y","Superseded",IF(C6>=Scoring!$B$16,"Immediate",IF(C6>=Scoring!$B$17,"This week",IF(C6>=Scoring!$B$18,"Nurture","Low")))) -> Immediate | C6: =SUM(AC6:AH6) -> 77 | D6: =IF(T6="Y","Superseded record",IF(AND(U6<>"",AA6<0),"Expired (verified)",IF(AND(U6<>"",AA6<=Scoring!$B$5),"Expiring: notice window (verified)",IF(AND(U6<>"",AA6<=Scoring!$B$6),"Expiring: 10-yr horizon (verified)",IF(M6="No Longer Monitored","Out of program",IF(N6="","Unknown vintage",IF(N6<Scoring!$B$12,"Pre-1990, still listed",IF(AND(U6="",AA6<0),"Past 30-yr mark (verify)",IF(AND(U6="",AA6<=Scoring!$B$5),"30-yr mark: notice window (est.)",IF(AND(O6>=Scoring!$B$7,O6<=Scoring!$B$8),"Year-15 window",IF(O6>=Scoring!$B$9,"Recap window",IF(O6>=11,"Late compliance","Credit period")))))))))))) -> 30-yr mark: notice window (est.) | E6: ORA19970035 | F6: FLOYD LIGHT APTS | G6: 1031 SE 106TH AVE | H6: PORTLAND | I6: 97216 | J6: 51 | K6: 23 | L6: =IF(OR(J6="",K6=""),"",MAX(J6-K6,0)) -> 28 | M6: Not Indicated | N6: 1997 | O6: =IF(N6="","",Scoring!$B$4-N6) -> 29 | P6: =IF(N6="","",N6+14) -> 2011 | Q6: =IF(N6="","",IF(N6<Scoring!$B$12,"n/a (pre-1990)",N6+Scoring!$B$13)) -> 2026 | R6: =IF(J6="","Unknown",IF(J6>=5,"Yes","No (under 5 units)")) -> Yes | AA6: =IF(U6<>"",(U6-Scoring!$B$3)/365.25,IF(N6="","",IF(N6<Scoring!$B$12,"",(DATE(N6+Scoring!$B$13,12,31)-Scoring!$B$3)/365.25))) -> 0.24640657 | AB6: =IF(T6="Y",0,IF(OR(D6="Expired (verified)",D6="Expiring: notice window (verified)",D6="Expiring: 10-yr horizon (verified)",D6="Past 30-yr mark (verify)",D6="30-yr mark: notice window (est.)",D6="Year-15 window"),1,0)+IF(ISNUMBER(O6),IF(O6>=Scoring!$B$10,1,0),0)+IF(AND(ISNUMBER(L6),ISNUMBER(J6)),IF(J6>0,IF(L6/J6>=Scoring!$B$11,1,0),0),0)+IF(ISNUMBER(Z6),MIN(Z6,3),0)) -> 3 | AC6: =IF(AB6>=3,Scoring!$C$24,IF(AB6=2,Scoring!$C$23,IF(AB6=1,Scoring!$C$22,0))) -> 25 | AD6: =IF(T6="Y",0,IF(ISNUMBER(X6),IF(X6>0.7,Scoring!$C$25,IF(X6>=0.5,Scoring!$C$26,IF(X6>=0.3,Scoring!$C$27,Scoring!$C$28))),Scoring!$C$29)) -> 10 | AE6: =IF(D6="Expiring: notice window (verified)",Scoring!$C$30,IF(OR(D6="Expired (verified)",D6="30-yr mark: notice window (est.)",D6="Year-15 window"),Scoring!$C$31,IF(D6="Expiring: 10-yr horizon (verified)",Scoring!$C$32,IF(D6="Past 30-yr mark (verify)",Scoring!$C$33,IF(OR(D6="Credit period",D6="Superseded record"),Scoring!$C$35,Scoring!$C$34))))) -> 14 | AF6: =IF(T6="Y",0,IF(ISNUMBER(V6),IF(Scoring!$B$4-V6>15,Scoring!$C$36,IF(Scoring!$B$4-V6>=10,Scoring!$C$37,IF(Scoring!$B$4-V6>=5,Scoring!$C$38,Scoring!$C$39))),IF(OR(N6="",D6="Out of program"),Scoring!$C$40,IF(O6>15,Scoring!$C$36,IF(O6>=10,Scoring!$C$37,IF(O6>=5,Scoring!$C$38,Scoring!$C$39)))))) -> 15 | AG6: =IF(T6="Y",0,IF(Y6="Y",Scoring!$C$41,IF(ISNUMBER(O6),IF(O6>=25,Scoring!$C$42,IF(O6>=15,Scoring!$C$43,Scoring!$C$44)),Scoring!$C$44))) -> 8 | AH6: =IF(T6="Y",0,IF(W6="",Scoring!$C$49,IFERROR(VLOOKUP(W6,Scoring!$B$45:$C$48,2,FALSE()),Scoring!$C$49))) -> 5 | AI6: =C6+IF(ISNUMBER(J6),J6,0)/100000+(10000-ROW())/1000000000 -> 77.00052
A7: =RANK(AI7,$AI$2:$AI$755) -> 6 | B7: =IF(T7="Y","Superseded",IF(C7>=Scoring!$B$16,"Immediate",IF(C7>=Scoring!$B$17,"This week",IF(C7>=Scoring!$B$18,"Nurture","Low")))) -> Immediate | C7: =SUM(AC7:AH7) -> 77 | D7: =IF(T7="Y","Superseded record",IF(AND(U7<>"",AA7<0),"Expired (verified)",IF(AND(U7<>"",AA7<=Scoring!$B$5),"Expiring: notice window (verified)",IF(AND(U7<>"",AA7<=Scoring!$B$6),"Expiring: 10-yr horizon (verified)",IF(M7="No Longer Monitored","Out of program",IF(N7="","Unknown vintage",IF(N7<Scoring!$B$12,"Pre-1990, still listed",IF(AND(U7="",AA7<0),"Past 30-yr mark (verify)",IF(AND(U7="",AA7<=Scoring!$B$5),"30-yr mark: notice window (est.)",IF(AND(O7>=Scoring!$B$7,O7<=Scoring!$B$8),"Year-15 window",IF(O7>=Scoring!$B$9,"Recap window",IF(O7>=11,"Late compliance","Credit period")))))))))))) -> 30-yr mark: notice window (est.) | E7: ORA19990040 | F7: COLUMBIA VIEW APTS | G7: 1695 OAK ST | H7: HOOD RIVER | I7: 97031 | J7: 48 | K7: 40 | L7: =IF(OR(J7="",K7=""),"",MAX(J7-K7,0)) -> 8 | M7: Not Indicated | N7: 1999 | O7: =IF(N7="","",Scoring!$B$4-N7) -> 27 | P7: =IF(N7="","",N7+14) -> 2013 | Q7: =IF(N7="","",IF(N7<Scoring!$B$12,"n/a (pre-1990)",N7+Scoring!$B$13)) -> 2028 | R7: =IF(J7="","Unknown",IF(J7>=5,"Yes","No (under 5 units)")) -> Yes | AA7: =IF(U7<>"",(U7-Scoring!$B$3)/365.25,IF(N7="","",IF(N7<Scoring!$B$12,"",(DATE(N7+Scoring!$B$13,12,31)-Scoring!$B$3)/365.25))) -> 2.2477755 | AB7: =IF(T7="Y",0,IF(OR(D7="Expired (verified)",D7="Expiring: notice window (verified)",D7="Expiring: 10-yr horizon (verified)",D7="Past 30-yr mark (verify)",D7="30-yr mark: notice window (est.)",D7="Year-15 window"),1,0)+IF(ISNUMBER(O7),IF(O7>=Scoring!$B$10,1,0),0)+IF(AND(ISNUMBER(L7),ISNUMBER(J7)),IF(J7>0,IF(L7/J7>=Scoring!$B$11,1,0),0),0)+IF(ISNUMBER(Z7),MIN(Z7,3),0)) -> 3 | AC7: =IF(AB7>=3,Scoring!$C$24,IF(AB7=2,Scoring!$C$23,IF(AB7=1,Scoring!$C$22,0))) -> 25 | AD7: =IF(T7="Y",0,IF(ISNUMBER(X7),IF(X7>0.7,Scoring!$C$25,IF(X7>=0.5,Scoring!$C$26,IF(X7>=0.3,Scoring!$C$27,Scoring!$C$28))),Scoring!$C$29)) -> 10 | AE7: =IF(D7="Expiring: notice window (verified)",Scoring!$C$30,IF(OR(D7="Expired (verified)",D7="30-yr mark: notice window (est.)",D7="Year-15 window"),Scoring!$C$31,IF(D7="Expiring: 10-yr horizon (verified)",Scoring!$C$32,IF(D7="Past 30-yr mark (verify)",Scoring!$C$33,IF(OR(D7="Credit period",D7="Superseded record"),Scoring!$C$35,Scoring!$C$34))))) -> 14 | AF7: =IF(T7="Y",0,IF(ISNUMBER(V7),IF(Scoring!$B$4-V7>15,Scoring!$C$36,IF(Scoring!$B$4-V7>=10,Scoring!$C$37,IF(Scoring!$B$4-V7>=5,Scoring!$C$38,Scoring!$C$39))),IF(OR(N7="",D7="Out of program"),Scoring!$C$40,IF(O7>15,Scoring!$C$36,IF(O7>=10,Scoring!$C$37,IF(O7>=5,Scoring!$C$38,Scoring!$C$39)))))) -> 15 | AG7: =IF(T7="Y",0,IF(Y7="Y",Scoring!$C$41,IF(ISNUMBER(O7),IF(O7>=25,Scoring!$C$42,IF(O7>=15,Scoring!$C$43,Scoring!$C$44)),Scoring!$C$44))) -> 8 | AH7: =IF(T7="Y",0,IF(W7="",Scoring!$C$49,IFERROR(VLOOKUP(W7,Scoring!$B$45:$C$48,2,FALSE()),Scoring!$C$49))) -> 5 | AI7: =C7+IF(ISNUMBER(J7),J7,0)/100000+(10000-ROW())/1000000000 -> 77.00049
A8: =RANK(AI8,$AI$2:$AI$755) -> 7 | B8: =IF(T8="Y","Superseded",IF(C8>=Scoring!$B$16,"Immediate",IF(C8>=Scoring!$B$17,"This week",IF(C8>=Scoring!$B$18,"Nurture","Low")))) -> Immediate | C8: =SUM(AC8:AH8) -> 77 | D8: =IF(T8="Y","Superseded record",IF(AND(U8<>"",AA8<0),"Expired (verified)",IF(AND(U8<>"",AA8<=Scoring!$B$5),"Expiring: notice window (verified)",IF(AND(U8<>"",AA8<=Scoring!$B$6),"Expiring: 10-yr horizon (verified)",IF(M8="No Longer Monitored","Out of program",IF(N8="","Unknown vintage",IF(N8<Scoring!$B$12,"Pre-1990, still listed",IF(AND(U8="",AA8<0),"Past 30-yr mark (verify)",IF(AND(U8="",AA8<=Scoring!$B$5),"30-yr mark: notice window (est.)",IF(AND(O8>=Scoring!$B$7,O8<=Scoring!$B$8),"Year-15 window",IF(O8>=Scoring!$B$9,"Recap window",IF(O8>=11,"Late compliance","Credit period")))))))))))) -> 30-yr mark: notice window (est.) | E8: ORA19990005 | F8: AMES CREEK COURT | G8: 1815 AMES CREEK RD | H8: SWEET HOME | I8: 97386 | J8: 31 | K8: 16 | L8: =IF(OR(J8="",K8=""),"",MAX(J8-K8,0)) -> 15 | M8: Not Indicated | N8: 1999 | O8: =IF(N8="","",Scoring!$B$4-N8) -> 27 | P8: =IF(N8="","",N8+14) -> 2013 | Q8: =IF(N8="","",IF(N8<Scoring!$B$12,"n/a (pre-1990)",N8+Scoring!$B$13)) -> 2028 | R8: =IF(J8="","Unknown",IF(J8>=5,"Yes","No (under 5 units)")) -> Yes | AA8: =IF(U8<>"",(U8-Scoring!$B$3)/365.25,IF(N8="","",IF(N8<Scoring!$B$12,"",(DATE(N8+Scoring!$B$13,12,31)-Scoring!$B$3)/365.25))) -> 2.2477755 | AB8: =IF(T8="Y",0,IF(OR(D8="Expired (verified)",D8="Expiring: notice window (verified)",D8="Expiring: 10-yr horizon (verified)",D8="Past 30-yr mark (verify)",D8="30-yr mark: notice window (est.)",D8="Year-15 window"),1,0)+IF(ISNUMBER(O8),IF(O8>=Scoring!$B$10,1,0),0)+IF(AND(ISNUMBER(L8),ISNUMBER(J8)),IF(J8>0,IF(L8/J8>=Scoring!$B$11,1,0),0),0)+IF(ISNUMBER(Z8),MIN(Z8,3),0)) -> 3 | AC8: =IF(AB8>=3,Scoring!$C$24,IF(AB8=2,Scoring!$C$23,IF(AB8=1,Scoring!$C$22,0))) -> 25 | AD8: =IF(T8="Y",0,IF(ISNUMBER(X8),IF(X8>0.7,Scoring!$C$25,IF(X8>=0.5,Scoring!$C$26,IF(X8>=0.3,Scoring!$C$27,Scoring!$C$28))),Scoring!$C$29)) -> 10 | AE8: =IF(D8="Expiring: notice window (verified)",Scoring!$C$30,IF(OR(D8="Expired (verified)",D8="30-yr mark: notice window (est.)",D8="Year-15 window"),Scoring!$C$31,IF(D8="Expiring: 10-yr horizon (verified)",Scoring!$C$32,IF(D8="Past 30-yr mark (verify)",Scoring!$C$33,IF(OR(D8="Credit period",D8="Superseded record"),Scoring!$C$35,Scoring!$C$34))))) -> 14 | AF8: =IF(T8="Y",0,IF(ISNUMBER(V8),IF(Scoring!$B$4-V8>15,Scoring!$C$36,IF(Scoring!$B$4-V8>=10,Scoring!$C$37,IF(Scoring!$B$4-V8>=5,Scoring!$C$38,Scoring!$C$39))),IF(OR(N8="",D8="Out of program"),Scoring!$C$40,IF(O8>15,Scoring!$C$36,IF(O8>=10,Scoring!$C$37,IF(O8>=5,Scoring!$C$38,Scoring!$C$39)))))) -> 15 | AG8: =IF(T8="Y",0,IF(Y8="Y",Scoring!$C$41,IF(ISNUMBER(O8),IF(O8>=25,Scoring!$C$42,IF(O8>=15,Scoring!$C$43,Scoring!$C$44)),Scoring!$C$44))) -> 8 | AH8: =IF(T8="Y",0,IF(W8="",Scoring!$C$49,IFERROR(VLOOKUP(W8,Scoring!$B$45:$C$48,2,FALSE()),Scoring!$C$49))) -> 5 | AI8: =C8+IF(ISNUMBER(J8),J8,0)/100000+(10000-ROW())/1000000000 -> 77.00032
A9: =RANK(AI9,$AI$2:$AI$755) -> 8 | B9: =IF(T9="Y","Superseded",IF(C9>=Scoring!$B$16,"Immediate",IF(C9>=Scoring!$B$17,"This week",IF(C9>=Scoring!$B$18,"Nurture","Low")))) -> Immediate | C9: =SUM(AC9:AH9) -> 77 | D9: =IF(T9="Y","Superseded record",IF(AND(U9<>"",AA9<0),"Expired (verified)",IF(AND(U9<>"",AA9<=Scoring!$B$5),"Expiring: notice window (verified)",IF(AND(U9<>"",AA9<=Scoring!$B$6),"Expiring: 10-yr horizon (verified)",IF(M9="No Longer Monitored","Out of program",IF(N9="","Unknown vintage",IF(N9<Scoring!$B$12,"Pre-1990, still listed",IF(AND(U9="",AA9<0),"Past 30-yr mark (verify)",IF(AND(U9="",AA9<=Scoring!$B$5),"30-yr mark: notice window (est.)",IF(AND(O9>=Scoring!$B$7,O9<=Scoring!$B$8),"Year-15 window",IF(O9>=Scoring!$B$9,"Recap window",IF(O9>=11,"Late compliance","Credit period")))))))))))) -> 30-yr mark: notice window (est.) | E9: ORA19990130 | F9: RONDEL COURT | G9: 180 FENTON AVE | H9: MOLALLA | I9: 97038 | J9: 30 | K9: 27 | L9: =IF(OR(J9="",K9=""),"",MAX(J9-K9,0)) -> 3 | M9: Not Indicated | N9: 1999 | O9: =IF(N9="","",Scoring!$B$4-N9) -> 27 | P9: =IF(N9="","",N9+14) -> 2013 | Q9: =IF(N9="","",IF(N9<Scoring!$B$12,"n/a (pre-1990)",N9+Scoring!$B$13)) -> 2028 | R9: =IF(J9="","Unknown",IF(J9>=5,"Yes","No (under 5 units)")) -> Yes | AA9: =IF(U9<>"",(U9-Scoring!$B$3)/365.25,IF(N9="","",IF(N9<Scoring!$B$12,"",(DATE(N9+Scoring!$B$13,12,31)-Scoring!$B$3)/365.25))) -> 2.2477755 | AB9: =IF(T9="Y",0,IF(OR(D9="Expired (verified)",D9="Expiring: notice window (verified)",D9="Expiring: 10-yr horizon (verified)",D9="Past 30-yr mark (verify)",D9="30-yr mark: notice window (est.)",D9="Year-15 window"),1,0)+IF(ISNUMBER(O9),IF(O9>=Scoring!$B$10,1,0),0)+IF(AND(ISNUMBER(L9),ISNUMBER(J9)),IF(J9>0,IF(L9/J9>=Scoring!$B$11,1,0),0),0)+IF(ISNUMBER(Z9),MIN(Z9,3),0)) -> 3 | AC9: =IF(AB9>=3,Scoring!$C$24,IF(AB9=2,Scoring!$C$23,IF(AB9=1,Scoring!$C$22,0))) -> 25 | AD9: =IF(T9="Y",0,IF(ISNUMBER(X9),IF(X9>0.7,Scoring!$C$25,IF(X9>=0.5,Scoring!$C$26,IF(X9>=0.3,Scoring!$C$27,Scoring!$C$28))),Scoring!$C$29)) -> 10 | AE9: =IF(D9="Expiring: notice window (verified)",Scoring!$C$30,IF(OR(D9="Expired (verified)",D9="30-yr mark: notice window (est.)",D9="Year-15 window"),Scoring!$C$31,IF(D9="Expiring: 10-yr horizon (verified)",Scoring!$C$32,IF(D9="Past 30-yr mark (verify)",Scoring!$C$33,IF(OR(D9="Credit period",D9="Superseded record"),Scoring!$C$35,Scoring!$C$34))))) -> 14 | AF9: =IF(T9="Y",0,IF(ISNUMBER(V9),IF(Scoring!$B$4-V9>15,Scoring!$C$36,IF(Scoring!$B$4-V9>=10,Scoring!$C$37,IF(Scoring!$B$4-V9>=5,Scoring!$C$38,Scoring!$C$39))),IF(OR(N9="",D9="Out of program"),Scoring!$C$40,IF(O9>15,Scoring!$C$36,IF(O9>=10,Scoring!$C$37,IF(O9>=5,Scoring!$C$38,Scoring!$C$39)))))) -> 15 | AG9: =IF(T9="Y",0,IF(Y9="Y",Scoring!$C$41,IF(ISNUMBER(O9),IF(O9>=25,Scoring!$C$42,IF(O9>=15,Scoring!$C$43,Scoring!$C$44)),Scoring!$C$44))) -> 8 | AH9: =IF(T9="Y",0,IF(W9="",Scoring!$C$49,IFERROR(VLOOKUP(W9,Scoring!$B$45:$C$48,2,FALSE()),Scoring!$C$49))) -> 5 | AI9: =C9+IF(ISNUMBER(J9),J9,0)/100000+(10000-ROW())/1000000000 -> 77.00031
A10: =RANK(AI10,$AI$2:$AI$755) -> 9 | B10: =IF(T10="Y","Superseded",IF(C10>=Scoring!$B$16,"Immediate",IF(C10>=Scoring!$B$17,"This week",IF(C10>=Scoring!$B$18,"Nurture","Low")))) -> This week | C10: =SUM(AC10:AH10) -> 71 | D10: =IF(T10="Y","Superseded record",IF(AND(U10<>"",AA10<0),"Expired (verified)",IF(AND(U10<>"",AA10<=Scoring!$B$5),"Expiring: notice window (verified)",IF(AND(U10<>"",AA10<=Scoring!$B$6),"Expiring: 10-yr horizon (verified)",IF(M10="No Longer Monitored","Out of program",IF(N10="","Unknown vintage",IF(N10<Scoring!$B$12,"Pre-1990, still listed",IF(AND(U10="",AA10<0),"Past 30-yr mark (verify)",IF(AND(U10="",AA10<=Scoring!$B$5),"30-yr mark: notice window (est.)",IF(AND(O10>=Scoring!$B$7,O10<=Scoring!$B$8),"Year-15 window",IF(O10>=Scoring!$B$9,"Recap window",IF(O10>=11,"Late compliance","Credit period")))))))))))) -> Past 30-yr mark (verify) | E10: ORA19949091 | F10: TWELFTH AVENUE TERRACE | G10: 1529 SW 12TH AVE | H10: PORTLAND | I10: 97201 | J10: 119 | K10: 100 | L10: =IF(OR(J10="",K10=""),"",MAX(J10-K10,0)) -> 19 | M10: Not Indicated | N10: 1994 | O10: =IF(N10="","",Scoring!$B$4-N10) -> 32 | P10: =IF(N10="","",N10+14) -> 2008 | Q10: =IF(N10="","",IF(N10<Scoring!$B$12,"n/a (pre-1990)",N10+Scoring!$B$13)) -> 2023 | R10: =IF(J10="","Unknown",IF(J10>=5,"Yes","No (under 5 units)")) -> Yes | AA10: =IF(U10<>"",(U10-Scoring!$B$3)/365.25,IF(N10="","",IF(N10<Scoring!$B$12,"",(DATE(N10+Scoring!$B$13,12,31)-Scoring!$B$3)/365.25))) -> -2.7542779 | AB10: =IF(T10="Y",0,IF(OR(D10="Expired (verified)",D10="Expiring: notice window (verified)",D10="Expiring: 10-yr horizon (verified)",D10="Past 30-yr mark (verify)",D10="30-yr mark: notice window (est.)",D10="Year-15 window"),1,0)+IF(ISNUMBER(O10),IF(O10>=Scoring!$B$10,1,0),0)+IF(AND(ISNUMBER(L10),ISNUMBER(J10)),IF(J10>0,IF(L10/J10>=Scoring!$B$11,1,0),0),0)+IF(ISNUMBER(Z10),MIN(Z10,3),0)) -> 3 | AC10: =IF(AB10>=3,Scoring!$C$24,IF(AB10=2,Scoring!$C$23,IF(AB10=1,Scoring!$C$22,0))) -> 25 | AD10: =IF(T10="Y",0,IF(ISNUMBER(X10),IF(X10>0.7,Scoring!$C$25,IF(X10>=0.5,Scoring!$C$26,IF(X10>=0.3,Scoring!$C$27,Scoring!$C$28))),Scoring!$C$29)) -> 10 | AE10: =IF(D10="Expiring: notice window (verified)",Scoring!$C$30,IF(OR(D10="Expired (verified)",D10="30-yr mark: notice window (est.)",D10="Year-15 window"),Scoring!$C$31,IF(D10="Expiring: 10-yr horizon (verified)",Scoring!$C$32,IF(D10="Past 30-yr mark (verify)",Scoring!$C$33,IF(OR(D10="Credit period",D10="Superseded record"),Scoring!$C$35,Scoring!$C$34))))) -> 8 | AF10: =IF(T10="Y",0,IF(ISNUMBER(V10),IF(Scoring!$B$4-V10>15,Scoring!$C$36,IF(Scoring!$B$4-V10>=10,Scoring!$C$37,IF(Scoring!$B$4-V10>=5,Scoring!$C$38,Scoring!$C$39))),IF(OR(N10="",D10="Out of program"),Scoring!$C$40,IF(O10>15,Scoring!$C$36,IF(O10>=10,Scoring!$C$37,IF(O10>=5,Scoring!$C$38,Scoring!$C$39)))))) -> 15 | AG10: =IF(T10="Y",0,IF(Y10="Y",Scoring!$C$41,IF(ISNUMBER(O10),IF(O10>=25,Scoring!$C$42,IF(O10>=15,Scoring!$C$43,Scoring!$C$44)),Scoring!$C$44))) -> 8 | AH10: =IF(T10="Y",0,IF(W10="",Scoring!$C$49,IFERROR(VLOOKUP(W10,Scoring!$B$45:$C$48,2,FALSE()),Scoring!$C$49))) -> 5 | AI10: =C10+IF(ISNUMBER(J10),J10,0)/100000+(10000-ROW())/1000000000 -> 71.0012
A11: =RANK(AI11,$AI$2:$AI$755) -> 10 | B11: =IF(T11="Y","Superseded",IF(C11>=Scoring!$B$16,"Immediate",IF(C11>=Scoring!$B$17,"This week",IF(C11>=Scoring!$B$18,"Nurture","Low")))) -> This week | C11: =SUM(AC11:AH11) -> 71 | D11: =IF(T11="Y","Superseded record",IF(AND(U11<>"",AA11<0),"Expired (verified)",IF(AND(U11<>"",AA11<=Scoring!$B$5),"Expiring: notice window (verified)",IF(AND(U11<>"",AA11<=Scoring!$B$6),"Expiring: 10-yr horizon (verified)",IF(M11="No Longer Monitored","Out of program",IF(N11="","Unknown vintage",IF(N11<Scoring!$B$12,"Pre-1990, still listed",IF(AND(U11="",AA11<0),"Past 30-yr mark (verify)",IF(AND(U11="",AA11<=Scoring!$B$5),"30-yr mark: notice window (est.)",IF(AND(O11>=Scoring!$B$7,O11<=Scoring!$B$8),"Year-15 window",IF(O11>=Scoring!$B$9,"Recap window",IF(O11>=11,"Late compliance","Credit period")))))))))))) -> Past 30-yr mark (verify) | E11: ORA19940065 | F11: ST JAMES | G11: 1320 SW TENTH AVE | H11: PORTLAND | J11: 109 | K11: 98 | L11: =IF(OR(J11="",K11=""),"",MAX(J11-K11,0)) -> 11 | M11: Not Indicated | N11: 1994 | O11: =IF(N11="","",Scoring!$B$4-N11) -> 32 | P11: =IF(N11="","",N11+14) -> 2008 | Q11: =IF(N11="","",IF(N11<Scoring!$B$12,"n/a (pre-1990)",N11+Scoring!$B$13)) -> 2023 | R11: =IF(J11="","Unknown",IF(J11>=5,"Yes","No (under 5 units)")) -> Yes | AA11: =IF(U11<>"",(U11-Scoring!$B$3)/365.25,IF(N11="","",IF(N11<Scoring!$B$12,"",(DATE(N11+Scoring!$B$13,12,31)-Scoring!$B$3)/365.25))) -> -2.7542779 | AB11: =IF(T11="Y",0,IF(OR(D11="Expired (verified)",D11="Expiring: notice window (verified)",D11="Expiring: 10-yr horizon (verified)",D11="Past 30-yr mark (verify)",D11="30-yr mark: notice window (est.)",D11="Year-15 window"),1,0)+IF(ISNUMBER(O11),IF(O11>=Scoring!$B$10,1,0),0)+IF(AND(ISNUMBER(L11),ISNUMBER(J11)),IF(J11>0,IF(L11/J11>=Scoring!$B$11,1,0),0),0)+IF(ISNUMBER(Z11),MIN(Z11,3),0)) -> 3 | AC11: =IF(AB11>=3,Scoring!$C$24,IF(AB11=2,Scoring!$C$23,IF(AB11=1,Scoring!$C$22,0))) -> 25 | AD11: =IF(T11="Y",0,IF(ISNUMBER(X11),IF(X11>0.7,Scoring!$C$25,IF(X11>=0.5,Scoring!$C$26,IF(X11>=0.3,Scoring!$C$27,Scoring!$C$28))),Scoring!$C$29)) -> 10 | AE11: =IF(D11="Expiring: notice window (verified)",Scoring!$C$30,IF(OR(D11="Expired (verified)",D11="30-yr mark: notice window (est.)",D11="Year-15 window"),Scoring!$C$31,IF(D11="Expiring: 10-yr horizon (verified)",Scoring!$C$32,IF(D11="Past 30-yr mark (verify)",Scoring!$C$33,IF(OR(D11="Credit period",D11="Superseded record"),Scoring!$C$35,Scoring!$C$34))))) -> 8 | AF11: =IF(T11="Y",0,IF(ISNUMBER(V11),IF(Scoring!$B$4-V11>15,Scoring!$C$36,IF(Scoring!$B$4-V11>=10,Scoring!$C$37,IF(Scoring!$B$4-V11>=5,Scoring!$C$38,Scoring!$C$39))),IF(OR(N11="",D11="Out of program"),Scoring!$C$40,IF(O11>15,Scoring!$C$36,IF(O11>=10,Scoring!$C$37,IF(O11>=5,Scoring!$C$38,Scoring!$C$39)))))) -> 15 | AG11: =IF(T11="Y",0,IF(Y11="Y",Scoring!$C$41,IF(ISNUMBER(O11),IF(O11>=25,Scoring!$C$42,IF(O11>=15,Scoring!$C$43,Scoring!$C$44)),Scoring!$C$44))) -> 8 | AH11: =IF(T11="Y",0,IF(W11="",Scoring!$C$49,IFERROR(VLOOKUP(W11,Scoring!$B$45:$C$48,2,FALSE()),Scoring!$C$49))) -> 5 | AI11: =C11+IF(ISNUMBER(J11),J11,0)/100000+(10000-ROW())/1000000000 -> 71.0011
A12: =RANK(AI12,$AI$2:$AI$755) -> 11 | B12: =IF(T12="Y","Superseded",IF(C12>=Scoring!$B$16,"Immediate",IF(C12>=Scoring!$B$17,"This week",IF(C12>=Scoring!$B$18,"Nurture","Low")))) -> This week | C12: =SUM(AC12:AH12) -> 71 | D12: =IF(T12="Y","Superseded record",IF(AND(U12<>"",AA12<0),"Expired (verified)",IF(AND(U12<>"",AA12<=Scoring!$B$5),"Expiring: notice window (verified)",IF(AND(U12<>"",AA12<=Scoring!$B$6),"Expiring: 10-yr horizon (verified)",IF(M12="No Longer Monitored","Out of program",IF(N12="","Unknown vintage",IF(N12<Scoring!$B$12,"Pre-1990, still listed",IF(AND(U12="",AA12<0),"Past 30-yr mark (verify)",IF(AND(U12="",AA12<=Scoring!$B$5),"30-yr mark: notice window (est.)",IF(AND(O12>=Scoring!$B$7,O12<=Scoring!$B$8),"Year-15 window",IF(O12>=Scoring!$B$9,"Recap window",IF(O12>=11,"Late compliance","Credit period")))))))))))) -> Past 30-yr mark (verify) | E12: ORA19930062 | F12: STONEYBROOK | G12: 933 NW CANAL BLVD | H12: REDMOND | I12: 97756 | J12: 50 | K12: 40 | L12: =IF(OR(J12="",K12=""),"",MAX(J12-K12,0)) -> 10 | M12: Not Indicated | N12: 1993 | O12: =IF(N12="","",Scoring!$B$4-N12) -> 33 | P12: =IF(N12="","",N12+14) -> 2007 | Q12: =IF(N12="","",IF(N12<Scoring!$B$12,"n/a (pre-1990)",N12+Scoring!$B$13)) -> 2022 | R12: =IF(J12="","Unknown",IF(J12>=5,"Yes","No (under 5 units)")) -> Yes | AA12: =IF(U12<>"",(U12-Scoring!$B$3)/365.25,IF(N12="","",IF(N12<Scoring!$B$12,"",(DATE(N12+Scoring!$B$13,12,31)-Scoring!$B$3)/365.25))) -> -3.7535934 | AB12: =IF(T12="Y",0,IF(OR(D12="Expired (verified)",D12="Expiring: notice window (verified)",D12="Expiring: 10-yr horizon (verified)",D12="Past 30-yr mark (verify)",D12="30-yr mark: notice window (est.)",D12="Year-15 window"),1,0)+IF(ISNUMBER(O12),IF(O12>=Scoring!$B$10,1,0),0)+IF(AND(ISNUMBER(L12),ISNUMBER(J12)),IF(J12>0,IF(L12/J12>=Scoring!$B$11,1,0),0),0)+IF(ISNUMBER(Z12),MIN(Z12,3),0)) -> 3 | AC12: =IF(AB12>=3,Scoring!$C$24,IF(AB12=2,Scoring!$C$23,IF(AB12=1,Scoring!$C$22,0))) -> 25 | AD12: =IF(T12="Y",0,IF(ISNUMBER(X12),IF(X12>0.7,Scoring!$C$25,IF(X12>=0.5,Scoring!$C$26,IF(X12>=0.3,Scoring!$C$27,Scoring!$C$28))),Scoring!$C$29)) -> 10 | AE12: =IF(D12="Expiring: notice window (verified)",Scoring!$C$30,IF(OR(D12="Expired (verified)",D12="30-yr mark: notice window (est.)",D12="Year-15 window"),Scoring!$C$31,IF(D12="Expiring: 10-yr horizon (verified)",Scoring!$C$32,IF(D12="Past 30-yr mark (verify)",Scoring!$C$33,IF(OR(D12="Credit period",D12="Superseded record"),Scoring!$C$35,Scoring!$C$34))))) -> 8 | AF12: =IF(T12="Y",0,IF(ISNUMBER(V12),IF(Scoring!$B$4-V12>15,Scoring!$C$36,IF(Scoring!$B$4-V12>=10,Scoring!$C$37,IF(Scoring!$B$4-V12>=5,Scoring!$C$38,Scoring!$C$39))),IF(OR(N12="",D12="Out of program"),Scoring!$C$40,IF(O12>15,Scoring!$C$36,IF(O12>=10,Scoring!$C$37,IF(O12>=5,Scoring!$C$38,Scoring!$C$39)))))) -> 15 | AG12: =IF(T12="Y",0,IF(Y12="Y",Scoring!$C$41,IF(ISNUMBER(O12),IF(O12>=25,Scoring!$C$42,IF(O12>=15,Scoring!$C$43,Scoring!$C$44)),Scoring!$C$44))) -> 8 | AH12: =IF(T12="Y",0,IF(W12="",Scoring!$C$49,IFERROR(VLOOKUP(W12,Scoring!$B$45:$C$48,2,FALSE()),Scoring!$C$49))) -> 5 | AI12: =C12+IF(ISNUMBER(J12),J12,0)/100000+(10000-ROW())/1000000000 -> 71.00051
A13: =RANK(AI13,$AI$2:$AI$755) -> 12 | B13: =IF(T13="Y","Superseded",IF(C13>=Scoring!$B$16,"Immediate",IF(C13>=Scoring!$B$17,"This week",IF(C13>=Scoring!$B$18,"Nurture","Low")))) -> This week | C13: =SUM(AC13:AH13) -> 70 | D13: =IF(T13="Y","Superseded record",IF(AND(U13<>"",AA13<0),"Expired (verified)",IF(AND(U13<>"",AA13<=Scoring!$B$5),"Expiring: notice window (verified)",IF(AND(U13<>"",AA13<=Scoring!$B$6),"Expiring: 10-yr horizon (verified)",IF(M13="No Longer Monitored","Out of program",IF(N13="","Unknown vintage",IF(N13<Scoring!$B$12,"Pre-1990, still listed",IF(AND(U13="",AA13<0),"Past 30-yr mark (verify)",IF(AND(U13="",AA13<=Scoring!$B$5),"30-yr mark: notice window (est.)",IF(AND(O13>=Scoring!$B$7,O13<=Scoring!$B$8),"Year-15 window",IF(O13>=Scoring!$B$9,"Recap window",IF(O13>=11,"Late compliance","Credit period")))))))))))) -> 30-yr mark: notice window (est.) | E13: ORA19980020 | F13: BERRY RIDGE APTS | G13: 2711 W POWELL BLVD | H13: GRESHAM | I13: 97030 | J13: 248 | K13: 248 | L13: =IF(OR(J13="",K13=""),"",MAX(J13-K13,0)) -> 0 | M13: Not Indicated | N13: 1998 | O13: =IF(N13="","",Scoring!$B$4-N13) -> 28 | P13: =IF(N13="","",N13+14) -> 2012 | Q13: =IF(N13="","",IF(N13<Scoring!$B$12,"n/a (pre-1990)",N13+Scoring!$B$13)) -> 2027 | R13: =IF(J13="","Unknown",IF(J13>=5,"Yes","No (under 5 units)")) -> Yes | AA13: =IF(U13<>"",(U13-Scoring!$B$3)/365.25,IF(N13="","",IF(N13<Scoring!$B$12,"",(DATE(N13+Scoring!$B$13,12,31)-Scoring!$B$3)/365.25))) -> 1.2457221 | AB13: =IF(T13="Y",0,IF(OR(D13="Expired (verified)",D13="Expiring: notice window (verified)",D13="Expiring: 10-yr horizon (verified)",D13="Past 30-yr mark (verify)",D13="30-yr mark: notice window (est.)",D13="Year-15 window"),1,0)+IF(ISNUMBER(O13),IF(O13>=Scoring!$B$10,1,0),0)+IF(AND(ISNUMBER(L13),ISNUMBER(J13)),IF(J13>0,IF(L13/J13>=Scoring!$B$11,1,0),0),0)+IF(ISNUMBER(Z13),MIN(Z13,3),0)) -> 2 | AC13: =IF(AB13>=3,Scoring!$C$24,IF(AB13=2,Scoring!$C$23,IF(AB13=1,Scoring!$C$22,0))) -> 18 | AD13: =IF(T13="Y",0,IF(ISNUMBER(X13),IF(X13>0.7,Scoring!$C$25,IF(X13>=0.5,Scoring!$C$26,IF(X13>=0.3,Scoring!$C$27,Scoring!$C$28))),Scoring!$C$29)) -> 10 | AE13: =IF(D13="Expiring: notice window (verified)",Scoring!$C$30,IF(OR(D13="Expired (verified)",D13="30-yr mark: notice window (est.)",D13="Year-15 window"),Scoring!$C$31,IF(D13="Expiring: 10-yr horizon (verified)",Scoring!$C$32,IF(D13="Past 30-yr mark (verify)",Scoring!$C$33,IF(OR(D13="Credit period",D13="Superseded record"),Scoring!$C$35,Scoring!$C$34))))) -> 14 | AF13: =IF(T13="Y",0,IF(ISNUMBER(V13),IF(Scoring!$B$4-V13>15,Scoring!$C$36,IF(Scoring!$B$4-V13>=10,Scoring!$C$37,IF(Scoring!$B$4-V13>=5,Scoring!$C$38,Scoring!$C$39))),IF(OR(N13="",D13="Out of program"),Scoring!$C$40,IF(O13>15,Scoring!$C$36,IF(O13>=10,Scoring!$C$37,IF(O13>=5,Scoring!$C$38,Scoring!$C$39)))))) -> 15 | AG13: =IF(T13="Y",0,IF(Y13="Y",Scoring!$C$41,IF(ISNUMBER(O13),IF(O13>=25,Scoring!$C$42,IF(O13>=15,Scoring!$C$43,Scoring!$C$44)),Scoring!$C$44))) -> 8 | AH13: =IF(T13="Y",0,IF(W13="",Scoring!$C$49,IFERROR(VLOOKUP(W13,Scoring!$B$45:$C$48,2,FALSE()),Scoring!$C$49))) -> 5 | AI13: =C13+IF(ISNUMBER(J13),J13,0)/100000+(10000-ROW())/1000000000 -> 70.00249
A14: =RANK(AI14,$AI$2:$AI$755) -> 13 | B14: =IF(T14="Y","Superseded",IF(C14>=Scoring!$B$16,"Immediate",IF(C14>=Scoring!$B$17,"This week",IF(C14>=Scoring!$B$18,"Nurture","Low")))) -> This week | C14: =SUM(AC14:AH14) -> 70 | D14: =IF(T14="Y","Superseded record",IF(AND(U14<>"",AA14<0),"Expired (verified)",IF(AND(U14<>"",AA14<=Scoring!$B$5),"Expiring: notice window (verified)",IF(AND(U14<>"",AA14<=Scoring!$B$6),"Expiring: 10-yr horizon (verified)",IF(M14="No Longer Monitored","Out of program",IF(N14="","Unknown vintage",IF(N14<Scoring!$B$12,"Pre-1990, still listed",IF(AND(U14="",AA14<0),"Past 30-yr mark (verify)",IF(AND(U14="",AA14<=Scoring!$B$5),"30-yr mark: notice window (est.)",IF(AND(O14>=Scoring!$B$7,O14<=Scoring!$B$8),"Year-15 window",IF(O14>=Scoring!$B$9,"Recap window",IF(O14>=11,"Late compliance","Credit period")))))))))))) -> 30-yr mark: notice window (est.) | E14: ORA19999166 | F14: BRIARCREEK APTS | G14: 1008 NW BRIARCREEK WAY | H14: HILLSBORO | I14: 97006 | J14: 216 | K14: 216 | L14: =IF(OR(J14="",K14=""),"",MAX(J14-K14,0)) -> 0 | M14: Not Indicated | N14: 1999 | O14: =IF(N14="","",Scoring!$B$4-N14) -> 27 | P14: =IF(N14="","",N14+14) -> 2013 | Q14: =IF(N14="","",IF(N14<Scoring!$B$12,"n/a (pre-1990)",N14+Scoring!$B$13)) -> 2028 | R14: =IF(J14="","Unknown",IF(J14>=5,"Yes","No (under 5 units)")) -> Yes | AA14: =IF(U14<>"",(U14-Scoring!$B$3)/365.25,IF(N14="","",IF(N14<Scoring!$B$12,"",(DATE(N14+Scoring!$B$13,12,31)-Scoring!$B$3)/365.25))) -> 2.2477755 | AB14: =IF(T14="Y",0,IF(OR(D14="Expired (verified)",D14="Expiring: notice window (verified)",D14="Expiring: 10-yr horizon (verified)",D14="Past 30-yr mark (verify)",D14="30-yr mark: notice window (est.)",D14="Year-15 window"),1,0)+IF(ISNUMBER(O14),IF(O14>=Scoring!$B$10,1,0),0)+IF(AND(ISNUMBER(L14),ISNUMBER(J14)),IF(J14>0,IF(L14/J14>=Scoring!$B$11,1,0),0),0)+IF(ISNUMBER(Z14),MIN(Z14,3),0)) -> 2 | AC14: =IF(AB14>=3,Scoring!$C$24,IF(AB14=2,Scoring!$C$23,IF(AB14=1,Scoring!$C$22,0))) -> 18 | AD14: =IF(T14="Y",0,IF(ISNUMBER(X14),IF(X14>0.7,Scoring!$C$25,IF(X14>=0.5,Scoring!$C$26,IF(X14>=0.3,Scoring!$C$27,Scoring!$C$28))),Scoring!$C$29)) -> 10 | AE14: =IF(D14="Expiring: notice window (verified)",Scoring!$C$30,IF(OR(D14="Expired (verified)",D14="30-yr mark: notice window (est.)",D14="Year-15 window"),Scoring!$C$31,IF(D14="Expiring: 10-yr horizon (verified)",Scoring!$C$32,IF(D14="Past 30-yr mark (verify)",Scoring!$C$33,IF(OR(D14="Credit period",D14="Superseded record"),Scoring!$C$35,Scoring!$C$34))))) -> 14 | AF14: =IF(T14="Y",0,IF(ISNUMBER(V14),IF(Scoring!$B$4-V14>15,Scoring!$C$36,IF(Scoring!$B$4-V14>=10,Scoring!$C$37,IF(Scoring!$B$4-V14>=5,Scoring!$C$38,Scoring!$C$39))),IF(OR(N14="",D14="Out of program"),Scoring!$C$40,IF(O14>15,Scoring!$C$36,IF(O14>=10,Scoring!$C$37,IF(O14>=5,Scoring!$C$38,Scoring!$C$39)))))) -> 15 | AG14: =IF(T14="Y",0,IF(Y14="Y",Scoring!$C$41,IF(ISNUMBER(O14),IF(O14>=25,Scoring!$C$42,IF(O14>=15,Scoring!$C$43,Scoring!$C$44)),Scoring!$C$44))) -> 8 | AH14: =IF(T14="Y",0,IF(W14="",Scoring!$C$49,IFERROR(VLOOKUP(W14,Scoring!$B$45:$C$48,2,FALSE()),Scoring!$C$49))) -> 5 | AI14: =C14+IF(ISNUMBER(J14),J14,0)/100000+(10000-ROW())/1000000000 -> 70.00217
A15: =RANK(AI15,$AI$2:$AI$755) -> 14 | B15: =IF(T15="Y","Superseded",IF(C15>=Scoring!$B$16,"Immediate",IF(C15>=Scoring!$B$17,"This week",IF(C15>=Scoring!$B$18,"Nurture","Low")))) -> This week | C15: =SUM(AC15:AH15) -> 70 | D15: =IF(T15="Y","Superseded record",IF(AND(U15<>"",AA15<0),"Expired (verified)",IF(AND(U15<>"",AA15<=Scoring!$B$5),"Expiring: notice window (verified)",IF(AND(U15<>"",AA15<=Scoring!$B$6),"Expiring: 10-yr horizon (verified)",IF(M15="No Longer Monitored","Out of program",IF(N15="","Unknown vintage",IF(N15<Scoring!$B$12,"Pre-1990, still listed",IF(AND(U15="",AA15<0),"Past 30-yr mark (verify)",IF(AND(U15="",AA15<=Scoring!$B$5),"30-yr mark: notice window (est.)",IF(AND(O15>=Scoring!$B$7,O15<=Scoring!$B$8),"Year-15 window",IF(O15>=Scoring!$B$9,"Recap window",IF(O15>=11,"Late compliance","Credit period")))))))))))) -> 30-yr mark: notice window (est.) | E15: ORA19970020 | F15: BETHANY MEADOWS I | G15: 16140 NW SPARTAN WAY | H15: PORTLAND | I15: 97229 | J15: 208 | K15: 208 | L15: =IF(OR(J15="",K15=""),"",MAX(J15-K15,0)) -> 0 | M15: Not Indicated | N15: 1997 | O15: =IF(N15="","",Scoring!$B$4-N15) -> 29 | P15: =IF(N15="","",N15+14) -> 2011 | Q15: =IF(N15="","",IF(N15<Scoring!$B$12,"n/a (pre-1990)",N15+Scoring!$B$13)) -> 2026 | R15: =IF(J15="","Unknown",IF(J15>=5,"Yes","No (under 5 units)")) -> Yes | AA15: =IF(U15<>"",(U15-Scoring!$B$3)/365.25,IF(N15="","",IF(N15<Scoring!$B$12,"",(DATE(N15+Scoring!$B$13,12,31)-Scoring!$B$3)/365.25))) -> 0.24640657 | AB15: =IF(T15="Y",0,IF(OR(D15="Expired (verified)",D15="Expiring: notice window (verified)",D15="Expiring: 10-yr horizon (verified)",D15="Past 30-yr mark (verify)",D15="30-yr mark: notice window (est.)",D15="Year-15 window"),1,0)+IF(ISNUMBER(O15),IF(O15>=Scoring!$B$10,1,0),0)+IF(AND(ISNUMBER(L15),ISNUMBER(J15)),IF(J15>0,IF(L15/J15>=Scoring!$B$11,1,0),0),0)+IF(ISNUMBER(Z15),MIN(Z15,3),0)) -> 2 | AC15: =IF(AB15>=3,Scoring!$C$24,IF(AB15=2,Scoring!$C$23,IF(AB15=1,Scoring!$C$22,0))) -> 18 | AD15: =IF(T15="Y",0,IF(ISNUMBER(X15),IF(X15>0.7,Scoring!$C$25,IF(X15>=0.5,Scoring!$C$26,IF(X15>=0.3,Scoring!$C$27,Scoring!$C$28))),Scoring!$C$29)) -> 10 | AE15: =IF(D15="Expiring: notice window (verified)",Scoring!$C$30,IF(OR(D15="Expired (verified)",D15="30-yr mark: notice window (est.)",D15="Year-15 window"),Scoring!$C$31,IF(D15="Expiring: 10-yr horizon (verified)",Scoring!$C$32,IF(D15="Past 30-yr mark (verify)",Scoring!$C$33,IF(OR(D15="Credit period",D15="Superseded record"),Scoring!$C$35,Scoring!$C$34))))) -> 14 | AF15: =IF(T15="Y",0,IF(ISNUMBER(V15),IF(Scoring!$B$4-V15>15,Scoring!$C$36,IF(Scoring!$B$4-V15>=10,Scoring!$C$37,IF(Scoring!$B$4-V15>=5,Scoring!$C$38,Scoring!$C$39))),IF(OR(N15="",D15="Out of program"),Scoring!$C$40,IF(O15>15,Scoring!$C$36,IF(O15>=10,Scoring!$C$37,IF(O15>=5,Scoring!$C$38,Scoring!$C$39)))))) -> 15 | AG15: =IF(T15="Y",0,IF(Y15="Y",Scoring!$C$41,IF(ISNUMBER(O15),IF(O15>=25,Scoring!$C$42,IF(O15>=15,Scoring!$C$43,Scoring!$C$44)),Scoring!$C$44))) -> 8 | AH15: =IF(T15="Y",0,IF(W15="",Scoring!$C$49,IFERROR(VLOOKUP(W15,Scoring!$B$45:$C$48,2,FALSE()),Scoring!$C$49))) -> 5 | AI15: =C15+IF(ISNUMBER(J15),J15,0)/100000+(10000-ROW())/1000000000 -> 70.00209
A16: =RANK(AI16,$AI$2:$AI$755) -> 15 | B16: =IF(T16="Y","Superseded",IF(C16>=Scoring!$B$16,"Immediate",IF(C16>=Scoring!$B$17,"This week",IF(C16>=Scoring!$B$18,"Nurture","Low")))) -> This week | C16: =SUM(AC16:AH16) -> 70 | D16: =IF(T16="Y","Superseded record",IF(AND(U16<>"",AA16<0),"Expired (verified)",IF(AND(U16<>"",AA16<=Scoring!$B$5),"Expiring: notice window (verified)",IF(AND(U16<>"",AA16<=Scoring!$B$6),"Expiring: 10-yr horizon (verified)",IF(M16="No Longer Monitored","Out of program",IF(N16="","Unknown vintage",IF(N16<Scoring!$B$12,"Pre-1990, still listed",IF(AND(U16="",AA16<0),"Past 30-yr mark (verify)",IF(AND(U16="",AA16<=Scoring!$B$5),"30-yr mark: notice window (est.)",IF(AND(O16>=Scoring!$B$7,O16<=Scoring!$B$8),"Year-15 window",IF(O16>=Scoring!$B$9,"Recap window",IF(O16>=11,"Late compliance","Credit period")))))))))))) -> 30-yr mark: notice window (est.) | E16: ORA19970075 | F16: PEARL COURT APTS | G16: 920 NW KEARNEY ST | H16: PORTLAND | I16: 97209 | J16: 199 | L16: =IF(OR(J16="",K16=""),"",MAX(J16-K16,0)) | M16: Not Indicated | N16: 1997 | O16: =IF(N16="","",Scoring!$B$4-N16) -> 29 | P16: =IF(N16="","",N16+14) -> 2011 | Q16: =IF(N16="","",IF(N16<Scoring!$B$12,"n/a (pre-1990)",N16+Scoring!$B$13)) -> 2026 | R16: =IF(J16="","Unknown",IF(J16>=5,"Yes","No (under 5 units)")) -> Yes | AA16: =IF(U16<>"",(U16-Scoring!$B$3)/365.25,IF(N16="","",IF(N16<Scoring!$B$12,"",(DATE(N16+Scoring!$B$13,12,31)-Scoring!$B$3)/365.25))) -> 0.24640657 | AB16: =IF(T16="Y",0,IF(OR(D16="Expired (verified)",D16="Expiring: notice window (verified)",D16="Expiring: 10-yr horizon (verified)",D16="Past 30-yr mark (verify)",D16="30-yr mark: notice window (est.)",D16="Year-15 window"),1,0)+IF(ISNUMBER(O16),IF(O16>=Scoring!$B$10,1,0),0)+IF(AND(ISNUMBER(L16),ISNUMBER(J16)),IF(J16>0,IF(L16/J16>=Scoring!$B$11,1,0),0),0)+IF(ISNUMBER(Z16),MIN(Z16,3),0)) -> 2 | AC16: =IF(AB16>=3,Scoring!$C$24,IF(AB16=2,Scoring!$C$23,IF(AB16=1,Scoring!$C$22,0))) -> 18 | AD16: =IF(T16="Y",0,IF(ISNUMBER(X16),IF(X16>0.7,Scoring!$C$25,IF(X16>=0.5,Scoring!$C$26,IF(X16>=0.3,Scoring!$C$27,Scoring!$C$28))),Scoring!$C$29)) -> 10 | AE16: =IF(D16="Expiring: notice window (verified)",Scoring!$C$30,IF(OR(D16="Expired (verified)",D16="30-yr mark: notice window (est.)",D16="Year-15 window"),Scoring!$C$31,IF(D16="Expiring: 10-yr horizon (verified)",Scoring!$C$32,IF(D16="Past 30-yr mark (verify)",Scoring!$C$33,IF(OR(D16="Credit period",D16="Superseded record"),Scoring!$C$35,Scoring!$C$34))))) -> 14 | AF16: =IF(T16="Y",0,IF(ISNUMBER(V16),IF(Scoring!$B$4-V16>15,Scoring!$C$36,IF(Scoring!$B$4-V16>=10,Scoring!$C$37,IF(Scoring!$B$4-V16>=5,Scoring!$C$38,Scoring!$C$39))),IF(OR(N16="",D16="Out of program"),Scoring!$C$40,IF(O16>15,Scoring!$C$36,IF(O16>=10,Scoring!$C$37,IF(O16>=5,Scoring!$C$38,Scoring!$C$39)))))) -> 15 | AG16: =IF(T16="Y",0,IF(Y16="Y",Scoring!$C$41,IF(ISNUMBER(O16),IF(O16>=25,Scoring!$C$42,IF(O16>=15,Scoring!$C$43,Scoring!$C$44)),Scoring!$C$44))) -> 8 | AH16: =IF(T16="Y",0,IF(W16="",Scoring!$C$49,IFERROR(VLOOKUP(W16,Scoring!$B$45:$C$48,2,FALSE()),Scoring!$C$49))) -> 5 | AI16: =C16+IF(ISNUMBER(J16),J16,0)/100000+(10000-ROW())/1000000000 -> 70.002
A17: =RANK(AI17,$AI$2:$AI$755) -> 16 | B17: =IF(T17="Y","Superseded",IF(C17>=Scoring!$B$16,"Immediate",IF(C17>=Scoring!$B$17,"This week",IF(C17>=Scoring!$B$18,"Nurture","Low")))) -> This week | C17: =SUM(AC17:AH17) -> 70 | D17: =IF(T17="Y","Superseded record",IF(AND(U17<>"",AA17<0),"Expired (verified)",IF(AND(U17<>"",AA17<=Scoring!$B$5),"Expiring: notice window (verified)",IF(AND(U17<>"",AA17<=Scoring!$B$6),"Expiring: 10-yr horizon (verified)",IF(M17="No Longer Monitored","Out of program",IF(N17="","Unknown vintage",IF(N17<Scoring!$B$12,"Pre-1990, still listed",IF(AND(U17="",AA17<0),"Past 30-yr mark (verify)",IF(AND(U17="",AA17<=Scoring!$B$5),"30-yr mark: notice window (est.)",IF(AND(O17>=Scoring!$B$7,O17<=Scoring!$B$8),"Year-15 window",IF(O17>=Scoring!$B$9,"Recap window",IF(O17>=11,"Late compliance","Credit period")))))))))))) -> 30-yr mark: notice window (est.) | E17: ORA19970080 | F17: PIER PARK APTS | G17: 8734 N COLUMBIA BLVD | H17: PORTLAND | I17: 97203 | J17: 164 | K17: 164 | L17: =IF(OR(J17="",K17=""),"",MAX(J17-K17,0)) -> 0 | M17: Not Indicated | N17: 1997 | O17: =IF(N17="","",Scoring!$B$4-N17) -> 29 | P17: =IF(N17="","",N17+14) -> 2011 | Q17: =IF(N17="","",IF(N17<Scoring!$B$12,"n/a (pre-1990)",N17+Scoring!$B$13)) -> 2026 | R17: =IF(J17="","Unknown",IF(J17>=5,"Yes","No (under 5 units)")) -> Yes | AA17: =IF(U17<>"",(U17-Scoring!$B$3)/365.25,IF(N17="","",IF(N17<Scoring!$B$12,"",(DATE(N17+Scoring!$B$13,12,31)-Scoring!$B$3)/365.25))) -> 0.24640657 | AB17: =IF(T17="Y",0,IF(OR(D17="Expired (verified)",D17="Expiring: notice window (verified)",D17="Expiring: 10-yr horizon (verified)",D17="Past 30-yr mark (verify)",D17="30-yr mark: notice window (est.)",D17="Year-15 window"),1,0)+IF(ISNUMBER(O17),IF(O17>=Scoring!$B$10,1,0),0)+IF(AND(ISNUMBER(L17),ISNUMBER(J17)),IF(J17>0,IF(L17/J17>=Scoring!$B$11,1,0),0),0)+IF(ISNUMBER(Z17),MIN(Z17,3),0)) -> 2 | AC17: =IF(AB17>=3,Scoring!$C$24,IF(AB17=2,Scoring!$C$23,IF(AB17=1,Scoring!$C$22,0))) -> 18 | AD17: =IF(T17="Y",0,IF(ISNUMBER(X17),IF(X17>0.7,Scoring!$C$25,IF(X17>=0.5,Scoring!$C$26,IF(X17>=0.3,Scoring!$C$27,Scoring!$C$28))),Scoring!$C$29)) -> 10 | AE17: =IF(D17="Expiring: notice window (verified)",Scoring!$C$30,IF(OR(D17="Expired (verified)",D17="30-yr mark: notice window (est.)",D17="Year-15 window"),Scoring!$C$31,IF(D17="Expiring: 10-yr horizon (verified)",Scoring!$C$32,IF(D17="Past 30-yr mark (verify)",Scoring!$C$33,IF(OR(D17="Credit period",D17="Superseded record"),Scoring!$C$35,Scoring!$C$34))))) -> 14 | AF17: =IF(T17="Y",0,IF(ISNUMBER(V17),IF(Scoring!$B$4-V17>15,Scoring!$C$36,IF(Scoring!$B$4-V17>=10,Scoring!$C$37,IF(Scoring!$B$4-V17>=5,Scoring!$C$38,Scoring!$C$39))),IF(OR(N17="",D17="Out of program"),Scoring!$C$40,IF(O17>15,Scoring!$C$36,IF(O17>=10,Scoring!$C$37,IF(O17>=5,Scoring!$C$38,Scoring!$C$39)))))) -> 15 | AG17: =IF(T17="Y",0,IF(Y17="Y",Scoring!$C$41,IF(ISNUMBER(O17),IF(O17>=25,Scoring!$C$42,IF(O17>=15,Scoring!$C$43,Scoring!$C$44)),Scoring!$C$44))) -> 8 | AH17: =IF(T17="Y",0,IF(W17="",Scoring!$C$49,IFERROR(VLOOKUP(W17,Scoring!$B$45:$C$48,2,FALSE()),Scoring!$C$49))) -> 5 | AI17: =C17+IF(ISNUMBER(J17),J17,0)/100000+(10000-ROW())/1000000000 -> 70.00165
A18: =RANK(AI18,$AI$2:$AI$755) -> 17 | B18: =IF(T18="Y","Superseded",IF(C18>=Scoring!$B$16,"Immediate",IF(C18>=Scoring!$B$17,"This week",IF(C18>=Scoring!$B$18,"Nurture","Low")))) -> This week | C18: =SUM(AC18:AH18) -> 70 | D18: =IF(T18="Y","Superseded record",IF(AND(U18<>"",AA18<0),"Expired (verified)",IF(AND(U18<>"",AA18<=Scoring!$B$5),"Expiring: notice window (verified)",IF(AND(U18<>"",AA18<=Scoring!$B$6),"Expiring: 10-yr horizon (verified)",IF(M18="No Longer Monitored","Out of program",IF(N18="","Unknown vintage",IF(N18<Scoring!$B$12,"Pre-1990, still listed",IF(AND(U18="",AA18<0),"Past 30-yr mark (verify)",IF(AND(U18="",AA18<=Scoring!$B$5),"30-yr mark: notice window (est.)",IF(AND(O18>=Scoring!$B$7,O18<=Scoring!$B$8),"Year-15 window",IF(O18>=Scoring!$B$9,"Recap window",IF(O18>=11,"Late compliance","Credit period")))))))))))) -> 30-yr mark: notice window (est.) | E18: ORA19989127 | F18: YARDS AT UNION STATION A | G18: 945 NW NAITO PKWY | H18: PORTLAND | I18: 97209 | J18: 158 | K18: 158 | L18: =IF(OR(J18="",K18=""),"",MAX(J18-K18,0)) -> 0 | M18: Not Indicated | N18: 1998 | O18: =IF(N18="","",Scoring!$B$4-N18) -> 28 | P18: =IF(N18="","",N18+14) -> 2012 | Q18: =IF(N18="","",IF(N18<Scoring!$B$12,"n/a (pre-1990)",N18+Scoring!$B$13)) -> 2027 | R18: =IF(J18="","Unknown",IF(J18>=5,"Yes","No (under 5 units)")) -> Yes | S18: Shares address with ORA19999167 (phase, resyndication or duplicate) | AA18: =IF(U18<>"",(U18-Scoring!$B$3)/365.25,IF(N18="","",IF(N18<Scoring!$B$12,"",(DATE(N18+Scoring!$B$13,12,31)-Scoring!$B$3)/365.25))) -> 1.2457221 | AB18: =IF(T18="Y",0,IF(OR(D18="Expired (verified)",D18="Expiring: notice window (verified)",D18="Expiring: 10-yr horizon (verified)",D18="Past 30-yr mark (verify)",D18="30-yr mark: notice window (est.)",D18="Year-15 window"),1,0)+IF(ISNUMBER(O18),IF(O18>=Scoring!$B$10,1,0),0)+IF(AND(ISNUMBER(L18),ISNUMBER(J18)),IF(J18>0,IF(L18/J18>=Scoring!$B$11,1,0),0),0)+IF(ISNUMBER(Z18),MIN(Z18,3),0)) -> 2 | AC18: =IF(AB18>=3,Scoring!$C$24,IF(AB18=2,Scoring!$C$23,IF(AB18=1,Scoring!$C$22,0))) -> 18 | AD18: =IF(T18="Y",0,IF(ISNUMBER(X18),IF(X18>0.7,Scoring!$C$25,IF(X18>=0.5,Scoring!$C$26,IF(X18>=0.3,Scoring!$C$27,Scoring!$C$28))),Scoring!$C$29)) -> 10 | AE18: =IF(D18="Expiring: notice window (verified)",Scoring!$C$30,IF(OR(D18="Expired (verified)",D18="30-yr mark: notice window (est.)",D18="Year-15 window"),Scoring!$C$31,IF(D18="Expiring: 10-yr horizon (verified)",Scoring!$C$32,IF(D18="Past 30-yr mark (verify)",Scoring!$C$33,IF(OR(D18="Credit period",D18="Superseded record"),Scoring!$C$35,Scoring!$C$34))))) -> 14 | AF18: =IF(T18="Y",0,IF(ISNUMBER(V18),IF(Scoring!$B$4-V18>15,Scoring!$C$36,IF(Scoring!$B$4-V18>=10,Scoring!$C$37,IF(Scoring!$B$4-V18>=5,Scoring!$C$38,Scoring!$C$39))),IF(OR(N18="",D18="Out of program"),Scoring!$C$40,IF(O18>15,Scoring!$C$36,IF(O18>=10,Scoring!$C$37,IF(O18>=5,Scoring!$C$38,Scoring!$C$39)))))) -> 15 | AG18: =IF(T18="Y",0,IF(Y18="Y",Scoring!$C$41,IF(ISNUMBER(O18),IF(O18>=25,Scoring!$C$42,IF(O18>=15,Scoring!$C$43,Scoring!$C$44)),Scoring!$C$44))) -> 8 | AH18: =IF(T18="Y",0,IF(W18="",Scoring!$C$49,IFERROR(VLOOKUP(W18,Scoring!$B$45:$C$48,2,FALSE()),Scoring!$C$49))) -> 5 | AI18: =C18+IF(ISNUMBER(J18),J18,0)/100000+(10000-ROW())/1000000000 -> 70.00159
A19: =RANK(AI19,$AI$2:$AI$755) -> 18 | B19: =IF(T19="Y","Superseded",IF(C19>=Scoring!$B$16,"Immediate",IF(C19>=Scoring!$B$17,"This week",IF(C19>=Scoring!$B$18,"Nurture","Low")))) -> This week | C19: =SUM(AC19:AH19) -> 70 | D19: =IF(T19="Y","Superseded record",IF(AND(U19<>"",AA19<0),"Expired (verified)",IF(AND(U19<>"",AA19<=Scoring!$B$5),"Expiring: notice window (verified)",IF(AND(U19<>"",AA19<=Scoring!$B$6),"Expiring: 10-yr horizon (verified)",IF(M19="No Longer Monitored","Out of program",IF(N19="","Unknown vintage",IF(N19<Scoring!$B$12,"Pre-1990, still listed",IF(AND(U19="",AA19<0),"Past 30-yr mark (verify)",IF(AND(U19="",AA19<=Scoring!$B$5),"30-yr mark: notice window (est.)",IF(AND(O19>=Scoring!$B$7,O19<=Scoring!$B$8),"Year-15 window",IF(O19>=Scoring!$B$9,"Recap window",IF(O19>=11,"Late compliance","Credit period")))))))))))) -> 30-yr mark: notice window (est.) | E19: ORA19990065 | F19: HAMILTON WEST APTS | G19: 1212 SW CLAY ST | H19: PORTLAND | I19: 97201 | J19: 152 | K19: 152 | L19: =IF(OR(J19="",K19=""),"",MAX(J19-K19,0)) -> 0 | M19: Not Indicated | N19: 1999 | O19: =IF(N19="","",Scoring!$B$4-N19) -> 27 | P19: =IF(N19="","",N19+14) -> 2013 | Q19: =IF(N19="","",IF(N19<Scoring!$B$12,"n/a (pre-1990)",N19+Scoring!$B$13)) -> 2028 | R19: =IF(J19="","Unknown",IF(J19>=5,"Yes","No (under 5 units)")) -> Yes | AA19: =IF(U19<>"",(U19-Scoring!$B$3)/365.25,IF(N19="","",IF(N19<Scoring!$B$12,"",(DATE(N19+Scoring!$B$13,12,31)-Scoring!$B$3)/365.25))) -> 2.2477755 | AB19: =IF(T19="Y",0,IF(OR(D19="Expired (verified)",D19="Expiring: notice window (verified)",D19="Expiring: 10-yr horizon (verified)",D19="Past 30-yr mark (verify)",D19="30-yr mark: notice window (est.)",D19="Year-15 window"),1,0)+IF(ISNUMBER(O19),IF(O19>=Scoring!$B$10,1,0),0)+IF(AND(ISNUMBER(L19),ISNUMBER(J19)),IF(J19>0,IF(L19/J19>=Scoring!$B$11,1,0),0),0)+IF(ISNUMBER(Z19),MIN(Z19,3),0)) -> 2 | AC19: =IF(AB19>=3,Scoring!$C$24,IF(AB19=2,Scoring!$C$23,IF(AB19=1,Scoring!$C$22,0))) -> 18 | AD19: =IF(T19="Y",0,IF(ISNUMBER(X19),IF(X19>0.7,Scoring!$C$25,IF(X19>=0.5,Scoring!$C$26,IF(X19>=0.3,Scoring!$C$27,Scoring!$C$28))),Scoring!$C$29)) -> 10 | AE19: =IF(D19="Expiring: notice window (verified)",Scoring!$C$30,IF(OR(D19="Expired (verified)",D19="30-yr mark: notice window (est.)",D19="Year-15 window"),Scoring!$C$31,IF(D19="Expiring: 10-yr horizon (verified)",Scoring!$C$32,IF(D19="Past 30-yr mark (verify)",Scoring!$C$33,IF(OR(D19="Credit period",D19="Superseded record"),Scoring!$C$35,Scoring!$C$34))))) -> 14 | AF19: =IF(T19="Y",0,IF(ISNUMBER(V19),IF(Scoring!$B$4-V19>15,Scoring!$C$36,IF(Scoring!$B$4-V19>=10,Scoring!$C$37,IF(Scoring!$B$4-V19>=5,Scoring!$C$38,Scoring!$C$39))),IF(OR(N19="",D19="Out of program"),Scoring!$C$40,IF(O19>15,Scoring!$C$36,IF(O19>=10,Scoring!$C$37,IF(O19>=5,Scoring!$C$38,Scoring!$C$39)))))) -> 15 | AG19: =IF(T19="Y",0,IF(Y19="Y",Scoring!$C$41,IF(ISNUMBER(O19),IF(O19>=25,Scoring!$C$42,IF(O19>=15,Scoring!$C$43,Scoring!$C$44)),Scoring!$C$44))) -> 8 | AH19: =IF(T19="Y",0,IF(W19="",Scoring!$C$49,IFERROR(VLOOKUP(W19,Scoring!$B$45:$C$48,2,FALSE()),Scoring!$C$49))) -> 5 | AI19: =C19+IF(ISNUMBER(J19),J19,0)/100000+(10000-ROW())/1000000000 -> 70.00153
A20: =RANK(AI20,$AI$2:$AI$755) -> 19 | B20: =IF(T20="Y","Superseded",IF(C20>=Scoring!$B$16,"Immediate",IF(C20>=Scoring!$B$17,"This week",IF(C20>=Scoring!$B$18,"Nurture","Low")))) -> This week | C20: =SUM(AC20:AH20) -> 70 | D20: =IF(T20="Y","Superseded record",IF(AND(U20<>"",AA20<0),"Expired (verified)",IF(AND(U20<>"",AA20<=Scoring!$B$5),"Expiring: notice window (verified)",IF(AND(U20<>"",AA20<=Scoring!$B$6),"Expiring: 10-yr horizon (verified)",IF(M20="No Longer Monitored","Out of program",IF(N20="","Unknown vintage",IF(N20<Scoring!$B$12,"Pre-1990, still listed",IF(AND(U20="",AA20<0),"Past 30-yr mark (verify)",IF(AND(U20="",AA20<=Scoring!$B$5),"30-yr mark: notice window (est.)",IF(AND(O20>=Scoring!$B$7,O20<=Scoring!$B$8),"Year-15 window",IF(O20>=Scoring!$B$9,"Recap window",IF(O20>=11,"Late compliance","Credit period")))))))))))) -> 30-yr mark: notice window (est.) | E20: ORA19980040 | F20: BUCKMAN HEIGHTS | G20: 430 NE 16TH AVE | H20: PORTLAND | I20: 97232 | J20: 144 | K20: 144 | L20: =IF(OR(J20="",K20=""),"",MAX(J20-K20,0)) -> 0 | M20: Not Indicated | N20: 1998 | O20: =IF(N20="","",Scoring!$B$4-N20) -> 28 | P20: =IF(N20="","",N20+14) -> 2012 | Q20: =IF(N20="","",IF(N20<Scoring!$B$12,"n/a (pre-1990)",N20+Scoring!$B$13)) -> 2027 | R20: =IF(J20="","Unknown",IF(J20>=5,"Yes","No (under 5 units)")) -> Yes | AA20: =IF(U20<>"",(U20-Scoring!$B$3)/365.25,IF(N20="","",IF(N20<Scoring!$B$12,"",(DATE(N20+Scoring!$B$13,12,31)-Scoring!$B$3)/365.25))) -> 1.2457221 | AB20: =IF(T20="Y",0,IF(OR(D20="Expired (verified)",D20="Expiring: notice window (verified)",D20="Expiring: 10-yr horizon (verified)",D20="Past 30-yr mark (verify)",D20="30-yr mark: notice window (est.)",D20="Year-15 window"),1,0)+IF(ISNUMBER(O20),IF(O20>=Scoring!$B$10,1,0),0)+IF(AND(ISNUMBER(L20),ISNUMBER(J20)),IF(J20>0,IF(L20/J20>=Scoring!$B$11,1,0),0),0)+IF(ISNUMBER(Z20),MIN(Z20,3),0)) -> 2 | AC20: =IF(AB20>=3,Scoring!$C$24,IF(AB20=2,Scoring!$C$23,IF(AB20=1,Scoring!$C$22,0))) -> 18 | AD20: =IF(T20="Y",0,IF(ISNUMBER(X20),IF(X20>0.7,Scoring!$C$25,IF(X20>=0.5,Scoring!$C$26,IF(X20>=0.3,Scoring!$C$27,Scoring!$C$28))),Scoring!$C$29)) -> 10 | AE20: =IF(D20="Expiring: notice window (verified)",Scoring!$C$30,IF(OR(D20="Expired (verified)",D20="30-yr mark: notice window (est.)",D20="Year-15 window"),Scoring!$C$31,IF(D20="Expiring: 10-yr horizon (verified)",Scoring!$C$32,IF(D20="Past 30-yr mark (verify)",Scoring!$C$33,IF(OR(D20="Credit period",D20="Superseded record"),Scoring!$C$35,Scoring!$C$34))))) -> 14 | AF20: =IF(T20="Y",0,IF(ISNUMBER(V20),IF(Scoring!$B$4-V20>15,Scoring!$C$36,IF(Scoring!$B$4-V20>=10,Scoring!$C$37,IF(Scoring!$B$4-V20>=5,Scoring!$C$38,Scoring!$C$39))),IF(OR(N20="",D20="Out of program"),Scoring!$C$40,IF(O20>15,Scoring!$C$36,IF(O20>=10,Scoring!$C$37,IF(O20>=5,Scoring!$C$38,Scoring!$C$39)))))) -> 15 | AG20: =IF(T20="Y",0,IF(Y20="Y",Scoring!$C$41,IF(ISNUMBER(O20),IF(O20>=25,Scoring!$C$42,IF(O20>=15,Scoring!$C$43,Scoring!$C$44)),Scoring!$C$44))) -> 8 | AH20: =IF(T20="Y",0,IF(W20="",Scoring!$C$49,IFERROR(VLOOKUP(W20,Scoring!$B$45:$C$48,2,FALSE()),Scoring!$C$49))) -> 5 | AI20: =C20+IF(ISNUMBER(J20),J20,0)/100000+(10000-ROW())/1000000000 -> 70.00145
A21: =RANK(AI21,$AI$2:$AI$755) -> 20 | B21: =IF(T21="Y","Superseded",IF(C21>=Scoring!$B$16,"Immediate",IF(C21>=Scoring!$B$17,"This week",IF(C21>=Scoring!$B$18,"Nurture","Low")))) -> This week | C21: =SUM(AC21:AH21) -> 70 | D21: =IF(T21="Y","Superseded record",IF(AND(U21<>"",AA21<0),"Expired (verified)",IF(AND(U21<>"",AA21<=Scoring!$B$5),"Expiring: notice window (verified)",IF(AND(U21<>"",AA21<=Scoring!$B$6),"Expiring: 10-yr horizon (verified)",IF(M21="No Longer Monitored","Out of program",IF(N21="","Unknown vintage",IF(N21<Scoring!$B$12,"Pre-1990, still listed",IF(AND(U21="",AA21<0),"Past 30-yr mark (verify)",IF(AND(U21="",AA21<=Scoring!$B$5),"30-yr mark: notice window (est.)",IF(AND(O21>=Scoring!$B$7,O21<=Scoring!$B$8),"Year-15 window",IF(O21>=Scoring!$B$9,"Recap window",IF(O21>=11,"Late compliance","Credit period")))))))))))) -> 30-yr mark: notice window (est.) | E21: ORA19999167 | F21: YARDS AT UNION STATION B | G21: 945 NW NAITO PKWY | H21: PORTLAND | I21: 97209 | J21: 139 | K21: 136 | L21: =IF(OR(J21="",K21=""),"",MAX(J21-K21,0)) -> 3 | M21: Not Indicated | N21: 1999 | O21: =IF(N21="","",Scoring!$B$4-N21) -> 27 | P21: =IF(N21="","",N21+14) -> 2013 | Q21: =IF(N21="","",IF(N21<Scoring!$B$12,"n/a (pre-1990)",N21+Scoring!$B$13)) -> 2028 | R21: =IF(J21="","Unknown",IF(J21>=5,"Yes","No (under 5 units)")) -> Yes | S21: Shares address with ORA19989127 (phase, resyndication or duplicate) | AA21: =IF(U21<>"",(U21-Scoring!$B$3)/365.25,IF(N21="","",IF(N21<Scoring!$B$12,"",(DATE(N21+Scoring!$B$13,12,31)-Scoring!$B$3)/365.25))) -> 2.2477755 | AB21: =IF(T21="Y",0,IF(OR(D21="Expired (verified)",D21="Expiring: notice window (verified)",D21="Expiring: 10-yr horizon (verified)",D21="Past 30-yr mark (verify)",D21="30-yr mark: notice window (est.)",D21="Year-15 window"),1,0)+IF(ISNUMBER(O21),IF(O21>=Scoring!$B$10,1,0),0)+IF(AND(ISNUMBER(L21),ISNUMBER(J21)),IF(J21>0,IF(L21/J21>=Scoring!$B$11,1,0),0),0)+IF(ISNUMBER(Z21),MIN(Z21,3),0)) -> 2 | AC21: =IF(AB21>=3,Scoring!$C$24,IF(AB21=2,Scoring!$C$23,IF(AB21=1,Scoring!$C$22,0))) -> 18 | AD21: =IF(T21="Y",0,IF(ISNUMBER(X21),IF(X21>0.7,Scoring!$C$25,IF(X21>=0.5,Scoring!$C$26,IF(X21>=0.3,Scoring!$C$27,Scoring!$C$28))),Scoring!$C$29)) -> 10 | AE21: =IF(D21="Expiring: notice window (verified)",Scoring!$C$30,IF(OR(D21="Expired (verified)",D21="30-yr mark: notice window (est.)",D21="Year-15 window"),Scoring!$C$31,IF(D21="Expiring: 10-yr horizon (verified)",Scoring!$C$32,IF(D21="Past 30-yr mark (verify)",Scoring!$C$33,IF(OR(D21="Credit period",D21="Superseded record"),Scoring!$C$35,Scoring!$C$34))))) -> 14 | AF21: =IF(T21="Y",0,IF(ISNUMBER(V21),IF(Scoring!$B$4-V21>15,Scoring!$C$36,IF(Scoring!$B$4-V21>=10,Scoring!$C$37,IF(Scoring!$B$4-V21>=5,Scoring!$C$38,Scoring!$C$39))),IF(OR(N21="",D21="Out of program"),Scoring!$C$40,IF(O21>15,Scoring!$C$36,IF(O21>=10,Scoring!$C$37,IF(O21>=5,Scoring!$C$38,Scoring!$C$39)))))) -> 15 | AG21: =IF(T21="Y",0,IF(Y21="Y",Scoring!$C$41,IF(ISNUMBER(O21),IF(O21>=25,Scoring!$C$42,IF(O21>=15,Scoring!$C$43,Scoring!$C$44)),Scoring!$C$44))) -> 8 | AH21: =IF(T21="Y",0,IF(W21="",Scoring!$C$49,IFERROR(VLOOKUP(W21,Scoring!$B$45:$C$48,2,FALSE()),Scoring!$C$49))) -> 5 | AI21: =C21+IF(ISNUMBER(J21),J21,0)/100000+(10000-ROW())/1000000000 -> 70.0014
A22: =RANK(AI22,$AI$2:$AI$755) -> 21 | B22: =IF(T22="Y","Superseded",IF(C22>=Scoring!$B$16,"Immediate",IF(C22>=Scoring!$B$17,"This week",IF(C22>=Scoring!$B$18,"Nurture","Low")))) -> This week | C22: =SUM(AC22:AH22) -> 70 | D22: =IF(T22="Y","Superseded record",IF(AND(U22<>"",AA22<0),"Expired (verified)",IF(AND(U22<>"",AA22<=Scoring!$B$5),"Expiring: notice window (verified)",IF(AND(U22<>"",AA22<=Scoring!$B$6),"Expiring: 10-yr horizon (verified)",IF(M22="No Longer Monitored","Out of program",IF(N22="","Unknown vintage",IF(N22<Scoring!$B$12,"Pre-1990, still listed",IF(AND(U22="",AA22<0),"Past 30-yr mark (verify)",IF(AND(U22="",AA22<=Scoring!$B$5),"30-yr mark: notice window (est.)",IF(AND(O22>=Scoring!$B$7,O22<=Scoring!$B$8),"Year-15 window",IF(O22>=Scoring!$B$9,"Recap window",IF(O22>=11,"Late compliance","Credit period")))))))))))) -> 30-yr mark: notice window (est.) | E22: ORA19980025 | F22: BETHANY MEADOWS II | G22: 16145 NW SPARTAN WAY | H22: PORTLAND | I22: 97229 | J22: 132 | K22: 132 | L22: =IF(OR(J22="",K22=""),"",MAX(J22-K22,0)) -> 0 | M22: Not Indicated | N22: 1998 | O22: =IF(N22="","",Scoring!$B$4-N22) -> 28 | P22: =IF(N22="","",N22+14) -> 2012 | Q22: =IF(N22="","",IF(N22<Scoring!$B$12,"n/a (pre-1990)",N22+Scoring!$B$13)) -> 2027 | R22: =IF(J22="","Unknown",IF(J22>=5,"Yes","No (under 5 units)")) -> Yes | AA22: =IF(U22<>"",(U22-Scoring!$B$3)/365.25,IF(N22="","",IF(N22<Scoring!$B$12,"",(DATE(N22+Scoring!$B$13,12,31)-Scoring!$B$3)/365.25))) -> 1.2457221 | AB22: =IF(T22="Y",0,IF(OR(D22="Expired (verified)",D22="Expiring: notice window (verified)",D22="Expiring: 10-yr horizon (verified)",D22="Past 30-yr mark (verify)",D22="30-yr mark: notice window (est.)",D22="Year-15 window"),1,0)+IF(ISNUMBER(O22),IF(O22>=Scoring!$B$10,1,0),0)+IF(AND(ISNUMBER(L22),ISNUMBER(J22)),IF(J22>0,IF(L22/J22>=Scoring!$B$11,1,0),0),0)+IF(ISNUMBER(Z22),MIN(Z22,3),0)) -> 2 | AC22: =IF(AB22>=3,Scoring!$C$24,IF(AB22=2,Scoring!$C$23,IF(AB22=1,Scoring!$C$22,0))) -> 18 | AD22: =IF(T22="Y",0,IF(ISNUMBER(X22),IF(X22>0.7,Scoring!$C$25,IF(X22>=0.5,Scoring!$C$26,IF(X22>=0.3,Scoring!$C$27,Scoring!$C$28))),Scoring!$C$29)) -> 10 | AE22: =IF(D22="Expiring: notice window (verified)",Scoring!$C$30,IF(OR(D22="Expired (verified)",D22="30-yr mark: notice window (est.)",D22="Year-15 window"),Scoring!$C$31,IF(D22="Expiring: 10-yr horizon (verified)",Scoring!$C$32,IF(D22="Past 30-yr mark (verify)",Scoring!$C$33,IF(OR(D22="Credit period",D22="Superseded record"),Scoring!$C$35,Scoring!$C$34))))) -> 14 | AF22: =IF(T22="Y",0,IF(ISNUMBER(V22),IF(Scoring!$B$4-V22>15,Scoring!$C$36,IF(Scoring!$B$4-V22>=10,Scoring!$C$37,IF(Scoring!$B$4-V22>=5,Scoring!$C$38,Scoring!$C$39))),IF(OR(N22="",D22="Out of program"),Scoring!$C$40,IF(O22>15,Scoring!$C$36,IF(O22>=10,Scoring!$C$37,IF(O22>=5,Scoring!$C$38,Scoring!$C$39)))))) -> 15 | AG22: =IF(T22="Y",0,IF(Y22="Y",Scoring!$C$41,IF(ISNUMBER(O22),IF(O22>=25,Scoring!$C$42,IF(O22>=15,Scoring!$C$43,Scoring!$C$44)),Scoring!$C$44))) -> 8 | AH22: =IF(T22="Y",0,IF(W22="",Scoring!$C$49,IFERROR(VLOOKUP(W22,Scoring!$B$45:$C$48,2,FALSE()),Scoring!$C$49))) -> 5 | AI22: =C22+IF(ISNUMBER(J22),J22,0)/100000+(10000-ROW())/1000000000 -> 70.00133
A23: =RANK(AI23,$AI$2:$AI$755) -> 22 | B23: =IF(T23="Y","Superseded",IF(C23>=Scoring!$B$16,"Immediate",IF(C23>=Scoring!$B$17,"This week",IF(C23>=Scoring!$B$18,"Nurture","Low")))) -> This week | C23: =SUM(AC23:AH23) -> 70 | D23: =IF(T23="Y","Superseded record",IF(AND(U23<>"",AA23<0),"Expired (verified)",IF(AND(U23<>"",AA23<=Scoring!$B$5),"Expiring: notice window (verified)",IF(AND(U23<>"",AA23<=Scoring!$B$6),"Expiring: 10-yr horizon (verified)",IF(M23="No Longer Monitored","Out of program",IF(N23="","Unknown vintage",IF(N23<Scoring!$B$12,"Pre-1990, still listed",IF(AND(U23="",AA23<0),"Past 30-yr mark (verify)",IF(AND(U23="",AA23<=Scoring!$B$5),"30-yr mark: notice window (est.)",IF(AND(O23>=Scoring!$B$7,O23<=Scoring!$B$8),"Year-15 window",IF(O23>=Scoring!$B$9,"Recap window",IF(O23>=11,"Late compliance","Credit period")))))))))))) -> 30-yr mark: notice window (est.) | E23: ORA19980050 | F23: CEDARWEST APTS | G23: 825 WATT WAY | H23: BEND | I23: 97701 | J23: 121 | L23: =IF(OR(J23="",K23=""),"",MAX(J23-K23,0)) | M23: Not Indicated | N23: 1998 | O23: =IF(N23="","",Scoring!$B$4-N23) -> 28 | P23: =IF(N23="","",N23+14) -> 2012 | Q23: =IF(N23="","",IF(N23<Scoring!$B$12,"n/a (pre-1990)",N23+Scoring!$B$13)) -> 2027 | R23: =IF(J23="","Unknown",IF(J23>=5,"Yes","No (under 5 units)")) -> Yes | AA23: =IF(U23<>"",(U23-Scoring!$B$3)/365.25,IF(N23="","",IF(N23<Scoring!$B$12,"",(DATE(N23+Scoring!$B$13,12,31)-Scoring!$B$3)/365.25))) -> 1.2457221 | AB23: =IF(T23="Y",0,IF(OR(D23="Expired (verified)",D23="Expiring: notice window (verified)",D23="Expiring: 10-yr horizon (verified)",D23="Past 30-yr mark (verify)",D23="30-yr mark: notice window (est.)",D23="Year-15 window"),1,0)+IF(ISNUMBER(O23),IF(O23>=Scoring!$B$10,1,0),0)+IF(AND(ISNUMBER(L23),ISNUMBER(J23)),IF(J23>0,IF(L23/J23>=Scoring!$B$11,1,0),0),0)+IF(ISNUMBER(Z23),MIN(Z23,3),0)) -> 2 | AC23: =IF(AB23>=3,Scoring!$C$24,IF(AB23=2,Scoring!$C$23,IF(AB23=1,Scoring!$C$22,0))) -> 18 | AD23: =IF(T23="Y",0,IF(ISNUMBER(X23),IF(X23>0.7,Scoring!$C$25,IF(X23>=0.5,Scoring!$C$26,IF(X23>=0.3,Scoring!$C$27,Scoring!$C$28))),Scoring!$C$29)) -> 10 | AE23: =IF(D23="Expiring: notice window (verified)",Scoring!$C$30,IF(OR(D23="Expired (verified)",D23="30-yr mark: notice window (est.)",D23="Year-15 window"),Scoring!$C$31,IF(D23="Expiring: 10-yr horizon (verified)",Scoring!$C$32,IF(D23="Past 30-yr mark (verify)",Scoring!$C$33,IF(OR(D23="Credit period",D23="Superseded record"),Scoring!$C$35,Scoring!$C$34))))) -> 14 | AF23: =IF(T23="Y",0,IF(ISNUMBER(V23),IF(Scoring!$B$4-V23>15,Scoring!$C$36,IF(Scoring!$B$4-V23>=10,Scoring!$C$37,IF(Scoring!$B$4-V23>=5,Scoring!$C$38,Scoring!$C$39))),IF(OR(N23="",D23="Out of program"),Scoring!$C$40,IF(O23>15,Scoring!$C$36,IF(O23>=10,Scoring!$C$37,IF(O23>=5,Scoring!$C$38,Scoring!$C$39)))))) -> 15 | AG23: =IF(T23="Y",0,IF(Y23="Y",Scoring!$C$41,IF(ISNUMBER(O23),IF(O23>=25,Scoring!$C$42,IF(O23>=15,Scoring!$C$43,Scoring!$C$44)),Scoring!$C$44))) -> 8 | AH23: =IF(T23="Y",0,IF(W23="",Scoring!$C$49,IFERROR(VLOOKUP(W23,Scoring!$B$45:$C$48,2,FALSE()),Scoring!$C$49))) -> 5 | AI23: =C23+IF(ISNUMBER(J23),J23,0)/100000+(10000-ROW())/1000000000 -> 70.00122
A24: =RANK(AI24,$AI$2:$AI$755) -> 23 | B24: =IF(T24="Y","Superseded",IF(C24>=Scoring!$B$16,"Immediate",IF(C24>=Scoring!$B$17,"This week",IF(C24>=Scoring!$B$18,"Nurture","Low")))) -> This week | C24: =SUM(AC24:AH24) -> 70 | D24: =IF(T24="Y","Superseded record",IF(AND(U24<>"",AA24<0),"Expired (verified)",IF(AND(U24<>"",AA24<=Scoring!$B$5),"Expiring: notice window (verified)",IF(AND(U24<>"",AA24<=Scoring!$B$6),"Expiring: 10-yr horizon (verified)",IF(M24="No Longer Monitored","Out of program",IF(N24="","Unknown vintage",IF(N24<Scoring!$B$12,"Pre-1990, still listed",IF(AND(U24="",AA24<0),"Past 30-yr mark (verify)",IF(AND(U24="",AA24<=Scoring!$B$5),"30-yr mark: notice window (est.)",IF(AND(O24>=Scoring!$B$7,O24<=Scoring!$B$8),"Year-15 window",IF(O24>=Scoring!$B$9,"Recap window",IF(O24>=11,"Late compliance","Credit period")))))))))))) -> 30-yr mark: notice window (est.) | E24: ORA19970135 | F24: WILLOW CREEK COMMONS | G24: 19145 SW ALEXANDER ST | H24: ALOHA | I24: 97003 | J24: 120 | K24: 120 | L24: =IF(OR(J24="",K24=""),"",MAX(J24-K24,0)) -> 0 | M24: Not Indicated | N24: 1997 | O24: =IF(N24="","",Scoring!$B$4-N24) -> 29 | P24: =IF(N24="","",N24+14) -> 2011 | Q24: =IF(N24="","",IF(N24<Scoring!$B$12,"n/a (pre-1990)",N24+Scoring!$B$13)) -> 2026 | R24: =IF(J24="","Unknown",IF(J24>=5,"Yes","No (under 5 units)")) -> Yes | AA24: =IF(U24<>"",(U24-Scoring!$B$3)/365.25,IF(N24="","",IF(N24<Scoring!$B$12,"",(DATE(N24+Scoring!$B$13,12,31)-Scoring!$B$3)/365.25))) -> 0.24640657 | AB24: =IF(T24="Y",0,IF(OR(D24="Expired (verified)",D24="Expiring: notice window (verified)",D24="Expiring: 10-yr horizon (verified)",D24="Past 30-yr mark (verify)",D24="30-yr mark: notice window (est.)",D24="Year-15 window"),1,0)+IF(ISNUMBER(O24),IF(O24>=Scoring!$B$10,1,0),0)+IF(AND(ISNUMBER(L24),ISNUMBER(J24)),IF(J24>0,IF(L24/J24>=Scoring!$B$11,1,0),0),0)+IF(ISNUMBER(Z24),MIN(Z24,3),0)) -> 2 | AC24: =IF(AB24>=3,Scoring!$C$24,IF(AB24=2,Scoring!$C$23,IF(AB24=1,Scoring!$C$22,0))) -> 18 | AD24: =IF(T24="Y",0,IF(ISNUMBER(X24),IF(X24>0.7,Scoring!$C$25,IF(X24>=0.5,Scoring!$C$26,IF(X24>=0.3,Scoring!$C$27,Scoring!$C$28))),Scoring!$C$29)) -> 10 | AE24: =IF(D24="Expiring: notice window (verified)",Scoring!$C$30,IF(OR(D24="Expired (verified)",D24="30-yr mark: notice window (est.)",D24="Year-15 window"),Scoring!$C$31,IF(D24="Expiring: 10-yr horizon (verified)",Scoring!$C$32,IF(D24="Past 30-yr mark (verify)",Scoring!$C$33,IF(OR(D24="Credit period",D24="Superseded record"),Scoring!$C$35,Scoring!$C$34))))) -> 14 | AF24: =IF(T24="Y",0,IF(ISNUMBER(V24),IF(Scoring!$B$4-V24>15,Scoring!$C$36,IF(Scoring!$B$4-V24>=10,Scoring!$C$37,IF(Scoring!$B$4-V24>=5,Scoring!$C$38,Scoring!$C$39))),IF(OR(N24="",D24="Out of program"),Scoring!$C$40,IF(O24>15,Scoring!$C$36,IF(O24>=10,Scoring!$C$37,IF(O24>=5,Scoring!$C$38,Scoring!$C$39)))))) -> 15 | AG24: =IF(T24="Y",0,IF(Y24="Y",Scoring!$C$41,IF(ISNUMBER(O24),IF(O24>=25,Scoring!$C$42,IF(O24>=15,Scoring!$C$43,Scoring!$C$44)),Scoring!$C$44))) -> 8 | AH24: =IF(T24="Y",0,IF(W24="",Scoring!$C$49,IFERROR(VLOOKUP(W24,Scoring!$B$45:$C$48,2,FALSE()),Scoring!$C$49))) -> 5 | AI24: =C24+IF(ISNUMBER(J24),J24,0)/100000+(10000-ROW())/1000000000 -> 70.00121
A25: =RANK(AI25,$AI$2:$AI$755) -> 24 | B25: =IF(T25="Y","Superseded",IF(C25>=Scoring!$B$16,"Immediate",IF(C25>=Scoring!$B$17,"This week",IF(C25>=Scoring!$B$18,"Nurture","Low")))) -> This week | C25: =SUM(AC25:AH25) -> 70 | D25: =IF(T25="Y","Superseded record",IF(AND(U25<>"",AA25<0),"Expired (verified)",IF(AND(U25<>"",AA25<=Scoring!$B$5),"Expiring: notice window (verified)",IF(AND(U25<>"",AA25<=Scoring!$B$6),"Expiring: 10-yr horizon (verified)",IF(M25="No Longer Monitored","Out of program",IF(N25="","Unknown vintage",IF(N25<Scoring!$B$12,"Pre-1990, still listed",IF(AND(U25="",AA25<0),"Past 30-yr mark (verify)",IF(AND(U25="",AA25<=Scoring!$B$5),"30-yr mark: notice window (est.)",IF(AND(O25>=Scoring!$B$7,O25<=Scoring!$B$8),"Year-15 window",IF(O25>=Scoring!$B$9,"Recap window",IF(O25>=11,"Late compliance","Credit period")))))))))))) -> 30-yr mark: notice window (est.) | E25: ORA19980105 | F25: STADIUM STATION | G25: 737 SW 17TH AVE | H25: PORTLAND | I25: 97205 | J25: 114 | K25: 114 | L25: =IF(OR(J25="",K25=""),"",MAX(J25-K25,0)) -> 0 | M25: Not Indicated | N25: 1998 | O25: =IF(N25="","",Scoring!$B$4-N25) -> 28 | P25: =IF(N25="","",N25+14) -> 2012 | Q25: =IF(N25="","",IF(N25<Scoring!$B$12,"n/a (pre-1990)",N25+Scoring!$B$13)) -> 2027 | R25: =IF(J25="","Unknown",IF(J25>=5,"Yes","No (under 5 units)")) -> Yes | AA25: =IF(U25<>"",(U25-Scoring!$B$3)/365.25,IF(N25="","",IF(N25<Scoring!$B$12,"",(DATE(N25+Scoring!$B$13,12,31)-Scoring!$B$3)/365.25))) -> 1.2457221 | AB25: =IF(T25="Y",0,IF(OR(D25="Expired (verified)",D25="Expiring: notice window (verified)",D25="Expiring: 10-yr horizon (verified)",D25="Past 30-yr mark (verify)",D25="30-yr mark: notice window (est.)",D25="Year-15 window"),1,0)+IF(ISNUMBER(O25),IF(O25>=Scoring!$B$10,1,0),0)+IF(AND(ISNUMBER(L25),ISNUMBER(J25)),IF(J25>0,IF(L25/J25>=Scoring!$B$11,1,0),0),0)+IF(ISNUMBER(Z25),MIN(Z25,3),0)) -> 2 | AC25: =IF(AB25>=3,Scoring!$C$24,IF(AB25=2,Scoring!$C$23,IF(AB25=1,Scoring!$C$22,0))) -> 18 | AD25: =IF(T25="Y",0,IF(ISNUMBER(X25),IF(X25>0.7,Scoring!$C$25,IF(X25>=0.5,Scoring!$C$26,IF(X25>=0.3,Scoring!$C$27,Scoring!$C$28))),Scoring!$C$29)) -> 10 | AE25: =IF(D25="Expiring: notice window (verified)",Scoring!$C$30,IF(OR(D25="Expired (verified)",D25="30-yr mark: notice window (est.)",D25="Year-15 window"),Scoring!$C$31,IF(D25="Expiring: 10-yr horizon (verified)",Scoring!$C$32,IF(D25="Past 30-yr mark (verify)",Scoring!$C$33,IF(OR(D25="Credit period",D25="Superseded record"),Scoring!$C$35,Scoring!$C$34))))) -> 14 | AF25: =IF(T25="Y",0,IF(ISNUMBER(V25),IF(Scoring!$B$4-V25>15,Scoring!$C$36,IF(Scoring!$B$4-V25>=10,Scoring!$C$37,IF(Scoring!$B$4-V25>=5,Scoring!$C$38,Scoring!$C$39))),IF(OR(N25="",D25="Out of program"),Scoring!$C$40,IF(O25>15,Scoring!$C$36,IF(O25>=10,Scoring!$C$37,IF(O25>=5,Scoring!$C$38,Scoring!$C$39)))))) -> 15 | AG25: =IF(T25="Y",0,IF(Y25="Y",Scoring!$C$41,IF(ISNUMBER(O25),IF(O25>=25,Scoring!$C$42,IF(O25>=15,Scoring!$C$43,Scoring!$C$44)),Scoring!$C$44))) -> 8 | AH25: =IF(T25="Y",0,IF(W25="",Scoring!$C$49,IFERROR(VLOOKUP(W25,Scoring!$B$45:$C$48,2,FALSE()),Scoring!$C$49))) -> 5 | AI25: =C25+IF(ISNUMBER(J25),J25,0)/100000+(10000-ROW())/1000000000 -> 70.00115
A26: =RANK(AI26,$AI$2:$AI$755) -> 25 | B26: =IF(T26="Y","Superseded",IF(C26>=Scoring!$B$16,"Immediate",IF(C26>=Scoring!$B$17,"This week",IF(C26>=Scoring!$B$18,"Nurture","Low")))) -> This week | C26: =SUM(AC26:AH26) -> 70 | D26: =IF(T26="Y","Superseded record",IF(AND(U26<>"",AA26<0),"Expired (verified)",IF(AND(U26<>"",AA26<=Scoring!$B$5),"Expiring: notice window (verified)",IF(AND(U26<>"",AA26<=Scoring!$B$6),"Expiring: 10-yr horizon (verified)",IF(M26="No Longer Monitored","Out of program",IF(N26="","Unknown vintage",IF(N26<Scoring!$B$12,"Pre-1990, still listed",IF(AND(U26="",AA26<0),"Past 30-yr mark (verify)",IF(AND(U26="",AA26<=Scoring!$B$5),"30-yr mark: notice window (est.)",IF(AND(O26>=Scoring!$B$7,O26<=Scoring!$B$8),"Year-15 window",IF(O26>=Scoring!$B$9,"Recap window",IF(O26>=11,"Late compliance","Credit period")))))))))))) -> 30-yr mark: notice window (est.) | E26: ORA19970085 | F26: THE WESTSHORE | G26: 222 SW PINE ST | H26: PORTLAND | I26: 97204 | J26: 113 | K26: 113 | L26: =IF(OR(J26="",K26=""),"",MAX(J26-K26,0)) -> 0 | M26: Not Indicated | N26: 1997 | O26: =IF(N26="","",Scoring!$B$4-N26) -> 29 | P26: =IF(N26="","",N26+14) -> 2011 | Q26: =IF(N26="","",IF(N26<Scoring!$B$12,"n/a (pre-1990)",N26+Scoring!$B$13)) -> 2026 | R26: =IF(J26="","Unknown",IF(J26>=5,"Yes","No (under 5 units)")) -> Yes | AA26: =IF(U26<>"",(U26-Scoring!$B$3)/365.25,IF(N26="","",IF(N26<Scoring!$B$12,"",(DATE(N26+Scoring!$B$13,12,31)-Scoring!$B$3)/365.25))) -> 0.24640657 | AB26: =IF(T26="Y",0,IF(OR(D26="Expired (verified)",D26="Expiring: notice window (verified)",D26="Expiring: 10-yr horizon (verified)",D26="Past 30-yr mark (verify)",D26="30-yr mark: notice window (est.)",D26="Year-15 window"),1,0)+IF(ISNUMBER(O26),IF(O26>=Scoring!$B$10,1,0),0)+IF(AND(ISNUMBER(L26),ISNUMBER(J26)),IF(J26>0,IF(L26/J26>=Scoring!$B$11,1,0),0),0)+IF(ISNUMBER(Z26),MIN(Z26,3),0)) -> 2 | AC26: =IF(AB26>=3,Scoring!$C$24,IF(AB26=2,Scoring!$C$23,IF(AB26=1,Scoring!$C$22,0))) -> 18 | AD26: =IF(T26="Y",0,IF(ISNUMBER(X26),IF(X26>0.7,Scoring!$C$25,IF(X26>=0.5,Scoring!$C$26,IF(X26>=0.3,Scoring!$C$27,Scoring!$C$28))),Scoring!$C$29)) -> 10 | AE26: =IF(D26="Expiring: notice window (verified)",Scoring!$C$30,IF(OR(D26="Expired (verified)",D26="30-yr mark: notice window (est.)",D26="Year-15 window"),Scoring!$C$31,IF(D26="Expiring: 10-yr horizon (verified)",Scoring!$C$32,IF(D26="Past 30-yr mark (verify)",Scoring!$C$33,IF(OR(D26="Credit period",D26="Superseded record"),Scoring!$C$35,Scoring!$C$34))))) -> 14 | AF26: =IF(T26="Y",0,IF(ISNUMBER(V26),IF(Scoring!$B$4-V26>15,Scoring!$C$36,IF(Scoring!$B$4-V26>=10,Scoring!$C$37,IF(Scoring!$B$4-V26>=5,Scoring!$C$38,Scoring!$C$39))),IF(OR(N26="",D26="Out of program"),Scoring!$C$40,IF(O26>15,Scoring!$C$36,IF(O26>=10,Scoring!$C$37,IF(O26>=5,Scoring!$C$38,Scoring!$C$39)))))) -> 15 | AG26: =IF(T26="Y",0,IF(Y26="Y",Scoring!$C$41,IF(ISNUMBER(O26),IF(O26>=25,Scoring!$C$42,IF(O26>=15,Scoring!$C$43,Scoring!$C$44)),Scoring!$C$44))) -> 8 | AH26: =IF(T26="Y",0,IF(W26="",Scoring!$C$49,IFERROR(VLOOKUP(W26,Scoring!$B$45:$C$48,2,FALSE()),Scoring!$C$49))) -> 5 | AI26: =C26+IF(ISNUMBER(J26),J26,0)/100000+(10000-ROW())/1000000000 -> 70.00114
A27: =RANK(AI27,$AI$2:$AI$755) -> 26 | B27: =IF(T27="Y","Superseded",IF(C27>=Scoring!$B$16,"Immediate",IF(C27>=Scoring!$B$17,"This week",IF(C27>=Scoring!$B$18,"Nurture","Low")))) -> This week | C27: =SUM(AC27:AH27) -> 70 | D27: =IF(T27="Y","Superseded record",IF(AND(U27<>"",AA27<0),"Expired (verified)",IF(AND(U27<>"",AA27<=Scoring!$B$5),"Expiring: notice window (verified)",IF(AND(U27<>"",AA27<=Scoring!$B$6),"Expiring: 10-yr horizon (verified)",IF(M27="No Longer Monitored","Out of program",IF(N27="","Unknown vintage",IF(N27<Scoring!$B$12,"Pre-1990, still listed",IF(AND(U27="",AA27<0),"Past 30-yr mark (verify)",IF(AND(U27="",AA27<=Scoring!$B$5),"30-yr mark: notice window (est.)",IF(AND(O27>=Scoring!$B$7,O27<=Scoring!$B$8),"Year-15 window",IF(O27>=Scoring!$B$9,"Recap window",IF(O27>=11,"Late compliance","Credit period")))))))))))) -> 30-yr mark: notice window (est.) | E27: ORA19970120 | F27: TERRACE VIEW APTS | G27: 6685 SW SAGERT ST | H27: TUALATIN | I27: 97062 | J27: 100 | L27: =IF(OR(J27="",K27=""),"",MAX(J27-K27,0)) | M27: Not Indicated | N27: 1997 | O27: =IF(N27="","",Scoring!$B$4-N27) -> 29 | P27: =IF(N27="","",N27+14) -> 2011 | Q27: =IF(N27="","",IF(N27<Scoring!$B$12,"n/a (pre-1990)",N27+Scoring!$B$13)) -> 2026 | R27: =IF(J27="","Unknown",IF(J27>=5,"Yes","No (under 5 units)")) -> Yes | AA27: =IF(U27<>"",(U27-Scoring!$B$3)/365.25,IF(N27="","",IF(N27<Scoring!$B$12,"",(DATE(N27+Scoring!$B$13,12,31)-Scoring!$B$3)/365.25))) -> 0.24640657 | AB27: =IF(T27="Y",0,IF(OR(D27="Expired (verified)",D27="Expiring: notice window (verified)",D27="Expiring: 10-yr horizon (verified)",D27="Past 30-yr mark (verify)",D27="30-yr mark: notice window (est.)",D27="Year-15 window"),1,0)+IF(ISNUMBER(O27),IF(O27>=Scoring!$B$10,1,0),0)+IF(AND(ISNUMBER(L27),ISNUMBER(J27)),IF(J27>0,IF(L27/J27>=Scoring!$B$11,1,0),0),0)+IF(ISNUMBER(Z27),MIN(Z27,3),0)) -> 2 | AC27: =IF(AB27>=3,Scoring!$C$24,IF(AB27=2,Scoring!$C$23,IF(AB27=1,Scoring!$C$22,0))) -> 18 | AD27: =IF(T27="Y",0,IF(ISNUMBER(X27),IF(X27>0.7,Scoring!$C$25,IF(X27>=0.5,Scoring!$C$26,IF(X27>=0.3,Scoring!$C$27,Scoring!$C$28))),Scoring!$C$29)) -> 10 | AE27: =IF(D27="Expiring: notice window (verified)",Scoring!$C$30,IF(OR(D27="Expired (verified)",D27="30-yr mark: notice window (est.)",D27="Year-15 window"),Scoring!$C$31,IF(D27="Expiring: 10-yr horizon (verified)",Scoring!$C$32,IF(D27="Past 30-yr mark (verify)",Scoring!$C$33,IF(OR(D27="Credit period",D27="Superseded record"),Scoring!$C$35,Scoring!$C$34))))) -> 14 | AF27: =IF(T27="Y",0,IF(ISNUMBER(V27),IF(Scoring!$B$4-V27>15,Scoring!$C$36,IF(Scoring!$B$4-V27>=10,Scoring!$C$37,IF(Scoring!$B$4-V27>=5,Scoring!$C$38,Scoring!$C$39))),IF(OR(N27="",D27="Out of program"),Scoring!$C$40,IF(O27>15,Scoring!$C$36,IF(O27>=10,Scoring!$C$37,IF(O27>=5,Scoring!$C$38,Scoring!$C$39)))))) -> 15 | AG27: =IF(T27="Y",0,IF(Y27="Y",Scoring!$C$41,IF(ISNUMBER(O27),IF(O27>=25,Scoring!$C$42,IF(O27>=15,Scoring!$C$43,Scoring!$C$44)),Scoring!$C$44))) -> 8 | AH27: =IF(T27="Y",0,IF(W27="",Scoring!$C$49,IFERROR(VLOOKUP(W27,Scoring!$B$45:$C$48,2,FALSE()),Scoring!$C$49))) -> 5 | AI27: =C27+IF(ISNUMBER(J27),J27,0)/100000+(10000-ROW())/1000000000 -> 70.00101
A28: =RANK(AI28,$AI$2:$AI$755) -> 27 | B28: =IF(T28="Y","Superseded",IF(C28>=Scoring!$B$16,"Immediate",IF(C28>=Scoring!$B$17,"This week",IF(C28>=Scoring!$B$18,"Nurture","Low")))) -> This week | C28: =SUM(AC28:AH28) -> 70 | D28: =IF(T28="Y","Superseded record",IF(AND(U28<>"",AA28<0),"Expired (verified)",IF(AND(U28<>"",AA28<=Scoring!$B$5),"Expiring: notice window (verified)",IF(AND(U28<>"",AA28<=Scoring!$B$6),"Expiring: 10-yr horizon (verified)",IF(M28="No Longer Monitored","Out of program",IF(N28="","Unknown vintage",IF(N28<Scoring!$B$12,"Pre-1990, still listed",IF(AND(U28="",AA28<0),"Past 30-yr mark (verify)",IF(AND(U28="",AA28<=Scoring!$B$5),"30-yr mark: notice window (est.)",IF(AND(O28>=Scoring!$B$7,O28<=Scoring!$B$8),"Year-15 window",IF(O28>=Scoring!$B$9,"Recap window",IF(O28>=11,"Late compliance","Credit period")))))))))))) -> 30-yr mark: notice window (est.) | E28: ORA19980090 | F28: PARK AT EMERALD VILLAGE | G28: 1950 N SECOND ST | H28: SPRINGFIELD | I28: 97477 | J28: 96 | K28: 96 | L28: =IF(OR(J28="",K28=""),"",MAX(J28-K28,0)) -> 0 | M28: Not Indicated | N28: 1998 | O28: =IF(N28="","",Scoring!$B$4-N28) -> 28 | P28: =IF(N28="","",N28+14) -> 2012 | Q28: =IF(N28="","",IF(N28<Scoring!$B$12,"n/a (pre-1990)",N28+Scoring!$B$13)) -> 2027 | R28: =IF(J28="","Unknown",IF(J28>=5,"Yes","No (under 5 units)")) -> Yes | AA28: =IF(U28<>"",(U28-Scoring!$B$3)/365.25,IF(N28="","",IF(N28<Scoring!$B$12,"",(DATE(N28+Scoring!$B$13,12,31)-Scoring!$B$3)/365.25))) -> 1.2457221 | AB28: =IF(T28="Y",0,IF(OR(D28="Expired (verified)",D28="Expiring: notice window (verified)",D28="Expiring: 10-yr horizon (verified)",D28="Past 30-yr mark (verify)",D28="30-yr mark: notice window (est.)",D28="Year-15 window"),1,0)+IF(ISNUMBER(O28),IF(O28>=Scoring!$B$10,1,0),0)+IF(AND(ISNUMBER(L28),ISNUMBER(J28)),IF(J28>0,IF(L28/J28>=Scoring!$B$11,1,0),0),0)+IF(ISNUMBER(Z28),MIN(Z28,3),0)) -> 2 | AC28: =IF(AB28>=3,Scoring!$C$24,IF(AB28=2,Scoring!$C$23,IF(AB28=1,Scoring!$C$22,0))) -> 18 | AD28: =IF(T28="Y",0,IF(ISNUMBER(X28),IF(X28>0.7,Scoring!$C$25,IF(X28>=0.5,Scoring!$C$26,IF(X28>=0.3,Scoring!$C$27,Scoring!$C$28))),Scoring!$C$29)) -> 10 | AE28: =IF(D28="Expiring: notice window (verified)",Scoring!$C$30,IF(OR(D28="Expired (verified)",D28="30-yr mark: notice window (est.)",D28="Year-15 window"),Scoring!$C$31,IF(D28="Expiring: 10-yr horizon (verified)",Scoring!$C$32,IF(D28="Past 30-yr mark (verify)",Scoring!$C$33,IF(OR(D28="Credit period",D28="Superseded record"),Scoring!$C$35,Scoring!$C$34))))) -> 14 | AF28: =IF(T28="Y",0,IF(ISNUMBER(V28),IF(Scoring!$B$4-V28>15,Scoring!$C$36,IF(Scoring!$B$4-V28>=10,Scoring!$C$37,IF(Scoring!$B$4-V28>=5,Scoring!$C$38,Scoring!$C$39))),IF(OR(N28="",D28="Out of program"),Scoring!$C$40,IF(O28>15,Scoring!$C$36,IF(O28>=10,Scoring!$C$37,IF(O28>=5,Scoring!$C$38,Scoring!$C$39)))))) -> 15 | AG28: =IF(T28="Y",0,IF(Y28="Y",Scoring!$C$41,IF(ISNUMBER(O28),IF(O28>=25,Scoring!$C$42,IF(O28>=15,Scoring!$C$43,Scoring!$C$44)),Scoring!$C$44))) -> 8 | AH28: =IF(T28="Y",0,IF(W28="",Scoring!$C$49,IFERROR(VLOOKUP(W28,Scoring!$B$45:$C$48,2,FALSE()),Scoring!$C$49))) -> 5 | AI28: =C28+IF(ISNUMBER(J28),J28,0)/100000+(10000-ROW())/1000000000 -> 70.00097
A29: =RANK(AI29,$AI$2:$AI$755) -> 28 | B29: =IF(T29="Y","Superseded",IF(C29>=Scoring!$B$16,"Immediate",IF(C29>=Scoring!$B$17,"This week",IF(C29>=Scoring!$B$18,"Nurture","Low")))) -> This week | C29: =SUM(AC29:AH29) -> 70 | D29: =IF(T29="Y","Superseded record",IF(AND(U29<>"",AA29<0),"Expired (verified)",IF(AND(U29<>"",AA29<=Scoring!$B$5),"Expiring: notice window (verified)",IF(AND(U29<>"",AA29<=Scoring!$B$6),"Expiring: 10-yr horizon (verified)",IF(M29="No Longer Monitored","Out of program",IF(N29="","Unknown vintage",IF(N29<Scoring!$B$12,"Pre-1990, still listed",IF(AND(U29="",AA29<0),"Past 30-yr mark (verify)",IF(AND(U29="",AA29<=Scoring!$B$5),"30-yr mark: notice window (est.)",IF(AND(O29>=Scoring!$B$7,O29<=Scoring!$B$8),"Year-15 window",IF(O29>=Scoring!$B$9,"Recap window",IF(O29>=11,"Late compliance","Credit period")))))))))))) -> 30-yr mark: notice window (est.) | E29: ORA19980070 | F29: GREENBRIAR APTS | G29: 250 S LOCUST ST | H29: CANBY | I29: 97013 | J29: 86 | K29: 86 | L29: =IF(OR(J29="",K29=""),"",MAX(J29-K29,0)) -> 0 | M29: Not Indicated | N29: 1998 | O29: =IF(N29="","",Scoring!$B$4-N29) -> 28 | P29: =IF(N29="","",N29+14) -> 2012 | Q29: =IF(N29="","",IF(N29<Scoring!$B$12,"n/a (pre-1990)",N29+Scoring!$B$13)) -> 2027 | R29: =IF(J29="","Unknown",IF(J29>=5,"Yes","No (under 5 units)")) -> Yes | AA29: =IF(U29<>"",(U29-Scoring!$B$3)/365.25,IF(N29="","",IF(N29<Scoring!$B$12,"",(DATE(N29+Scoring!$B$13,12,31)-Scoring!$B$3)/365.25))) -> 1.2457221 | AB29: =IF(T29="Y",0,IF(OR(D29="Expired (verified)",D29="Expiring: notice window (verified)",D29="Expiring: 10-yr horizon (verified)",D29="Past 30-yr mark (verify)",D29="30-yr mark: notice window (est.)",D29="Year-15 window"),1,0)+IF(ISNUMBER(O29),IF(O29>=Scoring!$B$10,1,0),0)+IF(AND(ISNUMBER(L29),ISNUMBER(J29)),IF(J29>0,IF(L29/J29>=Scoring!$B$11,1,0),0),0)+IF(ISNUMBER(Z29),MIN(Z29,3),0)) -> 2 | AC29: =IF(AB29>=3,Scoring!$C$24,IF(AB29=2,Scoring!$C$23,IF(AB29=1,Scoring!$C$22,0))) -> 18 | AD29: =IF(T29="Y",0,IF(ISNUMBER(X29),IF(X29>0.7,Scoring!$C$25,IF(X29>=0.5,Scoring!$C$26,IF(X29>=0.3,Scoring!$C$27,Scoring!$C$28))),Scoring!$C$29)) -> 10 | AE29: =IF(D29="Expiring: notice window (verified)",Scoring!$C$30,IF(OR(D29="Expired (verified)",D29="30-yr mark: notice window (est.)",D29="Year-15 window"),Scoring!$C$31,IF(D29="Expiring: 10-yr horizon (verified)",Scoring!$C$32,IF(D29="Past 30-yr mark (verify)",Scoring!$C$33,IF(OR(D29="Credit period",D29="Superseded record"),Scoring!$C$35,Scoring!$C$34))))) -> 14 | AF29: =IF(T29="Y",0,IF(ISNUMBER(V29),IF(Scoring!$B$4-V29>15,Scoring!$C$36,IF(Scoring!$B$4-V29>=10,Scoring!$C$37,IF(Scoring!$B$4-V29>=5,Scoring!$C$38,Scoring!$C$39))),IF(OR(N29="",D29="Out of program"),Scoring!$C$40,IF(O29>15,Scoring!$C$36,IF(O29>=10,Scoring!$C$37,IF(O29>=5,Scoring!$C$38,Scoring!$C$39)))))) -> 15 | AG29: =IF(T29="Y",0,IF(Y29="Y",Scoring!$C$41,IF(ISNUMBER(O29),IF(O29>=25,Scoring!$C$42,IF(O29>=15,Scoring!$C$43,Scoring!$C$44)),Scoring!$C$44))) -> 8 | AH29: =IF(T29="Y",0,IF(W29="",Scoring!$C$49,IFERROR(VLOOKUP(W29,Scoring!$B$45:$C$48,2,FALSE()),Scoring!$C$49))) -> 5 | AI29: =C29+IF(ISNUMBER(J29),J29,0)/100000+(10000-ROW())/1000000000 -> 70.00087
A30: =RANK(AI30,$AI$2:$AI$755) -> 29 | B30: =IF(T30="Y","Superseded",IF(C30>=Scoring!$B$16,"Immediate",IF(C30>=Scoring!$B$17,"This week",IF(C30>=Scoring!$B$18,"Nurture","Low")))) -> This week | C30: =SUM(AC30:AH30) -> 70 | D30: =IF(T30="Y","Superseded record",IF(AND(U30<>"",AA30<0),"Expired (verified)",IF(AND(U30<>"",AA30<=Scoring!$B$5),"Expiring: notice window (verified)",IF(AND(U30<>"",AA30<=Scoring!$B$6),"Expiring: 10-yr horizon (verified)",IF(M30="No Longer Monitored","Out of program",IF(N30="","Unknown vintage",IF(N30<Scoring!$B$12,"Pre-1990, still listed",IF(AND(U30="",AA30<0),"Past 30-yr mark (verify)",IF(AND(U30="",AA30<=Scoring!$B$5),"30-yr mark: notice window (est.)",IF(AND(O30>=Scoring!$B$7,O30<=Scoring!$B$8),"Year-15 window",IF(O30>=Scoring!$B$9,"Recap window",IF(O30>=11,"Late compliance","Credit period")))))))))))) -> 30-yr mark: notice window (est.) | E30: ORA19970015 | F30: BELMONT DAIRY | G30: 3340 SE MORRISON ST | H30: PORTLAND | I30: 97214 | J30: 81 | K30: 81 | L30: =IF(OR(J30="",K30=""),"",MAX(J30-K30,0)) -> 0 | M30: Not Indicated | N30: 1997 | O30: =IF(N30="","",Scoring!$B$4-N30) -> 29 | P30: =IF(N30="","",N30+14) -> 2011 | Q30: =IF(N30="","",IF(N30<Scoring!$B$12,"n/a (pre-1990)",N30+Scoring!$B$13)) -> 2026 | R30: =IF(J30="","Unknown",IF(J30>=5,"Yes","No (under 5 units)")) -> Yes | AA30: =IF(U30<>"",(U30-Scoring!$B$3)/365.25,IF(N30="","",IF(N30<Scoring!$B$12,"",(DATE(N30+Scoring!$B$13,12,31)-Scoring!$B$3)/365.25))) -> 0.24640657 | AB30: =IF(T30="Y",0,IF(OR(D30="Expired (verified)",D30="Expiring: notice window (verified)",D30="Expiring: 10-yr horizon (verified)",D30="Past 30-yr mark (verify)",D30="30-yr mark: notice window (est.)",D30="Year-15 window"),1,0)+IF(ISNUMBER(O30),IF(O30>=Scoring!$B$10,1,0),0)+IF(AND(ISNUMBER(L30),ISNUMBER(J30)),IF(J30>0,IF(L30/J30>=Scoring!$B$11,1,0),0),0)+IF(ISNUMBER(Z30),MIN(Z30,3),0)) -> 2 | AC30: =IF(AB30>=3,Scoring!$C$24,IF(AB30=2,Scoring!$C$23,IF(AB30=1,Scoring!$C$22,0))) -> 18 | AD30: =IF(T30="Y",0,IF(ISNUMBER(X30),IF(X30>0.7,Scoring!$C$25,IF(X30>=0.5,Scoring!$C$26,IF(X30>=0.3,Scoring!$C$27,Scoring!$C$28))),Scoring!$C$29)) -> 10 | AE30: =IF(D30="Expiring: notice window (verified)",Scoring!$C$30,IF(OR(D30="Expired (verified)",D30="30-yr mark: notice window (est.)",D30="Year-15 window"),Scoring!$C$31,IF(D30="Expiring: 10-yr horizon (verified)",Scoring!$C$32,IF(D30="Past 30-yr mark (verify)",Scoring!$C$33,IF(OR(D30="Credit period",D30="Superseded record"),Scoring!$C$35,Scoring!$C$34))))) -> 14 | AF30: =IF(T30="Y",0,IF(ISNUMBER(V30),IF(Scoring!$B$4-V30>15,Scoring!$C$36,IF(Scoring!$B$4-V30>=10,Scoring!$C$37,IF(Scoring!$B$4-V30>=5,Scoring!$C$38,Scoring!$C$39))),IF(OR(N30="",D30="Out of program"),Scoring!$C$40,IF(O30>15,Scoring!$C$36,IF(O30>=10,Scoring!$C$37,IF(O30>=5,Scoring!$C$38,Scoring!$C$39)))))) -> 15 | AG30: =IF(T30="Y",0,IF(Y30="Y",Scoring!$C$41,IF(ISNUMBER(O30),IF(O30>=25,Scoring!$C$42,IF(O30>=15,Scoring!$C$43,Scoring!$C$44)),Scoring!$C$44))) -> 8 | AH30: =IF(T30="Y",0,IF(W30="",Scoring!$C$49,IFERROR(VLOOKUP(W30,Scoring!$B$45:$C$48,2,FALSE()),Scoring!$C$49))) -> 5 | AI30: =C30+IF(ISNUMBER(J30),J30,0)/100000+(10000-ROW())/1000000000 -> 70.00082
A31: =RANK(AI31,$AI$2:$AI$755) -> 30 | B31: =IF(T31="Y","Superseded",IF(C31>=Scoring!$B$16,"Immediate",IF(C31>=Scoring!$B$17,"This week",IF(C31>=Scoring!$B$18,"Nurture","Low")))) -> This week | C31: =SUM(AC31:AH31) -> 70 | D31: =IF(T31="Y","Superseded record",IF(AND(U31<>"",AA31<0),"Expired (verified)",IF(AND(U31<>"",AA31<=Scoring!$B$5),"Expiring: notice window (verified)",IF(AND(U31<>"",AA31<=Scoring!$B$6),"Expiring: 10-yr horizon (verified)",IF(M31="No Longer Monitored","Out of program",IF(N31="","Unknown vintage",IF(N31<Scoring!$B$12,"Pre-1990, still listed",IF(AND(U31="",AA31<0),"Past 30-yr mark (verify)",IF(AND(U31="",AA31<=Scoring!$B$5),"30-yr mark: notice window (est.)",IF(AND(O31>=Scoring!$B$7,O31<=Scoring!$B$8),"Year-15 window",IF(O31>=Scoring!$B$9,"Recap window",IF(O31>=11,"Late compliance","Credit period")))))))))))) -> 30-yr mark: notice window (est.) | E31: ORA19990060 | F31: FOREST PARK APTS | G31: 2545 COLUMBIA BLVD | H31: ST HELENS | I31: 97051 | J31: 80 | L31: =IF(OR(J31="",K31=""),"",MAX(J31-K31,0)) | M31: Not Indicated | N31: 1999 | O31: =IF(N31="","",Scoring!$B$4-N31) -> 27 | P31: =IF(N31="","",N31+14) -> 2013 | Q31: =IF(N31="","",IF(N31<Scoring!$B$12,"n/a (pre-1990)",N31+Scoring!$B$13)) -> 2028 | R31: =IF(J31="","Unknown",IF(J31>=5,"Yes","No (under 5 units)")) -> Yes | AA31: =IF(U31<>"",(U31-Scoring!$B$3)/365.25,IF(N31="","",IF(N31<Scoring!$B$12,"",(DATE(N31+Scoring!$B$13,12,31)-Scoring!$B$3)/365.25))) -> 2.2477755 | AB31: =IF(T31="Y",0,IF(OR(D31="Expired (verified)",D31="Expiring: notice window (verified)",D31="Expiring: 10-yr horizon (verified)",D31="Past 30-yr mark (verify)",D31="30-yr mark: notice window (est.)",D31="Year-15 window"),1,0)+IF(ISNUMBER(O31),IF(O31>=Scoring!$B$10,1,0),0)+IF(AND(ISNUMBER(L31),ISNUMBER(J31)),IF(J31>0,IF(L31/J31>=Scoring!$B$11,1,0),0),0)+IF(ISNUMBER(Z31),MIN(Z31,3),0)) -> 2 | AC31: =IF(AB31>=3,Scoring!$C$24,IF(AB31=2,Scoring!$C$23,IF(AB31=1,Scoring!$C$22,0))) -> 18 | AD31: =IF(T31="Y",0,IF(ISNUMBER(X31),IF(X31>0.7,Scoring!$C$25,IF(X31>=0.5,Scoring!$C$26,IF(X31>=0.3,Scoring!$C$27,Scoring!$C$28))),Scoring!$C$29)) -> 10 | AE31: =IF(D31="Expiring: notice window (verified)",Scoring!$C$30,IF(OR(D31="Expired (verified)",D31="30-yr mark: notice window (est.)",D31="Year-15 window"),Scoring!$C$31,IF(D31="Expiring: 10-yr horizon (verified)",Scoring!$C$32,IF(D31="Past 30-yr mark (verify)",Scoring!$C$33,IF(OR(D31="Credit period",D31="Superseded record"),Scoring!$C$35,Scoring!$C$34))))) -> 14 | AF31: =IF(T31="Y",0,IF(ISNUMBER(V31),IF(Scoring!$B$4-V31>15,Scoring!$C$36,IF(Scoring!$B$4-V31>=10,Scoring!$C$37,IF(Scoring!$B$4-V31>=5,Scoring!$C$38,Scoring!$C$39))),IF(OR(N31="",D31="Out of program"),Scoring!$C$40,IF(O31>15,Scoring!$C$36,IF(O31>=10,Scoring!$C$37,IF(O31>=5,Scoring!$C$38,Scoring!$C$39)))))) -> 15 | AG31: =IF(T31="Y",0,IF(Y31="Y",Scoring!$C$41,IF(ISNUMBER(O31),IF(O31>=25,Scoring!$C$42,IF(O31>=15,Scoring!$C$43,Scoring!$C$44)),Scoring!$C$44))) -> 8 | AH31: =IF(T31="Y",0,IF(W31="",Scoring!$C$49,IFERROR(VLOOKUP(W31,Scoring!$B$45:$C$48,2,FALSE()),Scoring!$C$49))) -> 5 | AI31: =C31+IF(ISNUMBER(J31),J31,0)/100000+(10000-ROW())/1000000000 -> 70.00081
A32: =RANK(AI32,$AI$2:$AI$755) -> 31 | B32: =IF(T32="Y","Superseded",IF(C32>=Scoring!$B$16,"Immediate",IF(C32>=Scoring!$B$17,"This week",IF(C32>=Scoring!$B$18,"Nurture","Low")))) -> This week | C32: =SUM(AC32:AH32) -> 70 | D32: =IF(T32="Y","Superseded record",IF(AND(U32<>"",AA32<0),"Expired (verified)",IF(AND(U32<>"",AA32<=Scoring!$B$5),"Expiring: notice window (verified)",IF(AND(U32<>"",AA32<=Scoring!$B$6),"Expiring: 10-yr horizon (verified)",IF(M32="No Longer Monitored","Out of program",IF(N32="","Unknown vintage",IF(N32<Scoring!$B$12,"Pre-1990, still listed",IF(AND(U32="",AA32<0),"Past 30-yr mark (verify)",IF(AND(U32="",AA32<=Scoring!$B$5),"30-yr mark: notice window (est.)",IF(AND(O32>=Scoring!$B$7,O32<=Scoring!$B$8),"Year-15 window",IF(O32>=Scoring!$B$9,"Recap window",IF(O32>=11,"Late compliance","Credit period")))))))))))) -> 30-yr mark: notice window (est.) | E32: ORA19990015 | F32: BRENTWOOD OAKS APTS | G32: 3245 SW 182ND AVE | H32: ALOHA | I32: 97003 | J32: 78 | K32: 78 | L32: =IF(OR(J32="",K32=""),"",MAX(J32-K32,0)) -> 0 | M32: Not Indicated | N32: 1999 | O32: =IF(N32="","",Scoring!$B$4-N32) -> 27 | P32: =IF(N32="","",N32+14) -> 2013 | Q32: =IF(N32="","",IF(N32<Scoring!$B$12,"n/a (pre-1990)",N32+Scoring!$B$13)) -> 2028 | R32: =IF(J32="","Unknown",IF(J32>=5,"Yes","No (under 5 units)")) -> Yes | AA32: =IF(U32<>"",(U32-Scoring!$B$3)/365.25,IF(N32="","",IF(N32<Scoring!$B$12,"",(DATE(N32+Scoring!$B$13,12,31)-Scoring!$B$3)/365.25))) -> 2.2477755 | AB32: =IF(T32="Y",0,IF(OR(D32="Expired (verified)",D32="Expiring: notice window (verified)",D32="Expiring: 10-yr horizon (verified)",D32="Past 30-yr mark (verify)",D32="30-yr mark: notice window (est.)",D32="Year-15 window"),1,0)+IF(ISNUMBER(O32),IF(O32>=Scoring!$B$10,1,0),0)+IF(AND(ISNUMBER(L32),ISNUMBER(J32)),IF(J32>0,IF(L32/J32>=Scoring!$B$11,1,0),0),0)+IF(ISNUMBER(Z32),MIN(Z32,3),0)) -> 2 | AC32: =IF(AB32>=3,Scoring!$C$24,IF(AB32=2,Scoring!$C$23,IF(AB32=1,Scoring!$C$22,0))) -> 18 | AD32: =IF(T32="Y",0,IF(ISNUMBER(X32),IF(X32>0.7,Scoring!$C$25,IF(X32>=0.5,Scoring!$C$26,IF(X32>=0.3,Scoring!$C$27,Scoring!$C$28))),Scoring!$C$29)) -> 10 | AE32: =IF(D32="Expiring: notice window (verified)",Scoring!$C$30,IF(OR(D32="Expired (verified)",D32="30-yr mark: notice window (est.)",D32="Year-15 window"),Scoring!$C$31,IF(D32="Expiring: 10-yr horizon (verified)",Scoring!$C$32,IF(D32="Past 30-yr mark (verify)",Scoring!$C$33,IF(OR(D32="Credit period",D32="Superseded record"),Scoring!$C$35,Scoring!$C$34))))) -> 14 | AF32: =IF(T32="Y",0,IF(ISNUMBER(V32),IF(Scoring!$B$4-V32>15,Scoring!$C$36,IF(Scoring!$B$4-V32>=10,Scoring!$C$37,IF(Scoring!$B$4-V32>=5,Scoring!$C$38,Scoring!$C$39))),IF(OR(N32="",D32="Out of program"),Scoring!$C$40,IF(O32>15,Scoring!$C$36,IF(O32>=10,Scoring!$C$37,IF(O32>=5,Scoring!$C$38,Scoring!$C$39)))))) -> 15 | AG32: =IF(T32="Y",0,IF(Y32="Y",Scoring!$C$41,IF(ISNUMBER(O32),IF(O32>=25,Scoring!$C$42,IF(O32>=15,Scoring!$C$43,Scoring!$C$44)),Scoring!$C$44))) -> 8 | AH32: =IF(T32="Y",0,IF(W32="",Scoring!$C$49,IFERROR(VLOOKUP(W32,Scoring!$B$45:$C$48,2,FALSE()),Scoring!$C$49))) -> 5 | AI32: =C32+IF(ISNUMBER(J32),J32,0)/100000+(10000-ROW())/1000000000 -> 70.00079
A33: =RANK(AI33,$AI$2:$AI$755) -> 32 | B33: =IF(T33="Y","Superseded",IF(C33>=Scoring!$B$16,"Immediate",IF(C33>=Scoring!$B$17,"This week",IF(C33>=Scoring!$B$18,"Nurture","Low")))) -> This week | C33: =SUM(AC33:AH33) -> 70 | D33: =IF(T33="Y","Superseded record",IF(AND(U33<>"",AA33<0),"Expired (verified)",IF(AND(U33<>"",AA33<=Scoring!$B$5),"Expiring: notice window (verified)",IF(AND(U33<>"",AA33<=Scoring!$B$6),"Expiring: 10-yr horizon (verified)",IF(M33="No Longer Monitored","Out of program",IF(N33="","Unknown vintage",IF(N33<Scoring!$B$12,"Pre-1990, still listed",IF(AND(U33="",AA33<0),"Past 30-yr mark (verify)",IF(AND(U33="",AA33<=Scoring!$B$5),"30-yr mark: notice window (est.)",IF(AND(O33>=Scoring!$B$7,O33<=Scoring!$B$8),"Year-15 window",IF(O33>=Scoring!$B$9,"Recap window",IF(O33>=11,"Late compliance","Credit period")))))))))))) -> 30-yr mark: notice window (est.) | E33: ORA19990025 | F33: CASCADE CROSSING | G33: 10625 E BURNSIDE ST | H33: PORTLAND | I33: 97216 | J33: 74 | K33: 74 | L33: =IF(OR(J33="",K33=""),"",MAX(J33-K33,0)) -> 0 | M33: Not Indicated | N33: 1999 | O33: =IF(N33="","",Scoring!$B$4-N33) -> 27 | P33: =IF(N33="","",N33+14) -> 2013 | Q33: =IF(N33="","",IF(N33<Scoring!$B$12,"n/a (pre-1990)",N33+Scoring!$B$13)) -> 2028 | R33: =IF(J33="","Unknown",IF(J33>=5,"Yes","No (under 5 units)")) -> Yes | AA33: =IF(U33<>"",(U33-Scoring!$B$3)/365.25,IF(N33="","",IF(N33<Scoring!$B$12,"",(DATE(N33+Scoring!$B$13,12,31)-Scoring!$B$3)/365.25))) -> 2.2477755 | AB33: =IF(T33="Y",0,IF(OR(D33="Expired (verified)",D33="Expiring: notice window (verified)",D33="Expiring: 10-yr horizon (verified)",D33="Past 30-yr mark (verify)",D33="30-yr mark: notice window (est.)",D33="Year-15 window"),1,0)+IF(ISNUMBER(O33),IF(O33>=Scoring!$B$10,1,0),0)+IF(AND(ISNUMBER(L33),ISNUMBER(J33)),IF(J33>0,IF(L33/J33>=Scoring!$B$11,1,0),0),0)+IF(ISNUMBER(Z33),MIN(Z33,3),0)) -> 2 | AC33: =IF(AB33>=3,Scoring!$C$24,IF(AB33=2,Scoring!$C$23,IF(AB33=1,Scoring!$C$22,0))) -> 18 | AD33: =IF(T33="Y",0,IF(ISNUMBER(X33),IF(X33>0.7,Scoring!$C$25,IF(X33>=0.5,Scoring!$C$26,IF(X33>=0.3,Scoring!$C$27,Scoring!$C$28))),Scoring!$C$29)) -> 10 | AE33: =IF(D33="Expiring: notice window (verified)",Scoring!$C$30,IF(OR(D33="Expired (verified)",D33="30-yr mark: notice window (est.)",D33="Year-15 window"),Scoring!$C$31,IF(D33="Expiring: 10-yr horizon (verified)",Scoring!$C$32,IF(D33="Past 30-yr mark (verify)",Scoring!$C$33,IF(OR(D33="Credit period",D33="Superseded record"),Scoring!$C$35,Scoring!$C$34))))) -> 14 | AF33: =IF(T33="Y",0,IF(ISNUMBER(V33),IF(Scoring!$B$4-V33>15,Scoring!$C$36,IF(Scoring!$B$4-V33>=10,Scoring!$C$37,IF(Scoring!$B$4-V33>=5,Scoring!$C$38,Scoring!$C$39))),IF(OR(N33="",D33="Out of program"),Scoring!$C$40,IF(O33>15,Scoring!$C$36,IF(O33>=10,Scoring!$C$37,IF(O33>=5,Scoring!$C$38,Scoring!$C$39)))))) -> 15 | AG33: =IF(T33="Y",0,IF(Y33="Y",Scoring!$C$41,IF(ISNUMBER(O33),IF(O33>=25,Scoring!$C$42,IF(O33>=15,Scoring!$C$43,Scoring!$C$44)),Scoring!$C$44))) -> 8 | AH33: =IF(T33="Y",0,IF(W33="",Scoring!$C$49,IFERROR(VLOOKUP(W33,Scoring!$B$45:$C$48,2,FALSE()),Scoring!$C$49))) -> 5 | AI33: =C33+IF(ISNUMBER(J33),J33,0)/100000+(10000-ROW())/1000000000 -> 70.00075
A34: =RANK(AI34,$AI$2:$AI$755) -> 33 | B34: =IF(T34="Y","Superseded",IF(C34>=Scoring!$B$16,"Immediate",IF(C34>=Scoring!$B$17,"This week",IF(C34>=Scoring!$B$18,"Nurture","Low")))) -> This week | C34: =SUM(AC34:AH34) -> 70 | D34: =IF(T34="Y","Superseded record",IF(AND(U34<>"",AA34<0),"Expired (verified)",IF(AND(U34<>"",AA34<=Scoring!$B$5),"Expiring: notice window (verified)",IF(AND(U34<>"",AA34<=Scoring!$B$6),"Expiring: 10-yr horizon (verified)",IF(M34="No Longer Monitored","Out of program",IF(N34="","Unknown vintage",IF(N34<Scoring!$B$12,"Pre-1990, still listed",IF(AND(U34="",AA34<0),"Past 30-yr mark (verify)",IF(AND(U34="",AA34<=Scoring!$B$5),"30-yr mark: notice window (est.)",IF(AND(O34>=Scoring!$B$7,O34<=Scoring!$B$8),"Year-15 window",IF(O34>=Scoring!$B$9,"Recap window",IF(O34>=11,"Late compliance","Credit period")))))))))))) -> 30-yr mark: notice window (est.) | E34: ORA19990115 | F34: OAKWOOD MANOR | G34: 1665 OAK PATCH RD | H34: EUGENE | I34: 97402 | J34: 72 | K34: 72 | L34: =IF(OR(J34="",K34=""),"",MAX(J34-K34,0)) -> 0 | M34: Not Indicated | N34: 1999 | O34: =IF(N34="","",Scoring!$B$4-N34) -> 27 | P34: =IF(N34="","",N34+14) -> 2013 | Q34: =IF(N34="","",IF(N34<Scoring!$B$12,"n/a (pre-1990)",N34+Scoring!$B$13)) -> 2028 | R34: =IF(J34="","Unknown",IF(J34>=5,"Yes","No (under 5 units)")) -> Yes | AA34: =IF(U34<>"",(U34-Scoring!$B$3)/365.25,IF(N34="","",IF(N34<Scoring!$B$12,"",(DATE(N34+Scoring!$B$13,12,31)-Scoring!$B$3)/365.25))) -> 2.2477755 | AB34: =IF(T34="Y",0,IF(OR(D34="Expired (verified)",D34="Expiring: notice window (verified)",D34="Expiring: 10-yr horizon (verified)",D34="Past 30-yr mark (verify)",D34="30-yr mark: notice window (est.)",D34="Year-15 window"),1,0)+IF(ISNUMBER(O34),IF(O34>=Scoring!$B$10,1,0),0)+IF(AND(ISNUMBER(L34),ISNUMBER(J34)),IF(J34>0,IF(L34/J34>=Scoring!$B$11,1,0),0),0)+IF(ISNUMBER(Z34),MIN(Z34,3),0)) -> 2 | AC34: =IF(AB34>=3,Scoring!$C$24,IF(AB34=2,Scoring!$C$23,IF(AB34=1,Scoring!$C$22,0))) -> 18 | AD34: =IF(T34="Y",0,IF(ISNUMBER(X34),IF(X34>0.7,Scoring!$C$25,IF(X34>=0.5,Scoring!$C$26,IF(X34>=0.3,Scoring!$C$27,Scoring!$C$28))),Scoring!$C$29)) -> 10 | AE34: =IF(D34="Expiring: notice window (verified)",Scoring!$C$30,IF(OR(D34="Expired (verified)",D34="30-yr mark: notice window (est.)",D34="Year-15 window"),Scoring!$C$31,IF(D34="Expiring: 10-yr horizon (verified)",Scoring!$C$32,IF(D34="Past 30-yr mark (verify)",Scoring!$C$33,IF(OR(D34="Credit period",D34="Superseded record"),Scoring!$C$35,Scoring!$C$34))))) -> 14 | AF34: =IF(T34="Y",0,IF(ISNUMBER(V34),IF(Scoring!$B$4-V34>15,Scoring!$C$36,IF(Scoring!$B$4-V34>=10,Scoring!$C$37,IF(Scoring!$B$4-V34>=5,Scoring!$C$38,Scoring!$C$39))),IF(OR(N34="",D34="Out of program"),Scoring!$C$40,IF(O34>15,Scoring!$C$36,IF(O34>=10,Scoring!$C$37,IF(O34>=5,Scoring!$C$38,Scoring!$C$39)))))) -> 15 | AG34: =IF(T34="Y",0,IF(Y34="Y",Scoring!$C$41,IF(ISNUMBER(O34),IF(O34>=25,Scoring!$C$42,IF(O34>=15,Scoring!$C$43,Scoring!$C$44)),Scoring!$C$44))) -> 8 | AH34: =IF(T34="Y",0,IF(W34="",Scoring!$C$49,IFERROR(VLOOKUP(W34,Scoring!$B$45:$C$48,2,FALSE()),Scoring!$C$49))) -> 5 | AI34: =C34+IF(ISNUMBER(J34),J34,0)/100000+(10000-ROW())/1000000000 -> 70.00073
A35: =RANK(AI35,$AI$2:$AI$755) -> 34 | B35: =IF(T35="Y","Superseded",IF(C35>=Scoring!$B$16,"Immediate",IF(C35>=Scoring!$B$17,"This week",IF(C35>=Scoring!$B$18,"Nurture","Low")))) -> This week | C35: =SUM(AC35:AH35) -> 70 | D35: =IF(T35="Y","Superseded record",IF(AND(U35<>"",AA35<0),"Expired (verified)",IF(AND(U35<>"",AA35<=Scoring!$B$5),"Expiring: notice window (verified)",IF(AND(U35<>"",AA35<=Scoring!$B$6),"Expiring: 10-yr horizon (verified)",IF(M35="No Longer Monitored","Out of program",IF(N35="","Unknown vintage",IF(N35<Scoring!$B$12,"Pre-1990, still listed",IF(AND(U35="",AA35<0),"Past 30-yr mark (verify)",IF(AND(U35="",AA35<=Scoring!$B$5),"30-yr mark: notice window (est.)",IF(AND(O35>=Scoring!$B$7,O35<=Scoring!$B$8),"Year-15 window",IF(O35>=Scoring!$B$9,"Recap window",IF(O35>=11,"Late compliance","Credit period")))))))))))) -> 30-yr mark: notice window (est.) | E35: ORA19970030 | F35: EMPIRE PLACE APTS | G35: 314 NW FIFTH AVE | H35: PORTLAND | I35: 97209 | J35: 70 | K35: 70 | L35: =IF(OR(J35="",K35=""),"",MAX(J35-K35,0)) -> 0 | M35: Not Indicated | N35: 1997 | O35: =IF(N35="","",Scoring!$B$4-N35) -> 29 | P35: =IF(N35="","",N35+14) -> 2011 | Q35: =IF(N35="","",IF(N35<Scoring!$B$12,"n/a (pre-1990)",N35+Scoring!$B$13)) -> 2026 | R35: =IF(J35="","Unknown",IF(J35>=5,"Yes","No (under 5 units)")) -> Yes | AA35: =IF(U35<>"",(U35-Scoring!$B$3)/365.25,IF(N35="","",IF(N35<Scoring!$B$12,"",(DATE(N35+Scoring!$B$13,12,31)-Scoring!$B$3)/365.25))) -> 0.24640657 | AB35: =IF(T35="Y",0,IF(OR(D35="Expired (verified)",D35="Expiring: notice window (verified)",D35="Expiring: 10-yr horizon (verified)",D35="Past 30-yr mark (verify)",D35="30-yr mark: notice window (est.)",D35="Year-15 window"),1,0)+IF(ISNUMBER(O35),IF(O35>=Scoring!$B$10,1,0),0)+IF(AND(ISNUMBER(L35),ISNUMBER(J35)),IF(J35>0,IF(L35/J35>=Scoring!$B$11,1,0),0),0)+IF(ISNUMBER(Z35),MIN(Z35,3),0)) -> 2 | AC35: =IF(AB35>=3,Scoring!$C$24,IF(AB35=2,Scoring!$C$23,IF(AB35=1,Scoring!$C$22,0))) -> 18 | AD35: =IF(T35="Y",0,IF(ISNUMBER(X35),IF(X35>0.7,Scoring!$C$25,IF(X35>=0.5,Scoring!$C$26,IF(X35>=0.3,Scoring!$C$27,Scoring!$C$28))),Scoring!$C$29)) -> 10 | AE35: =IF(D35="Expiring: notice window (verified)",Scoring!$C$30,IF(OR(D35="Expired (verified)",D35="30-yr mark: notice window (est.)",D35="Year-15 window"),Scoring!$C$31,IF(D35="Expiring: 10-yr horizon (verified)",Scoring!$C$32,IF(D35="Past 30-yr mark (verify)",Scoring!$C$33,IF(OR(D35="Credit period",D35="Superseded record"),Scoring!$C$35,Scoring!$C$34))))) -> 14 | AF35: =IF(T35="Y",0,IF(ISNUMBER(V35),IF(Scoring!$B$4-V35>15,Scoring!$C$36,IF(Scoring!$B$4-V35>=10,Scoring!$C$37,IF(Scoring!$B$4-V35>=5,Scoring!$C$38,Scoring!$C$39))),IF(OR(N35="",D35="Out of program"),Scoring!$C$40,IF(O35>15,Scoring!$C$36,IF(O35>=10,Scoring!$C$37,IF(O35>=5,Scoring!$C$38,Scoring!$C$39)))))) -> 15 | AG35: =IF(T35="Y",0,IF(Y35="Y",Scoring!$C$41,IF(ISNUMBER(O35),IF(O35>=25,Scoring!$C$42,IF(O35>=15,Scoring!$C$43,Scoring!$C$44)),Scoring!$C$44))) -> 8 | AH35: =IF(T35="Y",0,IF(W35="",Scoring!$C$49,IFERROR(VLOOKUP(W35,Scoring!$B$45:$C$48,2,FALSE()),Scoring!$C$49))) -> 5 | AI35: =C35+IF(ISNUMBER(J35),J35,0)/100000+(10000-ROW())/1000000000 -> 70.00071
A36: =RANK(AI36,$AI$2:$AI$755) -> 35 | B36: =IF(T36="Y","Superseded",IF(C36>=Scoring!$B$16,"Immediate",IF(C36>=Scoring!$B$17,"This week",IF(C36>=Scoring!$B$18,"Nurture","Low")))) -> This week | C36: =SUM(AC36:AH36) -> 70 | D36: =IF(T36="Y","Superseded record",IF(AND(U36<>"",AA36<0),"Expired (verified)",IF(AND(U36<>"",AA36<=Scoring!$B$5),"Expiring: notice window (verified)",IF(AND(U36<>"",AA36<=Scoring!$B$6),"Expiring: 10-yr horizon (verified)",IF(M36="No Longer Monitored","Out of program",IF(N36="","Unknown vintage",IF(N36<Scoring!$B$12,"Pre-1990, still listed",IF(AND(U36="",AA36<0),"Past 30-yr mark (verify)",IF(AND(U36="",AA36<=Scoring!$B$5),"30-yr mark: notice window (est.)",IF(AND(O36>=Scoring!$B$7,O36<=Scoring!$B$8),"Year-15 window",IF(O36>=Scoring!$B$9,"Recap window",IF(O36>=11,"Late compliance","Credit period")))))))))))) -> 30-yr mark: notice window (est.) | E36: ORA19970125 | F36: VINE STREET COURTS PHASES I & II | G36: 2166 NE VINE ST | H36: ROSEBURG | I36: 97470 | J36: 70 | K36: 70 | L36: =IF(OR(J36="",K36=""),"",MAX(J36-K36,0)) -> 0 | M36: Not Indicated | N36: 1997 | O36: =IF(N36="","",Scoring!$B$4-N36) -> 29 | P36: =IF(N36="","",N36+14) -> 2011 | Q36: =IF(N36="","",IF(N36<Scoring!$B$12,"n/a (pre-1990)",N36+Scoring!$B$13)) -> 2026 | R36: =IF(J36="","Unknown",IF(J36>=5,"Yes","No (under 5 units)")) -> Yes | AA36: =IF(U36<>"",(U36-Scoring!$B$3)/365.25,IF(N36="","",IF(N36<Scoring!$B$12,"",(DATE(N36+Scoring!$B$13,12,31)-Scoring!$B$3)/365.25))) -> 0.24640657 | AB36: =IF(T36="Y",0,IF(OR(D36="Expired (verified)",D36="Expiring: notice window (verified)",D36="Expiring: 10-yr horizon (verified)",D36="Past 30-yr mark (verify)",D36="30-yr mark: notice window (est.)",D36="Year-15 window"),1,0)+IF(ISNUMBER(O36),IF(O36>=Scoring!$B$10,1,0),0)+IF(AND(ISNUMBER(L36),ISNUMBER(J36)),IF(J36>0,IF(L36/J36>=Scoring!$B$11,1,0),0),0)+IF(ISNUMBER(Z36),MIN(Z36,3),0)) -> 2 | AC36: =IF(AB36>=3,Scoring!$C$24,IF(AB36=2,Scoring!$C$23,IF(AB36=1,Scoring!$C$22,0))) -> 18 | AD36: =IF(T36="Y",0,IF(ISNUMBER(X36),IF(X36>0.7,Scoring!$C$25,IF(X36>=0.5,Scoring!$C$26,IF(X36>=0.3,Scoring!$C$27,Scoring!$C$28))),Scoring!$C$29)) -> 10 | AE36: =IF(D36="Expiring: notice window (verified)",Scoring!$C$30,IF(OR(D36="Expired (verified)",D36="30-yr mark: notice window (est.)",D36="Year-15 window"),Scoring!$C$31,IF(D36="Expiring: 10-yr horizon (verified)",Scoring!$C$32,IF(D36="Past 30-yr mark (verify)",Scoring!$C$33,IF(OR(D36="Credit period",D36="Superseded record"),Scoring!$C$35,Scoring!$C$34))))) -> 14 | AF36: =IF(T36="Y",0,IF(ISNUMBER(V36),IF(Scoring!$B$4-V36>15,Scoring!$C$36,IF(Scoring!$B$4-V36>=10,Scoring!$C$37,IF(Scoring!$B$4-V36>=5,Scoring!$C$38,Scoring!$C$39))),IF(OR(N36="",D36="Out of program"),Scoring!$C$40,IF(O36>15,Scoring!$C$36,IF(O36>=10,Scoring!$C$37,IF(O36>=5,Scoring!$C$38,Scoring!$C$39)))))) -> 15 | AG36: =IF(T36="Y",0,IF(Y36="Y",Scoring!$C$41,IF(ISNUMBER(O36),IF(O36>=25,Scoring!$C$42,IF(O36>=15,Scoring!$C$43,Scoring!$C$44)),Scoring!$C$44))) -> 8 | AH36: =IF(T36="Y",0,IF(W36="",Scoring!$C$49,IFERROR(VLOOKUP(W36,Scoring!$B$45:$C$48,2,FALSE()),Scoring!$C$49))) -> 5 | AI36: =C36+IF(ISNUMBER(J36),J36,0)/100000+(10000-ROW())/1000000000 -> 70.00071
A37: =RANK(AI37,$AI$2:$AI$755) -> 36 | B37: =IF(T37="Y","Superseded",IF(C37>=Scoring!$B$16,"Immediate",IF(C37>=Scoring!$B$17,"This week",IF(C37>=Scoring!$B$18,"Nurture","Low")))) -> This week | C37: =SUM(AC37:AH37) -> 70 | D37: =IF(T37="Y","Superseded record",IF(AND(U37<>"",AA37<0),"Expired (verified)",IF(AND(U37<>"",AA37<=Scoring!$B$5),"Expiring: notice window (verified)",IF(AND(U37<>"",AA37<=Scoring!$B$6),"Expiring: 10-yr horizon (verified)",IF(M37="No Longer Monitored","Out of program",IF(N37="","Unknown vintage",IF(N37<Scoring!$B$12,"Pre-1990, still listed",IF(AND(U37="",AA37<0),"Past 30-yr mark (verify)",IF(AND(U37="",AA37<=Scoring!$B$5),"30-yr mark: notice window (est.)",IF(AND(O37>=Scoring!$B$7,O37<=Scoring!$B$8),"Year-15 window",IF(O37>=Scoring!$B$9,"Recap window",IF(O37>=11,"Late compliance","Credit period")))))))))))) -> 30-yr mark: notice window (est.) | E37: ORA19970005 | F37: ALLEN FREEMONT PLAZA | G37: 221 NE FREMONT ST | H37: PORTLAND | I37: 97212 | J37: 64 | K37: 64 | L37: =IF(OR(J37="",K37=""),"",MAX(J37-K37,0)) -> 0 | M37: Not Indicated | N37: 1997 | O37: =IF(N37="","",Scoring!$B$4-N37) -> 29 | P37: =IF(N37="","",N37+14) -> 2011 | Q37: =IF(N37="","",IF(N37<Scoring!$B$12,"n/a (pre-1990)",N37+Scoring!$B$13)) -> 2026 | R37: =IF(J37="","Unknown",IF(J37>=5,"Yes","No (under 5 units)")) -> Yes | AA37: =IF(U37<>"",(U37-Scoring!$B$3)/365.25,IF(N37="","",IF(N37<Scoring!$B$12,"",(DATE(N37+Scoring!$B$13,12,31)-Scoring!$B$3)/365.25))) -> 0.24640657 | AB37: =IF(T37="Y",0,IF(OR(D37="Expired (verified)",D37="Expiring: notice window (verified)",D37="Expiring: 10-yr horizon (verified)",D37="Past 30-yr mark (verify)",D37="30-yr mark: notice window (est.)",D37="Year-15 window"),1,0)+IF(ISNUMBER(O37),IF(O37>=Scoring!$B$10,1,0),0)+IF(AND(ISNUMBER(L37),ISNUMBER(J37)),IF(J37>0,IF(L37/J37>=Scoring!$B$11,1,0),0),0)+IF(ISNUMBER(Z37),MIN(Z37,3),0)) -> 2 | AC37: =IF(AB37>=3,Scoring!$C$24,IF(AB37=2,Scoring!$C$23,IF(AB37=1,Scoring!$C$22,0))) -> 18 | AD37: =IF(T37="Y",0,IF(ISNUMBER(X37),IF(X37>0.7,Scoring!$C$25,IF(X37>=0.5,Scoring!$C$26,IF(X37>=0.3,Scoring!$C$27,Scoring!$C$28))),Scoring!$C$29)) -> 10 | AE37: =IF(D37="Expiring: notice window (verified)",Scoring!$C$30,IF(OR(D37="Expired (verified)",D37="30-yr mark: notice window (est.)",D37="Year-15 window"),Scoring!$C$31,IF(D37="Expiring: 10-yr horizon (verified)",Scoring!$C$32,IF(D37="Past 30-yr mark (verify)",Scoring!$C$33,IF(OR(D37="Credit period",D37="Superseded record"),Scoring!$C$35,Scoring!$C$34))))) -> 14 | AF37: =IF(T37="Y",0,IF(ISNUMBER(V37),IF(Scoring!$B$4-V37>15,Scoring!$C$36,IF(Scoring!$B$4-V37>=10,Scoring!$C$37,IF(Scoring!$B$4-V37>=5,Scoring!$C$38,Scoring!$C$39))),IF(OR(N37="",D37="Out of program"),Scoring!$C$40,IF(O37>15,Scoring!$C$36,IF(O37>=10,Scoring!$C$37,IF(O37>=5,Scoring!$C$38,Scoring!$C$39)))))) -> 15 | AG37: =IF(T37="Y",0,IF(Y37="Y",Scoring!$C$41,IF(ISNUMBER(O37),IF(O37>=25,Scoring!$C$42,IF(O37>=15,Scoring!$C$43,Scoring!$C$44)),Scoring!$C$44))) -> 8 | AH37: =IF(T37="Y",0,IF(W37="",Scoring!$C$49,IFERROR(VLOOKUP(W37,Scoring!$B$45:$C$48,2,FALSE()),Scoring!$C$49))) -> 5 | AI37: =C37+IF(ISNUMBER(J37),J37,0)/100000+(10000-ROW())/1000000000 -> 70.00065
A38: =RANK(AI38,$AI$2:$AI$755) -> 37 | B38: =IF(T38="Y","Superseded",IF(C38>=Scoring!$B$16,"Immediate",IF(C38>=Scoring!$B$17,"This week",IF(C38>=Scoring!$B$18,"Nurture","Low")))) -> This week | C38: =SUM(AC38:AH38) -> 70 | D38: =IF(T38="Y","Superseded record",IF(AND(U38<>"",AA38<0),"Expired (verified)",IF(AND(U38<>"",AA38<=Scoring!$B$5),"Expiring: notice window (verified)",IF(AND(U38<>"",AA38<=Scoring!$B$6),"Expiring: 10-yr horizon (verified)",IF(M38="No Longer Monitored","Out of program",IF(N38="","Unknown vintage",IF(N38<Scoring!$B$12,"Pre-1990, still listed",IF(AND(U38="",AA38<0),"Past 30-yr mark (verify)",IF(AND(U38="",AA38<=Scoring!$B$5),"30-yr mark: notice window (est.)",IF(AND(O38>=Scoring!$B$7,O38<=Scoring!$B$8),"Year-15 window",IF(O38>=Scoring!$B$9,"Recap window",IF(O38>=11,"Late compliance","Credit period")))))))))))) -> 30-yr mark: notice window (est.) | E38: ORA19980055 | F38: CHAMPION PARK APTS | G38: 4317 BROOKFIELD AVE | H38: TILLAMOOK | I38: 97141 | J38: 64 | K38: 64 | L38: =IF(OR(J38="",K38=""),"",MAX(J38-K38,0)) -> 0 | M38: Not Indicated | N38: 1998 | O38: =IF(N38="","",Scoring!$B$4-N38) -> 28 | P38: =IF(N38="","",N38+14) -> 2012 | Q38: =IF(N38="","",IF(N38<Scoring!$B$12,"n/a (pre-1990)",N38+Scoring!$B$13)) -> 2027 | R38: =IF(J38="","Unknown",IF(J38>=5,"Yes","No (under 5 units)")) -> Yes | S38: Shares address with ORA20040030 (phase, resyndication or duplicate) | AA38: =IF(U38<>"",(U38-Scoring!$B$3)/365.25,IF(N38="","",IF(N38<Scoring!$B$12,"",(DATE(N38+Scoring!$B$13,12,31)-Scoring!$B$3)/365.25))) -> 1.2457221 | AB38: =IF(T38="Y",0,IF(OR(D38="Expired (verified)",D38="Expiring: notice window (verified)",D38="Expiring: 10-yr horizon (verified)",D38="Past 30-yr mark (verify)",D38="30-yr mark: notice window (est.)",D38="Year-15 window"),1,0)+IF(ISNUMBER(O38),IF(O38>=Scoring!$B$10,1,0),0)+IF(AND(ISNUMBER(L38),ISNUMBER(J38)),IF(J38>0,IF(L38/J38>=Scoring!$B$11,1,0),0),0)+IF(ISNUMBER(Z38),MIN(Z38,3),0)) -> 2 | AC38: =IF(AB38>=3,Scoring!$C$24,IF(AB38=2,Scoring!$C$23,IF(AB38=1,Scoring!$C$22,0))) -> 18 | AD38: =IF(T38="Y",0,IF(ISNUMBER(X38),IF(X38>0.7,Scoring!$C$25,IF(X38>=0.5,Scoring!$C$26,IF(X38>=0.3,Scoring!$C$27,Scoring!$C$28))),Scoring!$C$29)) -> 10 | AE38: =IF(D38="Expiring: notice window (verified)",Scoring!$C$30,IF(OR(D38="Expired (verified)",D38="30-yr mark: notice window (est.)",D38="Year-15 window"),Scoring!$C$31,IF(D38="Expiring: 10-yr horizon (verified)",Scoring!$C$32,IF(D38="Past 30-yr mark (verify)",Scoring!$C$33,IF(OR(D38="Credit period",D38="Superseded record"),Scoring!$C$35,Scoring!$C$34))))) -> 14 | AF38: =IF(T38="Y",0,IF(ISNUMBER(V38),IF(Scoring!$B$4-V38>15,Scoring!$C$36,IF(Scoring!$B$4-V38>=10,Scoring!$C$37,IF(Scoring!$B$4-V38>=5,Scoring!$C$38,Scoring!$C$39))),IF(OR(N38="",D38="Out of program"),Scoring!$C$40,IF(O38>15,Scoring!$C$36,IF(O38>=10,Scoring!$C$37,IF(O38>=5,Scoring!$C$38,Scoring!$C$39)))))) -> 15 | AG38: =IF(T38="Y",0,IF(Y38="Y",Scoring!$C$41,IF(ISNUMBER(O38),IF(O38>=25,Scoring!$C$42,IF(O38>=15,Scoring!$C$43,Scoring!$C$44)),Scoring!$C$44))) -> 8 | AH38: =IF(T38="Y",0,IF(W38="",Scoring!$C$49,IFERROR(VLOOKUP(W38,Scoring!$B$45:$C$48,2,FALSE()),Scoring!$C$49))) -> 5 | AI38: =C38+IF(ISNUMBER(J38),J38,0)/100000+(10000-ROW())/1000000000 -> 70.00065
A39: =RANK(AI39,$AI$2:$AI$755) -> 38 | B39: =IF(T39="Y","Superseded",IF(C39>=Scoring!$B$16,"Immediate",IF(C39>=Scoring!$B$17,"This week",IF(C39>=Scoring!$B$18,"Nurture","Low")))) -> This week | C39: =SUM(AC39:AH39) -> 70 | D39: =IF(T39="Y","Superseded record",IF(AND(U39<>"",AA39<0),"Expired (verified)",IF(AND(U39<>"",AA39<=Scoring!$B$5),"Expiring: notice window (verified)",IF(AND(U39<>"",AA39<=Scoring!$B$6),"Expiring: 10-yr horizon (verified)",IF(M39="No Longer Monitored","Out of program",IF(N39="","Unknown vintage",IF(N39<Scoring!$B$12,"Pre-1990, still listed",IF(AND(U39="",AA39<0),"Past 30-yr mark (verify)",IF(AND(U39="",AA39<=Scoring!$B$5),"30-yr mark: notice window (est.)",IF(AND(O39>=Scoring!$B$7,O39<=Scoring!$B$8),"Year-15 window",IF(O39>=Scoring!$B$9,"Recap window",IF(O39>=11,"Late compliance","Credit period")))))))))))) -> 30-yr mark: notice window (est.) | E39: ORA19990145 | F39: VIEWCREST APTS | G39: 525 SW 13TH PL | H39: HERMISTON | I39: 97838 | J39: 64 | K39: 64 | L39: =IF(OR(J39="",K39=""),"",MAX(J39-K39,0)) -> 0 | M39: Not Indicated | N39: 1999 | O39: =IF(N39="","",Scoring!$B$4-N39) -> 27 | P39: =IF(N39="","",N39+14) -> 2013 | Q39: =IF(N39="","",IF(N39<Scoring!$B$12,"n/a (pre-1990)",N39+Scoring!$B$13)) -> 2028 | R39: =IF(J39="","Unknown",IF(J39>=5,"Yes","No (under 5 units)")) -> Yes | AA39: =IF(U39<>"",(U39-Scoring!$B$3)/365.25,IF(N39="","",IF(N39<Scoring!$B$12,"",(DATE(N39+Scoring!$B$13,12,31)-Scoring!$B$3)/365.25))) -> 2.2477755 | AB39: =IF(T39="Y",0,IF(OR(D39="Expired (verified)",D39="Expiring: notice window (verified)",D39="Expiring: 10-yr horizon (verified)",D39="Past 30-yr mark (verify)",D39="30-yr mark: notice window (est.)",D39="Year-15 window"),1,0)+IF(ISNUMBER(O39),IF(O39>=Scoring!$B$10,1,0),0)+IF(AND(ISNUMBER(L39),ISNUMBER(J39)),IF(J39>0,IF(L39/J39>=Scoring!$B$11,1,0),0),0)+IF(ISNUMBER(Z39),MIN(Z39,3),0)) -> 2 | AC39: =IF(AB39>=3,Scoring!$C$24,IF(AB39=2,Scoring!$C$23,IF(AB39=1,Scoring!$C$22,0))) -> 18 | AD39: =IF(T39="Y",0,IF(ISNUMBER(X39),IF(X39>0.7,Scoring!$C$25,IF(X39>=0.5,Scoring!$C$26,IF(X39>=0.3,Scoring!$C$27,Scoring!$C$28))),Scoring!$C$29)) -> 10 | AE39: =IF(D39="Expiring: notice window (verified)",Scoring!$C$30,IF(OR(D39="Expired (verified)",D39="30-yr mark: notice window (est.)",D39="Year-15 window"),Scoring!$C$31,IF(D39="Expiring: 10-yr horizon (verified)",Scoring!$C$32,IF(D39="Past 30-yr mark (verify)",Scoring!$C$33,IF(OR(D39="Credit period",D39="Superseded record"),Scoring!$C$35,Scoring!$C$34))))) -> 14 | AF39: =IF(T39="Y",0,IF(ISNUMBER(V39),IF(Scoring!$B$4-V39>15,Scoring!$C$36,IF(Scoring!$B$4-V39>=10,Scoring!$C$37,IF(Scoring!$B$4-V39>=5,Scoring!$C$38,Scoring!$C$39))),IF(OR(N39="",D39="Out of program"),Scoring!$C$40,IF(O39>15,Scoring!$C$36,IF(O39>=10,Scoring!$C$37,IF(O39>=5,Scoring!$C$38,Scoring!$C$39)))))) -> 15 | AG39: =IF(T39="Y",0,IF(Y39="Y",Scoring!$C$41,IF(ISNUMBER(O39),IF(O39>=25,Scoring!$C$42,IF(O39>=15,Scoring!$C$43,Scoring!$C$44)),Scoring!$C$44))) -> 8 | AH39: =IF(T39="Y",0,IF(W39="",Scoring!$C$49,IFERROR(VLOOKUP(W39,Scoring!$B$45:$C$48,2,FALSE()),Scoring!$C$49))) -> 5 | AI39: =C39+IF(ISNUMBER(J39),J39,0)/100000+(10000-ROW())/1000000000 -> 70.00065
A40: =RANK(AI40,$AI$2:$AI$755) -> 39 | B40: =IF(T40="Y","Superseded",IF(C40>=Scoring!$B$16,"Immediate",IF(C40>=Scoring!$B$17,"This week",IF(C40>=Scoring!$B$18,"Nurture","Low")))) -> This week | C40: =SUM(AC40:AH40) -> 70 | D40: =IF(T40="Y","Superseded record",IF(AND(U40<>"",AA40<0),"Expired (verified)",IF(AND(U40<>"",AA40<=Scoring!$B$5),"Expiring: notice window (verified)",IF(AND(U40<>"",AA40<=Scoring!$B$6),"Expiring: 10-yr horizon (verified)",IF(M40="No Longer Monitored","Out of program",IF(N40="","Unknown vintage",IF(N40<Scoring!$B$12,"Pre-1990, still listed",IF(AND(U40="",AA40<0),"Past 30-yr mark (verify)",IF(AND(U40="",AA40<=Scoring!$B$5),"30-yr mark: notice window (est.)",IF(AND(O40>=Scoring!$B$7,O40<=Scoring!$B$8),"Year-15 window",IF(O40>=Scoring!$B$9,"Recap window",IF(O40>=11,"Late compliance","Credit period")))))))))))) -> 30-yr mark: notice window (est.) | E40: ORA19970055 | F40: LENTS VILLAGE APTS | G40: 10325 SE HOLGATE BLVD | H40: PORTLAND | I40: 97266 | J40: 63 | K40: 63 | L40: =IF(OR(J40="",K40=""),"",MAX(J40-K40,0)) -> 0 | M40: Not Indicated | N40: 1997 | O40: =IF(N40="","",Scoring!$B$4-N40) -> 29 | P40: =IF(N40="","",N40+14) -> 2011 | Q40: =IF(N40="","",IF(N40<Scoring!$B$12,"n/a (pre-1990)",N40+Scoring!$B$13)) -> 2026 | R40: =IF(J40="","Unknown",IF(J40>=5,"Yes","No (under 5 units)")) -> Yes | AA40: =IF(U40<>"",(U40-Scoring!$B$3)/365.25,IF(N40="","",IF(N40<Scoring!$B$12,"",(DATE(N40+Scoring!$B$13,12,31)-Scoring!$B$3)/365.25))) -> 0.24640657 | AB40: =IF(T40="Y",0,IF(OR(D40="Expired (verified)",D40="Expiring: notice window (verified)",D40="Expiring: 10-yr horizon (verified)",D40="Past 30-yr mark (verify)",D40="30-yr mark: notice window (est.)",D40="Year-15 window"),1,0)+IF(ISNUMBER(O40),IF(O40>=Scoring!$B$10,1,0),0)+IF(AND(ISNUMBER(L40),ISNUMBER(J40)),IF(J40>0,IF(L40/J40>=Scoring!$B$11,1,0),0),0)+IF(ISNUMBER(Z40),MIN(Z40,3),0)) -> 2 | AC40: =IF(AB40>=3,Scoring!$C$24,IF(AB40=2,Scoring!$C$23,IF(AB40=1,Scoring!$C$22,0))) -> 18 | AD40: =IF(T40="Y",0,IF(ISNUMBER(X40),IF(X40>0.7,Scoring!$C$25,IF(X40>=0.5,Scoring!$C$26,IF(X40>=0.3,Scoring!$C$27,Scoring!$C$28))),Scoring!$C$29)) -> 10 | AE40: =IF(D40="Expiring: notice window (verified)",Scoring!$C$30,IF(OR(D40="Expired (verified)",D40="30-yr mark: notice window (est.)",D40="Year-15 window"),Scoring!$C$31,IF(D40="Expiring: 10-yr horizon (verified)",Scoring!$C$32,IF(D40="Past 30-yr mark (verify)",Scoring!$C$33,IF(OR(D40="Credit period",D40="Superseded record"),Scoring!$C$35,Scoring!$C$34))))) -> 14 | AF40: =IF(T40="Y",0,IF(ISNUMBER(V40),IF(Scoring!$B$4-V40>15,Scoring!$C$36,IF(Scoring!$B$4-V40>=10,Scoring!$C$37,IF(Scoring!$B$4-V40>=5,Scoring!$C$38,Scoring!$C$39))),IF(OR(N40="",D40="Out of program"),Scoring!$C$40,IF(O40>15,Scoring!$C$36,IF(O40>=10,Scoring!$C$37,IF(O40>=5,Scoring!$C$38,Scoring!$C$39)))))) -> 15 | AG40: =IF(T40="Y",0,IF(Y40="Y",Scoring!$C$41,IF(ISNUMBER(O40),IF(O40>=25,Scoring!$C$42,IF(O40>=15,Scoring!$C$43,Scoring!$C$44)),Scoring!$C$44))) -> 8 | AH40: =IF(T40="Y",0,IF(W40="",Scoring!$C$49,IFERROR(VLOOKUP(W40,Scoring!$B$45:$C$48,2,FALSE()),Scoring!$C$49))) -> 5 | AI40: =C40+IF(ISNUMBER(J40),J40,0)/100000+(10000-ROW())/1000000000 -> 70.00064
A41: =RANK(AI41,$AI$2:$AI$755) -> 40 | B41: =IF(T41="Y","Superseded",IF(C41>=Scoring!$B$16,"Immediate",IF(C41>=Scoring!$B$17,"This week",IF(C41>=Scoring!$B$18,"Nurture","Low")))) -> This week | C41: =SUM(AC41:AH41) -> 70 | D41: =IF(T41="Y","Superseded record",IF(AND(U41<>"",AA41<0),"Expired (verified)",IF(AND(U41<>"",AA41<=Scoring!$B$5),"Expiring: notice window (verified)",IF(AND(U41<>"",AA41<=Scoring!$B$6),"Expiring: 10-yr horizon (verified)",IF(M41="No Longer Monitored","Out of program",IF(N41="","Unknown vintage",IF(N41<Scoring!$B$12,"Pre-1990, still listed",IF(AND(U41="",AA41<0),"Past 30-yr mark (verify)",IF(AND(U41="",AA41<=Scoring!$B$5),"30-yr mark: notice window (est.)",IF(AND(O41>=Scoring!$B$7,O41<=Scoring!$B$8),"Year-15 window",IF(O41>=Scoring!$B$9,"Recap window",IF(O41>=11,"Late compliance","Credit period")))))))))))) -> 30-yr mark: notice window (est.) | E41: ORA19990075 | F41: JACOBS LANE | G41: 3450 JACOBS LN | H41: EUGENE | I41: 97402 | J41: 63 | K41: 63 | L41: =IF(OR(J41="",K41=""),"",MAX(J41-K41,0)) -> 0 | M41: Not Indicated | N41: 1999 | O41: =IF(N41="","",Scoring!$B$4-N41) -> 27 | P41: =IF(N41="","",N41+14) -> 2013 | Q41: =IF(N41="","",IF(N41<Scoring!$B$12,"n/a (pre-1990)",N41+Scoring!$B$13)) -> 2028 | R41: =IF(J41="","Unknown",IF(J41>=5,"Yes","No (under 5 units)")) -> Yes | AA41: =IF(U41<>"",(U41-Scoring!$B$3)/365.25,IF(N41="","",IF(N41<Scoring!$B$12,"",(DATE(N41+Scoring!$B$13,12,31)-Scoring!$B$3)/365.25))) -> 2.2477755 | AB41: =IF(T41="Y",0,IF(OR(D41="Expired (verified)",D41="Expiring: notice window (verified)",D41="Expiring: 10-yr horizon (verified)",D41="Past 30-yr mark (verify)",D41="30-yr mark: notice window (est.)",D41="Year-15 window"),1,0)+IF(ISNUMBER(O41),IF(O41>=Scoring!$B$10,1,0),0)+IF(AND(ISNUMBER(L41),ISNUMBER(J41)),IF(J41>0,IF(L41/J41>=Scoring!$B$11,1,0),0),0)+IF(ISNUMBER(Z41),MIN(Z41,3),0)) -> 2 | AC41: =IF(AB41>=3,Scoring!$C$24,IF(AB41=2,Scoring!$C$23,IF(AB41=1,Scoring!$C$22,0))) -> 18 | AD41: =IF(T41="Y",0,IF(ISNUMBER(X41),IF(X41>0.7,Scoring!$C$25,IF(X41>=0.5,Scoring!$C$26,IF(X41>=0.3,Scoring!$C$27,Scoring!$C$28))),Scoring!$C$29)) -> 10 | AE41: =IF(D41="Expiring: notice window (verified)",Scoring!$C$30,IF(OR(D41="Expired (verified)",D41="30-yr mark: notice window (est.)",D41="Year-15 window"),Scoring!$C$31,IF(D41="Expiring: 10-yr horizon (verified)",Scoring!$C$32,IF(D41="Past 30-yr mark (verify)",Scoring!$C$33,IF(OR(D41="Credit period",D41="Superseded record"),Scoring!$C$35,Scoring!$C$34))))) -> 14 | AF41: =IF(T41="Y",0,IF(ISNUMBER(V41),IF(Scoring!$B$4-V41>15,Scoring!$C$36,IF(Scoring!$B$4-V41>=10,Scoring!$C$37,IF(Scoring!$B$4-V41>=5,Scoring!$C$38,Scoring!$C$39))),IF(OR(N41="",D41="Out of program"),Scoring!$C$40,IF(O41>15,Scoring!$C$36,IF(O41>=10,Scoring!$C$37,IF(O41>=5,Scoring!$C$38,Scoring!$C$39)))))) -> 15 | AG41: =IF(T41="Y",0,IF(Y41="Y",Scoring!$C$41,IF(ISNUMBER(O41),IF(O41>=25,Scoring!$C$42,IF(O41>=15,Scoring!$C$43,Scoring!$C$44)),Scoring!$C$44))) -> 8 | AH41: =IF(T41="Y",0,IF(W41="",Scoring!$C$49,IFERROR(VLOOKUP(W41,Scoring!$B$45:$C$48,2,FALSE()),Scoring!$C$49))) -> 5 | AI41: =C41+IF(ISNUMBER(J41),J41,0)/100000+(10000-ROW())/1000000000 -> 70.00064
A42: =RANK(AI42,$AI$2:$AI$755) -> 41 | B42: =IF(T42="Y","Superseded",IF(C42>=Scoring!$B$16,"Immediate",IF(C42>=Scoring!$B$17,"This week",IF(C42>=Scoring!$B$18,"Nurture","Low")))) -> This week | C42: =SUM(AC42:AH42) -> 70 | D42: =IF(T42="Y","Superseded record",IF(AND(U42<>"",AA42<0),"Expired (verified)",IF(AND(U42<>"",AA42<=Scoring!$B$5),"Expiring: notice window (verified)",IF(AND(U42<>"",AA42<=Scoring!$B$6),"Expiring: 10-yr horizon (verified)",IF(M42="No Longer Monitored","Out of program",IF(N42="","Unknown vintage",IF(N42<Scoring!$B$12,"Pre-1990, still listed",IF(AND(U42="",AA42<0),"Past 30-yr mark (verify)",IF(AND(U42="",AA42<=Scoring!$B$5),"30-yr mark: notice window (est.)",IF(AND(O42>=Scoring!$B$7,O42<=Scoring!$B$8),"Year-15 window",IF(O42>=Scoring!$B$9,"Recap window",IF(O42>=11,"Late compliance","Credit period")))))))))))) -> 30-yr mark: notice window (est.) | E42: ORA19980120 | F42: WOODLEAF VILLAGE | G42: 745 WOODLEAF LN | H42: EUGENE | I42: 97405 | J42: 60 | K42: 60 | L42: =IF(OR(J42="",K42=""),"",MAX(J42-K42,0)) -> 0 | M42: Not Indicated | N42: 1998 | O42: =IF(N42="","",Scoring!$B$4-N42) -> 28 | P42: =IF(N42="","",N42+14) -> 2012 | Q42: =IF(N42="","",IF(N42<Scoring!$B$12,"n/a (pre-1990)",N42+Scoring!$B$13)) -> 2027 | R42: =IF(J42="","Unknown",IF(J42>=5,"Yes","No (under 5 units)")) -> Yes | AA42: =IF(U42<>"",(U42-Scoring!$B$3)/365.25,IF(N42="","",IF(N42<Scoring!$B$12,"",(DATE(N42+Scoring!$B$13,12,31)-Scoring!$B$3)/365.25))) -> 1.2457221 | AB42: =IF(T42="Y",0,IF(OR(D42="Expired (verified)",D42="Expiring: notice window (verified)",D42="Expiring: 10-yr horizon (verified)",D42="Past 30-yr mark (verify)",D42="30-yr mark: notice window (est.)",D42="Year-15 window"),1,0)+IF(ISNUMBER(O42),IF(O42>=Scoring!$B$10,1,0),0)+IF(AND(ISNUMBER(L42),ISNUMBER(J42)),IF(J42>0,IF(L42/J42>=Scoring!$B$11,1,0),0),0)+IF(ISNUMBER(Z42),MIN(Z42,3),0)) -> 2 | AC42: =IF(AB42>=3,Scoring!$C$24,IF(AB42=2,Scoring!$C$23,IF(AB42=1,Scoring!$C$22,0))) -> 18 | AD42: =IF(T42="Y",0,IF(ISNUMBER(X42),IF(X42>0.7,Scoring!$C$25,IF(X42>=0.5,Scoring!$C$26,IF(X42>=0.3,Scoring!$C$27,Scoring!$C$28))),Scoring!$C$29)) -> 10 | AE42: =IF(D42="Expiring: notice window (verified)",Scoring!$C$30,IF(OR(D42="Expired (verified)",D42="30-yr mark: notice window (est.)",D42="Year-15 window"),Scoring!$C$31,IF(D42="Expiring: 10-yr horizon (verified)",Scoring!$C$32,IF(D42="Past 30-yr mark (verify)",Scoring!$C$33,IF(OR(D42="Credit period",D42="Superseded record"),Scoring!$C$35,Scoring!$C$34))))) -> 14 | AF42: =IF(T42="Y",0,IF(ISNUMBER(V42),IF(Scoring!$B$4-V42>15,Scoring!$C$36,IF(Scoring!$B$4-V42>=10,Scoring!$C$37,IF(Scoring!$B$4-V42>=5,Scoring!$C$38,Scoring!$C$39))),IF(OR(N42="",D42="Out of program"),Scoring!$C$40,IF(O42>15,Scoring!$C$36,IF(O42>=10,Scoring!$C$37,IF(O42>=5,Scoring!$C$38,Scoring!$C$39)))))) -> 15 | AG42: =IF(T42="Y",0,IF(Y42="Y",Scoring!$C$41,IF(ISNUMBER(O42),IF(O42>=25,Scoring!$C$42,IF(O42>=15,Scoring!$C$43,Scoring!$C$44)),Scoring!$C$44))) -> 8 | AH42: =IF(T42="Y",0,IF(W42="",Scoring!$C$49,IFERROR(VLOOKUP(W42,Scoring!$B$45:$C$48,2,FALSE()),Scoring!$C$49))) -> 5 | AI42: =C42+IF(ISNUMBER(J42),J42,0)/100000+(10000-ROW())/1000000000 -> 70.00061
A43: =RANK(AI43,$AI$2:$AI$755) -> 42 | B43: =IF(T43="Y","Superseded",IF(C43>=Scoring!$B$16,"Immediate",IF(C43>=Scoring!$B$17,"This week",IF(C43>=Scoring!$B$18,"Nurture","Low")))) -> This week | C43: =SUM(AC43:AH43) -> 70 | D43: =IF(T43="Y","Superseded record",IF(AND(U43<>"",AA43<0),"Expired (verified)",IF(AND(U43<>"",AA43<=Scoring!$B$5),"Expiring: notice window (verified)",IF(AND(U43<>"",AA43<=Scoring!$B$6),"Expiring: 10-yr horizon (verified)",IF(M43="No Longer Monitored","Out of program",IF(N43="","Unknown vintage",IF(N43<Scoring!$B$12,"Pre-1990, still listed",IF(AND(U43="",AA43<0),"Past 30-yr mark (verify)",IF(AND(U43="",AA43<=Scoring!$B$5),"30-yr mark: notice window (est.)",IF(AND(O43>=Scoring!$B$7,O43<=Scoring!$B$8),"Year-15 window",IF(O43>=Scoring!$B$9,"Recap window",IF(O43>=11,"Late compliance","Credit period")))))))))))) -> 30-yr mark: notice window (est.) | E43: ORA19990160 | F43: VILLAGE GARDENS | G43: 15230 NE SANDY BLVD | H43: PORTLAND | I43: 97230 | J43: 59 | K43: 59 | L43: =IF(OR(J43="",K43=""),"",MAX(J43-K43,0)) -> 0 | M43: Not Indicated | N43: 1999 | O43: =IF(N43="","",Scoring!$B$4-N43) -> 27 | P43: =IF(N43="","",N43+14) -> 2013 | Q43: =IF(N43="","",IF(N43<Scoring!$B$12,"n/a (pre-1990)",N43+Scoring!$B$13)) -> 2028 | R43: =IF(J43="","Unknown",IF(J43>=5,"Yes","No (under 5 units)")) -> Yes | AA43: =IF(U43<>"",(U43-Scoring!$B$3)/365.25,IF(N43="","",IF(N43<Scoring!$B$12,"",(DATE(N43+Scoring!$B$13,12,31)-Scoring!$B$3)/365.25))) -> 2.2477755 | AB43: =IF(T43="Y",0,IF(OR(D43="Expired (verified)",D43="Expiring: notice window (verified)",D43="Expiring: 10-yr horizon (verified)",D43="Past 30-yr mark (verify)",D43="30-yr mark: notice window (est.)",D43="Year-15 window"),1,0)+IF(ISNUMBER(O43),IF(O43>=Scoring!$B$10,1,0),0)+IF(AND(ISNUMBER(L43),ISNUMBER(J43)),IF(J43>0,IF(L43/J43>=Scoring!$B$11,1,0),0),0)+IF(ISNUMBER(Z43),MIN(Z43,3),0)) -> 2 | AC43: =IF(AB43>=3,Scoring!$C$24,IF(AB43=2,Scoring!$C$23,IF(AB43=1,Scoring!$C$22,0))) -> 18 | AD43: =IF(T43="Y",0,IF(ISNUMBER(X43),IF(X43>0.7,Scoring!$C$25,IF(X43>=0.5,Scoring!$C$26,IF(X43>=0.3,Scoring!$C$27,Scoring!$C$28))),Scoring!$C$29)) -> 10 | AE43: =IF(D43="Expiring: notice window (verified)",Scoring!$C$30,IF(OR(D43="Expired (verified)",D43="30-yr mark: notice window (est.)",D43="Year-15 window"),Scoring!$C$31,IF(D43="Expiring: 10-yr horizon (verified)",Scoring!$C$32,IF(D43="Past 30-yr mark (verify)",Scoring!$C$33,IF(OR(D43="Credit period",D43="Superseded record"),Scoring!$C$35,Scoring!$C$34))))) -> 14 | AF43: =IF(T43="Y",0,IF(ISNUMBER(V43),IF(Scoring!$B$4-V43>15,Scoring!$C$36,IF(Scoring!$B$4-V43>=10,Scoring!$C$37,IF(Scoring!$B$4-V43>=5,Scoring!$C$38,Scoring!$C$39))),IF(OR(N43="",D43="Out of program"),Scoring!$C$40,IF(O43>15,Scoring!$C$36,IF(O43>=10,Scoring!$C$37,IF(O43>=5,Scoring!$C$38,Scoring!$C$39)))))) -> 15 | AG43: =IF(T43="Y",0,IF(Y43="Y",Scoring!$C$41,IF(ISNUMBER(O43),IF(O43>=25,Scoring!$C$42,IF(O43>=15,Scoring!$C$43,Scoring!$C$44)),Scoring!$C$44))) -> 8 | AH43: =IF(T43="Y",0,IF(W43="",Scoring!$C$49,IFERROR(VLOOKUP(W43,Scoring!$B$45:$C$48,2,FALSE()),Scoring!$C$49))) -> 5 | AI43: =C43+IF(ISNUMBER(J43),J43,0)/100000+(10000-ROW())/1000000000 -> 70.0006
A44: =RANK(AI44,$AI$2:$AI$755) -> 43 | B44: =IF(T44="Y","Superseded",IF(C44>=Scoring!$B$16,"Immediate",IF(C44>=Scoring!$B$17,"This week",IF(C44>=Scoring!$B$18,"Nurture","Low")))) -> This week | C44: =SUM(AC44:AH44) -> 70 | D44: =IF(T44="Y","Superseded record",IF(AND(U44<>"",AA44<0),"Expired (verified)",IF(AND(U44<>"",AA44<=Scoring!$B$5),"Expiring: notice window (verified)",IF(AND(U44<>"",AA44<=Scoring!$B$6),"Expiring: 10-yr horizon (verified)",IF(M44="No Longer Monitored","Out of program",IF(N44="","Unknown vintage",IF(N44<Scoring!$B$12,"Pre-1990, still listed",IF(AND(U44="",AA44<0),"Past 30-yr mark (verify)",IF(AND(U44="",AA44<=Scoring!$B$5),"30-yr mark: notice window (est.)",IF(AND(O44>=Scoring!$B$7,O44<=Scoring!$B$8),"Year-15 window",IF(O44>=Scoring!$B$9,"Recap window",IF(O44>=11,"Late compliance","Credit period")))))))))))) -> 30-yr mark: notice window (est.) | E44: ORA19970060 | F44: MISSION CREEK | G44: 51 UMATILLA LOOP | H44: PENDLETON | I44: 97801 | J44: 58 | K44: 58 | L44: =IF(OR(J44="",K44=""),"",MAX(J44-K44,0)) -> 0 | M44: Not Indicated | N44: 1997 | O44: =IF(N44="","",Scoring!$B$4-N44) -> 29 | P44: =IF(N44="","",N44+14) -> 2011 | Q44: =IF(N44="","",IF(N44<Scoring!$B$12,"n/a (pre-1990)",N44+Scoring!$B$13)) -> 2026 | R44: =IF(J44="","Unknown",IF(J44>=5,"Yes","No (under 5 units)")) -> Yes | AA44: =IF(U44<>"",(U44-Scoring!$B$3)/365.25,IF(N44="","",IF(N44<Scoring!$B$12,"",(DATE(N44+Scoring!$B$13,12,31)-Scoring!$B$3)/365.25))) -> 0.24640657 | AB44: =IF(T44="Y",0,IF(OR(D44="Expired (verified)",D44="Expiring: notice window (verified)",D44="Expiring: 10-yr horizon (verified)",D44="Past 30-yr mark (verify)",D44="30-yr mark: notice window (est.)",D44="Year-15 window"),1,0)+IF(ISNUMBER(O44),IF(O44>=Scoring!$B$10,1,0),0)+IF(AND(ISNUMBER(L44),ISNUMBER(J44)),IF(J44>0,IF(L44/J44>=Scoring!$B$11,1,0),0),0)+IF(ISNUMBER(Z44),MIN(Z44,3),0)) -> 2 | AC44: =IF(AB44>=3,Scoring!$C$24,IF(AB44=2,Scoring!$C$23,IF(AB44=1,Scoring!$C$22,0))) -> 18 | AD44: =IF(T44="Y",0,IF(ISNUMBER(X44),IF(X44>0.7,Scoring!$C$25,IF(X44>=0.5,Scoring!$C$26,IF(X44>=0.3,Scoring!$C$27,Scoring!$C$28))),Scoring!$C$29)) -> 10 | AE44: =IF(D44="Expiring: notice window (verified)",Scoring!$C$30,IF(OR(D44="Expired (verified)",D44="30-yr mark: notice window (est.)",D44="Year-15 window"),Scoring!$C$31,IF(D44="Expiring: 10-yr horizon (verified)",Scoring!$C$32,IF(D44="Past 30-yr mark (verify)",Scoring!$C$33,IF(OR(D44="Credit period",D44="Superseded record"),Scoring!$C$35,Scoring!$C$34))))) -> 14 | AF44: =IF(T44="Y",0,IF(ISNUMBER(V44),IF(Scoring!$B$4-V44>15,Scoring!$C$36,IF(Scoring!$B$4-V44>=10,Scoring!$C$37,IF(Scoring!$B$4-V44>=5,Scoring!$C$38,Scoring!$C$39))),IF(OR(N44="",D44="Out of program"),Scoring!$C$40,IF(O44>15,Scoring!$C$36,IF(O44>=10,Scoring!$C$37,IF(O44>=5,Scoring!$C$38,Scoring!$C$39)))))) -> 15 | AG44: =IF(T44="Y",0,IF(Y44="Y",Scoring!$C$41,IF(ISNUMBER(O44),IF(O44>=25,Scoring!$C$42,IF(O44>=15,Scoring!$C$43,Scoring!$C$44)),Scoring!$C$44))) -> 8 | AH44: =IF(T44="Y",0,IF(W44="",Scoring!$C$49,IFERROR(VLOOKUP(W44,Scoring!$B$45:$C$48,2,FALSE()),Scoring!$C$49))) -> 5 | AI44: =C44+IF(ISNUMBER(J44),J44,0)/100000+(10000-ROW())/1000000000 -> 70.00059
A45: =RANK(AI45,$AI$2:$AI$755) -> 44 | B45: =IF(T45="Y","Superseded",IF(C45>=Scoring!$B$16,"Immediate",IF(C45>=Scoring!$B$17,"This week",IF(C45>=Scoring!$B$18,"Nurture","Low")))) -> This week | C45: =SUM(AC45:AH45) -> 70 | D45: =IF(T45="Y","Superseded record",IF(AND(U45<>"",AA45<0),"Expired (verified)",IF(AND(U45<>"",AA45<=Scoring!$B$5),"Expiring: notice window (verified)",IF(AND(U45<>"",AA45<=Scoring!$B$6),"Expiring: 10-yr horizon (verified)",IF(M45="No Longer Monitored","Out of program",IF(N45="","Unknown vintage",IF(N45<Scoring!$B$12,"Pre-1990, still listed",IF(AND(U45="",AA45<0),"Past 30-yr mark (verify)",IF(AND(U45="",AA45<=Scoring!$B$5),"30-yr mark: notice window (est.)",IF(AND(O45>=Scoring!$B$7,O45<=Scoring!$B$8),"Year-15 window",IF(O45>=Scoring!$B$9,"Recap window",IF(O45>=11,"Late compliance","Credit period")))))))))))) -> 30-yr mark: notice window (est.) | E45: ORA19989126 | F45: SIERRA WEST | G45: 356 SE 12TH AVE | H45: HILLSBORO | I45: 97123 | J45: 56 | K45: 55 | L45: =IF(OR(J45="",K45=""),"",MAX(J45-K45,0)) -> 1 | M45: Not Indicated | N45: 1998 | O45: =IF(N45="","",Scoring!$B$4-N45) -> 28 | P45: =IF(N45="","",N45+14) -> 2012 | Q45: =IF(N45="","",IF(N45<Scoring!$B$12,"n/a (pre-1990)",N45+Scoring!$B$13)) -> 2027 | R45: =IF(J45="","Unknown",IF(J45>=5,"Yes","No (under 5 units)")) -> Yes | AA45: =IF(U45<>"",(U45-Scoring!$B$3)/365.25,IF(N45="","",IF(N45<Scoring!$B$12,"",(DATE(N45+Scoring!$B$13,12,31)-Scoring!$B$3)/365.25))) -> 1.2457221 | AB45: =IF(T45="Y",0,IF(OR(D45="Expired (verified)",D45="Expiring: notice window (verified)",D45="Expiring: 10-yr horizon (verified)",D45="Past 30-yr mark (verify)",D45="30-yr mark: notice window (est.)",D45="Year-15 window"),1,0)+IF(ISNUMBER(O45),IF(O45>=Scoring!$B$10,1,0),0)+IF(AND(ISNUMBER(L45),ISNUMBER(J45)),IF(J45>0,IF(L45/J45>=Scoring!$B$11,1,0),0),0)+IF(ISNUMBER(Z45),MIN(Z45,3),0)) -> 2 | AC45: =IF(AB45>=3,Scoring!$C$24,IF(AB45=2,Scoring!$C$23,IF(AB45=1,Scoring!$C$22,0))) -> 18 | AD45: =IF(T45="Y",0,IF(ISNUMBER(X45),IF(X45>0.7,Scoring!$C$25,IF(X45>=0.5,Scoring!$C$26,IF(X45>=0.3,Scoring!$C$27,Scoring!$C$28))),Scoring!$C$29)) -> 10 | AE45: =IF(D45="Expiring: notice window (verified)",Scoring!$C$30,IF(OR(D45="Expired (verified)",D45="30-yr mark: notice window (est.)",D45="Year-15 window"),Scoring!$C$31,IF(D45="Expiring: 10-yr horizon (verified)",Scoring!$C$32,IF(D45="Past 30-yr mark (verify)",Scoring!$C$33,IF(OR(D45="Credit period",D45="Superseded record"),Scoring!$C$35,Scoring!$C$34))))) -> 14 | AF45: =IF(T45="Y",0,IF(ISNUMBER(V45),IF(Scoring!$B$4-V45>15,Scoring!$C$36,IF(Scoring!$B$4-V45>=10,Scoring!$C$37,IF(Scoring!$B$4-V45>=5,Scoring!$C$38,Scoring!$C$39))),IF(OR(N45="",D45="Out of program"),Scoring!$C$40,IF(O45>15,Scoring!$C$36,IF(O45>=10,Scoring!$C$37,IF(O45>=5,Scoring!$C$38,Scoring!$C$39)))))) -> 15 | AG45: =IF(T45="Y",0,IF(Y45="Y",Scoring!$C$41,IF(ISNUMBER(O45),IF(O45>=25,Scoring!$C$42,IF(O45>=15,Scoring!$C$43,Scoring!$C$44)),Scoring!$C$44))) -> 8 | AH45: =IF(T45="Y",0,IF(W45="",Scoring!$C$49,IFERROR(VLOOKUP(W45,Scoring!$B$45:$C$48,2,FALSE()),Scoring!$C$49))) -> 5 | AI45: =C45+IF(ISNUMBER(J45),J45,0)/100000+(10000-ROW())/1000000000 -> 70.00057
A46: =RANK(AI46,$AI$2:$AI$755) -> 45 | B46: =IF(T46="Y","Superseded",IF(C46>=Scoring!$B$16,"Immediate",IF(C46>=Scoring!$B$17,"This week",IF(C46>=Scoring!$B$18,"Nurture","Low")))) -> This week | C46: =SUM(AC46:AH46) -> 70 | D46: =IF(T46="Y","Superseded record",IF(AND(U46<>"",AA46<0),"Expired (verified)",IF(AND(U46<>"",AA46<=Scoring!$B$5),"Expiring: notice window (verified)",IF(AND(U46<>"",AA46<=Scoring!$B$6),"Expiring: 10-yr horizon (verified)",IF(M46="No Longer Monitored","Out of program",IF(N46="","Unknown vintage",IF(N46<Scoring!$B$12,"Pre-1990, still listed",IF(AND(U46="",AA46<0),"Past 30-yr mark (verify)",IF(AND(U46="",AA46<=Scoring!$B$5),"30-yr mark: notice window (est.)",IF(AND(O46>=Scoring!$B$7,O46<=Scoring!$B$8),"Year-15 window",IF(O46>=Scoring!$B$9,"Recap window",IF(O46>=11,"Late compliance","Credit period")))))))))))) -> 30-yr mark: notice window (est.) | E46: ORA19990080 | F46: MACDONALD CTR ALF | G46: 615 NW COUCH ST | H46: PORTLAND | I46: 97209 | J46: 54 | K46: 54 | L46: =IF(OR(J46="",K46=""),"",MAX(J46-K46,0)) -> 0 | M46: Not Indicated | N46: 1999 | O46: =IF(N46="","",Scoring!$B$4-N46) -> 27 | P46: =IF(N46="","",N46+14) -> 2013 | Q46: =IF(N46="","",IF(N46<Scoring!$B$12,"n/a (pre-1990)",N46+Scoring!$B$13)) -> 2028 | R46: =IF(J46="","Unknown",IF(J46>=5,"Yes","No (under 5 units)")) -> Yes | AA46: =IF(U46<>"",(U46-Scoring!$B$3)/365.25,IF(N46="","",IF(N46<Scoring!$B$12,"",(DATE(N46+Scoring!$B$13,12,31)-Scoring!$B$3)/365.25))) -> 2.2477755 | AB46: =IF(T46="Y",0,IF(OR(D46="Expired (verified)",D46="Expiring: notice window (verified)",D46="Expiring: 10-yr horizon (verified)",D46="Past 30-yr mark (verify)",D46="30-yr mark: notice window (est.)",D46="Year-15 window"),1,0)+IF(ISNUMBER(O46),IF(O46>=Scoring!$B$10,1,0),0)+IF(AND(ISNUMBER(L46),ISNUMBER(J46)),IF(J46>0,IF(L46/J46>=Scoring!$B$11,1,0),0),0)+IF(ISNUMBER(Z46),MIN(Z46,3),0)) -> 2 | AC46: =IF(AB46>=3,Scoring!$C$24,IF(AB46=2,Scoring!$C$23,IF(AB46=1,Scoring!$C$22,0))) -> 18 | AD46: =IF(T46="Y",0,IF(ISNUMBER(X46),IF(X46>0.7,Scoring!$C$25,IF(X46>=0.5,Scoring!$C$26,IF(X46>=0.3,Scoring!$C$27,Scoring!$C$28))),Scoring!$C$29)) -> 10 | AE46: =IF(D46="Expiring: notice window (verified)",Scoring!$C$30,IF(OR(D46="Expired (verified)",D46="30-yr mark: notice window (est.)",D46="Year-15 window"),Scoring!$C$31,IF(D46="Expiring: 10-yr horizon (verified)",Scoring!$C$32,IF(D46="Past 30-yr mark (verify)",Scoring!$C$33,IF(OR(D46="Credit period",D46="Superseded record"),Scoring!$C$35,Scoring!$C$34))))) -> 14 | AF46: =IF(T46="Y",0,IF(ISNUMBER(V46),IF(Scoring!$B$4-V46>15,Scoring!$C$36,IF(Scoring!$B$4-V46>=10,Scoring!$C$37,IF(Scoring!$B$4-V46>=5,Scoring!$C$38,Scoring!$C$39))),IF(OR(N46="",D46="Out of program"),Scoring!$C$40,IF(O46>15,Scoring!$C$36,IF(O46>=10,Scoring!$C$37,IF(O46>=5,Scoring!$C$38,Scoring!$C$39)))))) -> 15 | AG46: =IF(T46="Y",0,IF(Y46="Y",Scoring!$C$41,IF(ISNUMBER(O46),IF(O46>=25,Scoring!$C$42,IF(O46>=15,Scoring!$C$43,Scoring!$C$44)),Scoring!$C$44))) -> 8 | AH46: =IF(T46="Y",0,IF(W46="",Scoring!$C$49,IFERROR(VLOOKUP(W46,Scoring!$B$45:$C$48,2,FALSE()),Scoring!$C$49))) -> 5 | AI46: =C46+IF(ISNUMBER(J46),J46,0)/100000+(10000-ROW())/1000000000 -> 70.00055
A47: =RANK(AI47,$AI$2:$AI$755) -> 46 | B47: =IF(T47="Y","Superseded",IF(C47>=Scoring!$B$16,"Immediate",IF(C47>=Scoring!$B$17,"This week",IF(C47>=Scoring!$B$18,"Nurture","Low")))) -> This week | C47: =SUM(AC47:AH47) -> 70 | D47: =IF(T47="Y","Superseded record",IF(AND(U47<>"",AA47<0),"Expired (verified)",IF(AND(U47<>"",AA47<=Scoring!$B$5),"Expiring: notice window (verified)",IF(AND(U47<>"",AA47<=Scoring!$B$6),"Expiring: 10-yr horizon (verified)",IF(M47="No Longer Monitored","Out of program",IF(N47="","Unknown vintage",IF(N47<Scoring!$B$12,"Pre-1990, still listed",IF(AND(U47="",AA47<0),"Past 30-yr mark (verify)",IF(AND(U47="",AA47<=Scoring!$B$5),"30-yr mark: notice window (est.)",IF(AND(O47>=Scoring!$B$7,O47<=Scoring!$B$8),"Year-15 window",IF(O47>=Scoring!$B$9,"Recap window",IF(O47>=11,"Late compliance","Credit period")))))))))))) -> 30-yr mark: notice window (est.) | E47: ORA19990100 | F47: NEWPORT APTS | G47: 125 NW 60TH ST | H47: NEWPORT | I47: 97365 | J47: 52 | K47: 51 | L47: =IF(OR(J47="",K47=""),"",MAX(J47-K47,0)) -> 1 | M47: Not Indicated | N47: 1999 | O47: =IF(N47="","",Scoring!$B$4-N47) -> 27 | P47: =IF(N47="","",N47+14) -> 2013 | Q47: =IF(N47="","",IF(N47<Scoring!$B$12,"n/a (pre-1990)",N47+Scoring!$B$13)) -> 2028 | R47: =IF(J47="","Unknown",IF(J47>=5,"Yes","No (under 5 units)")) -> Yes | AA47: =IF(U47<>"",(U47-Scoring!$B$3)/365.25,IF(N47="","",IF(N47<Scoring!$B$12,"",(DATE(N47+Scoring!$B$13,12,31)-Scoring!$B$3)/365.25))) -> 2.2477755 | AB47: =IF(T47="Y",0,IF(OR(D47="Expired (verified)",D47="Expiring: notice window (verified)",D47="Expiring: 10-yr horizon (verified)",D47="Past 30-yr mark (verify)",D47="30-yr mark: notice window (est.)",D47="Year-15 window"),1,0)+IF(ISNUMBER(O47),IF(O47>=Scoring!$B$10,1,0),0)+IF(AND(ISNUMBER(L47),ISNUMBER(J47)),IF(J47>0,IF(L47/J47>=Scoring!$B$11,1,0),0),0)+IF(ISNUMBER(Z47),MIN(Z47,3),0)) -> 2 | AC47: =IF(AB47>=3,Scoring!$C$24,IF(AB47=2,Scoring!$C$23,IF(AB47=1,Scoring!$C$22,0))) -> 18 | AD47: =IF(T47="Y",0,IF(ISNUMBER(X47),IF(X47>0.7,Scoring!$C$25,IF(X47>=0.5,Scoring!$C$26,IF(X47>=0.3,Scoring!$C$27,Scoring!$C$28))),Scoring!$C$29)) -> 10 | AE47: =IF(D47="Expiring: notice window (verified)",Scoring!$C$30,IF(OR(D47="Expired (verified)",D47="30-yr mark: notice window (est.)",D47="Year-15 window"),Scoring!$C$31,IF(D47="Expiring: 10-yr horizon (verified)",Scoring!$C$32,IF(D47="Past 30-yr mark (verify)",Scoring!$C$33,IF(OR(D47="Credit period",D47="Superseded record"),Scoring!$C$35,Scoring!$C$34))))) -> 14 | AF47: =IF(T47="Y",0,IF(ISNUMBER(V47),IF(Scoring!$B$4-V47>15,Scoring!$C$36,IF(Scoring!$B$4-V47>=10,Scoring!$C$37,IF(Scoring!$B$4-V47>=5,Scoring!$C$38,Scoring!$C$39))),IF(OR(N47="",D47="Out of program"),Scoring!$C$40,IF(O47>15,Scoring!$C$36,IF(O47>=10,Scoring!$C$37,IF(O47>=5,Scoring!$C$38,Scoring!$C$39)))))) -> 15 | AG47: =IF(T47="Y",0,IF(Y47="Y",Scoring!$C$41,IF(ISNUMBER(O47),IF(O47>=25,Scoring!$C$42,IF(O47>=15,Scoring!$C$43,Scoring!$C$44)),Scoring!$C$44))) -> 8 | AH47: =IF(T47="Y",0,IF(W47="",Scoring!$C$49,IFERROR(VLOOKUP(W47,Scoring!$B$45:$C$48,2,FALSE()),Scoring!$C$49))) -> 5 | AI47: =C47+IF(ISNUMBER(J47),J47,0)/100000+(10000-ROW())/1000000000 -> 70.00053
A48: =RANK(AI48,$AI$2:$AI$755) -> 47 | B48: =IF(T48="Y","Superseded",IF(C48>=Scoring!$B$16,"Immediate",IF(C48>=Scoring!$B$17,"This week",IF(C48>=Scoring!$B$18,"Nurture","Low")))) -> This week | C48: =SUM(AC48:AH48) -> 70 | D48: =IF(T48="Y","Superseded record",IF(AND(U48<>"",AA48<0),"Expired (verified)",IF(AND(U48<>"",AA48<=Scoring!$B$5),"Expiring: notice window (verified)",IF(AND(U48<>"",AA48<=Scoring!$B$6),"Expiring: 10-yr horizon (verified)",IF(M48="No Longer Monitored","Out of program",IF(N48="","Unknown vintage",IF(N48<Scoring!$B$12,"Pre-1990, still listed",IF(AND(U48="",AA48<0),"Past 30-yr mark (verify)",IF(AND(U48="",AA48<=Scoring!$B$5),"30-yr mark: notice window (est.)",IF(AND(O48>=Scoring!$B$7,O48<=Scoring!$B$8),"Year-15 window",IF(O48>=Scoring!$B$9,"Recap window",IF(O48>=11,"Late compliance","Credit period")))))))))))) -> 30-yr mark: notice window (est.) | E48: ORA19980115 | F48: WOLF RIDGE | G48: 1301 E SANTIAM ST | H48: STAYTON | I48: 97383 | J48: 51 | K48: 51 | L48: =IF(OR(J48="",K48=""),"",MAX(J48-K48,0)) -> 0 | M48: Not Indicated | N48: 1998 | O48: =IF(N48="","",Scoring!$B$4-N48) -> 28 | P48: =IF(N48="","",N48+14) -> 2012 | Q48: =IF(N48="","",IF(N48<Scoring!$B$12,"n/a (pre-1990)",N48+Scoring!$B$13)) -> 2027 | R48: =IF(J48="","Unknown",IF(J48>=5,"Yes","No (under 5 units)")) -> Yes | AA48: =IF(U48<>"",(U48-Scoring!$B$3)/365.25,IF(N48="","",IF(N48<Scoring!$B$12,"",(DATE(N48+Scoring!$B$13,12,31)-Scoring!$B$3)/365.25))) -> 1.2457221 | AB48: =IF(T48="Y",0,IF(OR(D48="Expired (verified)",D48="Expiring: notice window (verified)",D48="Expiring: 10-yr horizon (verified)",D48="Past 30-yr mark (verify)",D48="30-yr mark: notice window (est.)",D48="Year-15 window"),1,0)+IF(ISNUMBER(O48),IF(O48>=Scoring!$B$10,1,0),0)+IF(AND(ISNUMBER(L48),ISNUMBER(J48)),IF(J48>0,IF(L48/J48>=Scoring!$B$11,1,0),0),0)+IF(ISNUMBER(Z48),MIN(Z48,3),0)) -> 2 | AC48: =IF(AB48>=3,Scoring!$C$24,IF(AB48=2,Scoring!$C$23,IF(AB48=1,Scoring!$C$22,0))) -> 18 | AD48: =IF(T48="Y",0,IF(ISNUMBER(X48),IF(X48>0.7,Scoring!$C$25,IF(X48>=0.5,Scoring!$C$26,IF(X48>=0.3,Scoring!$C$27,Scoring!$C$28))),Scoring!$C$29)) -> 10 | AE48: =IF(D48="Expiring: notice window (verified)",Scoring!$C$30,IF(OR(D48="Expired (verified)",D48="30-yr mark: notice window (est.)",D48="Year-15 window"),Scoring!$C$31,IF(D48="Expiring: 10-yr horizon (verified)",Scoring!$C$32,IF(D48="Past 30-yr mark (verify)",Scoring!$C$33,IF(OR(D48="Credit period",D48="Superseded record"),Scoring!$C$35,Scoring!$C$34))))) -> 14 | AF48: =IF(T48="Y",0,IF(ISNUMBER(V48),IF(Scoring!$B$4-V48>15,Scoring!$C$36,IF(Scoring!$B$4-V48>=10,Scoring!$C$37,IF(Scoring!$B$4-V48>=5,Scoring!$C$38,Scoring!$C$39))),IF(OR(N48="",D48="Out of program"),Scoring!$C$40,IF(O48>15,Scoring!$C$36,IF(O48>=10,Scoring!$C$37,IF(O48>=5,Scoring!$C$38,Scoring!$C$39)))))) -> 15 | AG48: =IF(T48="Y",0,IF(Y48="Y",Scoring!$C$41,IF(ISNUMBER(O48),IF(O48>=25,Scoring!$C$42,IF(O48>=15,Scoring!$C$43,Scoring!$C$44)),Scoring!$C$44))) -> 8 | AH48: =IF(T48="Y",0,IF(W48="",Scoring!$C$49,IFERROR(VLOOKUP(W48,Scoring!$B$45:$C$48,2,FALSE()),Scoring!$C$49))) -> 5 | AI48: =C48+IF(ISNUMBER(J48),J48,0)/100000+(10000-ROW())/1000000000 -> 70.00052
A49: =RANK(AI49,$AI$2:$AI$755) -> 48 | B49: =IF(T49="Y","Superseded",IF(C49>=Scoring!$B$16,"Immediate",IF(C49>=Scoring!$B$17,"This week",IF(C49>=Scoring!$B$18,"Nurture","Low")))) -> This week | C49: =SUM(AC49:AH49) -> 70 | D49: =IF(T49="Y","Superseded record",IF(AND(U49<>"",AA49<0),"Expired (verified)",IF(AND(U49<>"",AA49<=Scoring!$B$5),"Expiring: notice window (verified)",IF(AND(U49<>"",AA49<=Scoring!$B$6),"Expiring: 10-yr horizon (verified)",IF(M49="No Longer Monitored","Out of program",IF(N49="","Unknown vintage",IF(N49<Scoring!$B$12,"Pre-1990, still listed",IF(AND(U49="",AA49<0),"Past 30-yr mark (verify)",IF(AND(U49="",AA49<=Scoring!$B$5),"30-yr mark: notice window (est.)",IF(AND(O49>=Scoring!$B$7,O49<=Scoring!$B$8),"Year-15 window",IF(O49>=Scoring!$B$9,"Recap window",IF(O49>=11,"Late compliance","Credit period")))))))))))) -> 30-yr mark: notice window (est.) | E49: ORA19980045 | F49: CASCADE HOUSE AT HOPE VILLAGE | G49: 1555 S IVY ST | H49: CANBY | I49: 97013 | J49: 50 | K49: 50 | L49: =IF(OR(J49="",K49=""),"",MAX(J49-K49,0)) -> 0 | M49: Not Indicated | N49: 1998 | O49: =IF(N49="","",Scoring!$B$4-N49) -> 28 | P49: =IF(N49="","",N49+14) -> 2012 | Q49: =IF(N49="","",IF(N49<Scoring!$B$12,"n/a (pre-1990)",N49+Scoring!$B$13)) -> 2027 | R49: =IF(J49="","Unknown",IF(J49>=5,"Yes","No (under 5 units)")) -> Yes | AA49: =IF(U49<>"",(U49-Scoring!$B$3)/365.25,IF(N49="","",IF(N49<Scoring!$B$12,"",(DATE(N49+Scoring!$B$13,12,31)-Scoring!$B$3)/365.25))) -> 1.2457221 | AB49: =IF(T49="Y",0,IF(OR(D49="Expired (verified)",D49="Expiring: notice window (verified)",D49="Expiring: 10-yr horizon (verified)",D49="Past 30-yr mark (verify)",D49="30-yr mark: notice window (est.)",D49="Year-15 window"),1,0)+IF(ISNUMBER(O49),IF(O49>=Scoring!$B$10,1,0),0)+IF(AND(ISNUMBER(L49),ISNUMBER(J49)),IF(J49>0,IF(L49/J49>=Scoring!$B$11,1,0),0),0)+IF(ISNUMBER(Z49),MIN(Z49,3),0)) -> 2 | AC49: =IF(AB49>=3,Scoring!$C$24,IF(AB49=2,Scoring!$C$23,IF(AB49=1,Scoring!$C$22,0))) -> 18 | AD49: =IF(T49="Y",0,IF(ISNUMBER(X49),IF(X49>0.7,Scoring!$C$25,IF(X49>=0.5,Scoring!$C$26,IF(X49>=0.3,Scoring!$C$27,Scoring!$C$28))),Scoring!$C$29)) -> 10 | AE49: =IF(D49="Expiring: notice window (verified)",Scoring!$C$30,IF(OR(D49="Expired (verified)",D49="30-yr mark: notice window (est.)",D49="Year-15 window"),Scoring!$C$31,IF(D49="Expiring: 10-yr horizon (verified)",Scoring!$C$32,IF(D49="Past 30-yr mark (verify)",Scoring!$C$33,IF(OR(D49="Credit period",D49="Superseded record"),Scoring!$C$35,Scoring!$C$34))))) -> 14 | AF49: =IF(T49="Y",0,IF(ISNUMBER(V49),IF(Scoring!$B$4-V49>15,Scoring!$C$36,IF(Scoring!$B$4-V49>=10,Scoring!$C$37,IF(Scoring!$B$4-V49>=5,Scoring!$C$38,Scoring!$C$39))),IF(OR(N49="",D49="Out of program"),Scoring!$C$40,IF(O49>15,Scoring!$C$36,IF(O49>=10,Scoring!$C$37,IF(O49>=5,Scoring!$C$38,Scoring!$C$39)))))) -> 15 | AG49: =IF(T49="Y",0,IF(Y49="Y",Scoring!$C$41,IF(ISNUMBER(O49),IF(O49>=25,Scoring!$C$42,IF(O49>=15,Scoring!$C$43,Scoring!$C$44)),Scoring!$C$44))) -> 8 | AH49: =IF(T49="Y",0,IF(W49="",Scoring!$C$49,IFERROR(VLOOKUP(W49,Scoring!$B$45:$C$48,2,FALSE()),Scoring!$C$49))) -> 5 | AI49: =C49+IF(ISNUMBER(J49),J49,0)/100000+(10000-ROW())/1000000000 -> 70.00051
A50: =RANK(AI50,$AI$2:$AI$755) -> 49 | B50: =IF(T50="Y","Superseded",IF(C50>=Scoring!$B$16,"Immediate",IF(C50>=Scoring!$B$17,"This week",IF(C50>=Scoring!$B$18,"Nurture","Low")))) -> This week | C50: =SUM(AC50:AH50) -> 70 | D50: =IF(T50="Y","Superseded record",IF(AND(U50<>"",AA50<0),"Expired (verified)",IF(AND(U50<>"",AA50<=Scoring!$B$5),"Expiring: notice window (verified)",IF(AND(U50<>"",AA50<=Scoring!$B$6),"Expiring: 10-yr horizon (verified)",IF(M50="No Longer Monitored","Out of program",IF(N50="","Unknown vintage",IF(N50<Scoring!$B$12,"Pre-1990, still listed",IF(AND(U50="",AA50<0),"Past 30-yr mark (verify)",IF(AND(U50="",AA50<=Scoring!$B$5),"30-yr mark: notice window (est.)",IF(AND(O50>=Scoring!$B$7,O50<=Scoring!$B$8),"Year-15 window",IF(O50>=Scoring!$B$9,"Recap window",IF(O50>=11,"Late compliance","Credit period")))))))))))) -> 30-yr mark: notice window (est.) | E50: ORA19970040 | F50: HAILEY PLACE APTS | G50: 600 SW 30TH ST | H50: PENDLETON | I50: 97801 | J50: 48 | K50: 48 | L50: =IF(OR(J50="",K50=""),"",MAX(J50-K50,0)) -> 0 | M50: Not Indicated | N50: 1997 | O50: =IF(N50="","",Scoring!$B$4-N50) -> 29 | P50: =IF(N50="","",N50+14) -> 2011 | Q50: =IF(N50="","",IF(N50<Scoring!$B$12,"n/a (pre-1990)",N50+Scoring!$B$13)) -> 2026 | R50: =IF(J50="","Unknown",IF(J50>=5,"Yes","No (under 5 units)")) -> Yes | AA50: =IF(U50<>"",(U50-Scoring!$B$3)/365.25,IF(N50="","",IF(N50<Scoring!$B$12,"",(DATE(N50+Scoring!$B$13,12,31)-Scoring!$B$3)/365.25))) -> 0.24640657 | AB50: =IF(T50="Y",0,IF(OR(D50="Expired (verified)",D50="Expiring: notice window (verified)",D50="Expiring: 10-yr horizon (verified)",D50="Past 30-yr mark (verify)",D50="30-yr mark: notice window (est.)",D50="Year-15 window"),1,0)+IF(ISNUMBER(O50),IF(O50>=Scoring!$B$10,1,0),0)+IF(AND(ISNUMBER(L50),ISNUMBER(J50)),IF(J50>0,IF(L50/J50>=Scoring!$B$11,1,0),0),0)+IF(ISNUMBER(Z50),MIN(Z50,3),0)) -> 2 | AC50: =IF(AB50>=3,Scoring!$C$24,IF(AB50=2,Scoring!$C$23,IF(AB50=1,Scoring!$C$22,0))) -> 18 | AD50: =IF(T50="Y",0,IF(ISNUMBER(X50),IF(X50>0.7,Scoring!$C$25,IF(X50>=0.5,Scoring!$C$26,IF(X50>=0.3,Scoring!$C$27,Scoring!$C$28))),Scoring!$C$29)) -> 10 | AE50: =IF(D50="Expiring: notice window (verified)",Scoring!$C$30,IF(OR(D50="Expired (verified)",D50="30-yr mark: notice window (est.)",D50="Year-15 window"),Scoring!$C$31,IF(D50="Expiring: 10-yr horizon (verified)",Scoring!$C$32,IF(D50="Past 30-yr mark (verify)",Scoring!$C$33,IF(OR(D50="Credit period",D50="Superseded record"),Scoring!$C$35,Scoring!$C$34))))) -> 14 | AF50: =IF(T50="Y",0,IF(ISNUMBER(V50),IF(Scoring!$B$4-V50>15,Scoring!$C$36,IF(Scoring!$B$4-V50>=10,Scoring!$C$37,IF(Scoring!$B$4-V50>=5,Scoring!$C$38,Scoring!$C$39))),IF(OR(N50="",D50="Out of program"),Scoring!$C$40,IF(O50>15,Scoring!$C$36,IF(O50>=10,Scoring!$C$37,IF(O50>=5,Scoring!$C$38,Scoring!$C$39)))))) -> 15 | AG50: =IF(T50="Y",0,IF(Y50="Y",Scoring!$C$41,IF(ISNUMBER(O50),IF(O50>=25,Scoring!$C$42,IF(O50>=15,Scoring!$C$43,Scoring!$C$44)),Scoring!$C$44))) -> 8 | AH50: =IF(T50="Y",0,IF(W50="",Scoring!$C$49,IFERROR(VLOOKUP(W50,Scoring!$B$45:$C$48,2,FALSE()),Scoring!$C$49))) -> 5 | AI50: =C50+IF(ISNUMBER(J50),J50,0)/100000+(10000-ROW())/1000000000 -> 70.00049
... A80: =RANK(AI80,$AI$2:$AI$755) -> 79 | B80: =IF(T80="Y","Superseded",IF(C80>=Scoring!$B$16,"Immediate",IF(C80>=Scoring!$B$17,"This week",IF(C80>=Scoring!$B$18,"Nurture","Low")))) -> This week | C80: =SUM(AC80:AH80) -> 70 | D80: =IF(T80="Y","Superseded record",IF(AND(U80<>"",AA80<0),"Expired (verified)",IF(AND(U80<>"",AA80<=Scoring!$B$5),"Expiring: notice window (verified)",IF(AND(U80<>"",AA80<=Scoring!$B$6),"Expiring: 10-yr horizon (verified)",IF(M80="No Longer Monitored","Out of program",IF(N80="","Unknown vintage",IF(N80<Scoring!$B$12,"Pre-1990, still listed",IF(AND(U80="",AA80<0),"Past 30-yr mark (verify)",IF(AND(U80="",AA80<=Scoring!$B$5),"30-yr mark: notice window (est.)",IF(AND(O80>=Scoring!$B$7,O80<=Scoring!$B$8),"Year-15 window",IF(O80>=Scoring!$B$9,"Recap window",IF(O80>=11,"Late compliance","Credit period")))))))))))) -> 30-yr mark: notice window (est.) | E80: ORA19970045 | F80: KELLY PLACE APTS | G80: 1215 NE KELLY AVE | H80: GRESHAM | I80: 97030 | J80: 20 | K80: 20 | L80: =IF(OR(J80="",K80=""),"",MAX(J80-K80,0)) -> 0 | M80: Not Indicated | N80: 1997 | O80: =IF(N80="","",Scoring!$B$4-N80) -> 29 | P80: =IF(N80="","",N80+14) -> 2011 | Q80: =IF(N80="","",IF(N80<Scoring!$B$12,"n/a (pre-1990)",N80+Scoring!$B$13)) -> 2026 | R80: =IF(J80="","Unknown",IF(J80>=5,"Yes","No (under 5 units)")) -> Yes | AA80: =IF(U80<>"",(U80-Scoring!$B$3)/365.25,IF(N80="","",IF(N80<Scoring!$B$12,"",(DATE(N80+Scoring!$B$13,12,31)-Scoring!$B$3)/365.25))) -> 0.24640657 | AB80: =IF(T80="Y",0,IF(OR(D80="Expired (verified)",D80="Expiring: notice window (verified)",D80="Expiring: 10-yr horizon (verified)",D80="Past 30-yr mark (verify)",D80="30-yr mark: notice window (est.)",D80="Year-15 window"),1,0)+IF(ISNUMBER(O80),IF(O80>=Scoring!$B$10,1,0),0)+IF(AND(ISNUMBER(L80),ISNUMBER(J80)),IF(J80>0,IF(L80/J80>=Scoring!$B$11,1,0),0),0)+IF(ISNUMBER(Z80),MIN(Z80,3),0)) -> 2 | AC80: =IF(AB80>=3,Scoring!$C$24,IF(AB80=2,Scoring!$C$23,IF(AB80=1,Scoring!$C$22,0))) -> 18 | AD80: =IF(T80="Y",0,IF(ISNUMBER(X80),IF(X80>0.7,Scoring!$C$25,IF(X80>=0.5,Scoring!$C$26,IF(X80>=0.3,Scoring!$C$27,Scoring!$C$28))),Scoring!$C$29)) -> 10 | AE80: =IF(D80="Expiring: notice window (verified)",Scoring!$C$30,IF(OR(D80="Expired (verified)",D80="30-yr mark: notice window (est.)",D80="Year-15 window"),Scoring!$C$31,IF(D80="Expiring: 10-yr horizon (verified)",Scoring!$C$32,IF(D80="Past 30-yr mark (verify)",Scoring!$C$33,IF(OR(D80="Credit period",D80="Superseded record"),Scoring!$C$35,Scoring!$C$34))))) -> 14 | AF80: =IF(T80="Y",0,IF(ISNUMBER(V80),IF(Scoring!$B$4-V80>15,Scoring!$C$36,IF(Scoring!$B$4-V80>=10,Scoring!$C$37,IF(Scoring!$B$4-V80>=5,Scoring!$C$38,Scoring!$C$39))),IF(OR(N80="",D80="Out of program"),Scoring!$C$40,IF(O80>15,Scoring!$C$36,IF(O80>=10,Scoring!$C$37,IF(O80>=5,Scoring!$C$38,Scoring!$C$39)))))) -> 15 | AG80: =IF(T80="Y",0,IF(Y80="Y",Scoring!$C$41,IF(ISNUMBER(O80),IF(O80>=25,Scoring!$C$42,IF(O80>=15,Scoring!$C$43,Scoring!$C$44)),Scoring!$C$44))) -> 8 | AH80: =IF(T80="Y",0,IF(W80="",Scoring!$C$49,IFERROR(VLOOKUP(W80,Scoring!$B$45:$C$48,2,FALSE()),Scoring!$C$49))) -> 5 | AI80: =C80+IF(ISNUMBER(J80),J80,0)/100000+(10000-ROW())/1000000000 -> 70.00021
A81: =RANK(AI81,$AI$2:$AI$755) -> 80 | B81: =IF(T81="Y","Superseded",IF(C81>=Scoring!$B$16,"Immediate",IF(C81>=Scoring!$B$17,"This week",IF(C81>=Scoring!$B$18,"Nurture","Low")))) -> This week | C81: =SUM(AC81:AH81) -> 70 | D81: =IF(T81="Y","Superseded record",IF(AND(U81<>"",AA81<0),"Expired (verified)",IF(AND(U81<>"",AA81<=Scoring!$B$5),"Expiring: notice window (verified)",IF(AND(U81<>"",AA81<=Scoring!$B$6),"Expiring: 10-yr horizon (verified)",IF(M81="No Longer Monitored","Out of program",IF(N81="","Unknown vintage",IF(N81<Scoring!$B$12,"Pre-1990, still listed",IF(AND(U81="",AA81<0),"Past 30-yr mark (verify)",IF(AND(U81="",AA81<=Scoring!$B$5),"30-yr mark: notice window (est.)",IF(AND(O81>=Scoring!$B$7,O81<=Scoring!$B$8),"Year-15 window",IF(O81>=Scoring!$B$9,"Recap window",IF(O81>=11,"Late compliance","Credit period")))))))))))) -> 30-yr mark: notice window (est.) | E81: ORA19980085 | F81: MYRTLE TERRACE | G81: 1135 SIMPSON ST | H81: MYRTLE CREEK | J81: 20 | K81: 20 | L81: =IF(OR(J81="",K81=""),"",MAX(J81-K81,0)) -> 0 | M81: Not Indicated | N81: 1998 | O81: =IF(N81="","",Scoring!$B$4-N81) -> 28 | P81: =IF(N81="","",N81+14) -> 2012 | Q81: =IF(N81="","",IF(N81<Scoring!$B$12,"n/a (pre-1990)",N81+Scoring!$B$13)) -> 2027 | R81: =IF(J81="","Unknown",IF(J81>=5,"Yes","No (under 5 units)")) -> Yes | AA81: =IF(U81<>"",(U81-Scoring!$B$3)/365.25,IF(N81="","",IF(N81<Scoring!$B$12,"",(DATE(N81+Scoring!$B$13,12,31)-Scoring!$B$3)/365.25))) -> 1.2457221 | AB81: =IF(T81="Y",0,IF(OR(D81="Expired (verified)",D81="Expiring: notice window (verified)",D81="Expiring: 10-yr horizon (verified)",D81="Past 30-yr mark (verify)",D81="30-yr mark: notice window (est.)",D81="Year-15 window"),1,0)+IF(ISNUMBER(O81),IF(O81>=Scoring!$B$10,1,0),0)+IF(AND(ISNUMBER(L81),ISNUMBER(J81)),IF(J81>0,IF(L81/J81>=Scoring!$B$11,1,0),0),0)+IF(ISNUMBER(Z81),MIN(Z81,3),0)) -> 2 | AC81: =IF(AB81>=3,Scoring!$C$24,IF(AB81=2,Scoring!$C$23,IF(AB81=1,Scoring!$C$22,0))) -> 18 | AD81: =IF(T81="Y",0,IF(ISNUMBER(X81),IF(X81>0.7,Scoring!$C$25,IF(X81>=0.5,Scoring!$C$26,IF(X81>=0.3,Scoring!$C$27,Scoring!$C$28))),Scoring!$C$29)) -> 10 | AE81: =IF(D81="Expiring: notice window (verified)",Scoring!$C$30,IF(OR(D81="Expired (verified)",D81="30-yr mark: notice window (est.)",D81="Year-15 window"),Scoring!$C$31,IF(D81="Expiring: 10-yr horizon (verified)",Scoring!$C$32,IF(D81="Past 30-yr mark (verify)",Scoring!$C$33,IF(OR(D81="Credit period",D81="Superseded record"),Scoring!$C$35,Scoring!$C$34))))) -> 14 | AF81: =IF(T81="Y",0,IF(ISNUMBER(V81),IF(Scoring!$B$4-V81>15,Scoring!$C$36,IF(Scoring!$B$4-V81>=10,Scoring!$C$37,IF(Scoring!$B$4-V81>=5,Scoring!$C$38,Scoring!$C$39))),IF(OR(N81="",D81="Out of program"),Scoring!$C$40,IF(O81>15,Scoring!$C$36,IF(O81>=10,Scoring!$C$37,IF(O81>=5,Scoring!$C$38,Scoring!$C$39)))))) -> 15 | AG81: =IF(T81="Y",0,IF(Y81="Y",Scoring!$C$41,IF(ISNUMBER(O81),IF(O81>=25,Scoring!$C$42,IF(O81>=15,Scoring!$C$43,Scoring!$C$44)),Scoring!$C$44))) -> 8 | AH81: =IF(T81="Y",0,IF(W81="",Scoring!$C$49,IFERROR(VLOOKUP(W81,Scoring!$B$45:$C$48,2,FALSE()),Scoring!$C$49))) -> 5 | AI81: =C81+IF(ISNUMBER(J81),J81,0)/100000+(10000-ROW())/1000000000 -> 70.00021
A82: =RANK(AI82,$AI$2:$AI$755) -> 81 | B82: =IF(T82="Y","Superseded",IF(C82>=Scoring!$B$16,"Immediate",IF(C82>=Scoring!$B$17,"This week",IF(C82>=Scoring!$B$18,"Nurture","Low")))) -> This week | C82: =SUM(AC82:AH82) -> 70 | D82: =IF(T82="Y","Superseded record",IF(AND(U82<>"",AA82<0),"Expired (verified)",IF(AND(U82<>"",AA82<=Scoring!$B$5),"Expiring: notice window (verified)",IF(AND(U82<>"",AA82<=Scoring!$B$6),"Expiring: 10-yr horizon (verified)",IF(M82="No Longer Monitored","Out of program",IF(N82="","Unknown vintage",IF(N82<Scoring!$B$12,"Pre-1990, still listed",IF(AND(U82="",AA82<0),"Past 30-yr mark (verify)",IF(AND(U82="",AA82<=Scoring!$B$5),"30-yr mark: notice window (est.)",IF(AND(O82>=Scoring!$B$7,O82<=Scoring!$B$8),"Year-15 window",IF(O82>=Scoring!$B$9,"Recap window",IF(O82>=11,"Late compliance","Credit period")))))))))))) -> 30-yr mark: notice window (est.) | E82: ORA19990105 | F82: OAK PLAZA APTS | G82: 1265 SALEM AVE SE | H82: ALBANY | I82: 97321 | J82: 20 | K82: 20 | L82: =IF(OR(J82="",K82=""),"",MAX(J82-K82,0)) -> 0 | M82: Not Indicated | N82: 1999 | O82: =IF(N82="","",Scoring!$B$4-N82) -> 27 | P82: =IF(N82="","",N82+14) -> 2013 | Q82: =IF(N82="","",IF(N82<Scoring!$B$12,"n/a (pre-1990)",N82+Scoring!$B$13)) -> 2028 | R82: =IF(J82="","Unknown",IF(J82>=5,"Yes","No (under 5 units)")) -> Yes | AA82: =IF(U82<>"",(U82-Scoring!$B$3)/365.25,IF(N82="","",IF(N82<Scoring!$B$12,"",(DATE(N82+Scoring!$B$13,12,31)-Scoring!$B$3)/365.25))) -> 2.2477755 | AB82: =IF(T82="Y",0,IF(OR(D82="Expired (verified)",D82="Expiring: notice window (verified)",D82="Expiring: 10-yr horizon (verified)",D82="Past 30-yr mark (verify)",D82="30-yr mark: notice window (est.)",D82="Year-15 window"),1,0)+IF(ISNUMBER(O82),IF(O82>=Scoring!$B$10,1,0),0)+IF(AND(ISNUMBER(L82),ISNUMBER(J82)),IF(J82>0,IF(L82/J82>=Scoring!$B$11,1,0),0),0)+IF(ISNUMBER(Z82),MIN(Z82,3),0)) -> 2 | AC82: =IF(AB82>=3,Scoring!$C$24,IF(AB82=2,Scoring!$C$23,IF(AB82=1,Scoring!$C$22,0))) -> 18 | AD82: =IF(T82="Y",0,IF(ISNUMBER(X82),IF(X82>0.7,Scoring!$C$25,IF(X82>=0.5,Scoring!$C$26,IF(X82>=0.3,Scoring!$C$27,Scoring!$C$28))),Scoring!$C$29)) -> 10 | AE82: =IF(D82="Expiring: notice window (verified)",Scoring!$C$30,IF(OR(D82="Expired (verified)",D82="30-yr mark: notice window (est.)",D82="Year-15 window"),Scoring!$C$31,IF(D82="Expiring: 10-yr horizon (verified)",Scoring!$C$32,IF(D82="Past 30-yr mark (verify)",Scoring!$C$33,IF(OR(D82="Credit period",D82="Superseded record"),Scoring!$C$35,Scoring!$C$34))))) -> 14 | AF82: =IF(T82="Y",0,IF(ISNUMBER(V82),IF(Scoring!$B$4-V82>15,Scoring!$C$36,IF(Scoring!$B$4-V82>=10,Scoring!$C$37,IF(Scoring!$B$4-V82>=5,Scoring!$C$38,Scoring!$C$39))),IF(OR(N82="",D82="Out of program"),Scoring!$C$40,IF(O82>15,Scoring!$C$36,IF(O82>=10,Scoring!$C$37,IF(O82>=5,Scoring!$C$38,Scoring!$C$39)))))) -> 15 | AG82: =IF(T82="Y",0,IF(Y82="Y",Scoring!$C$41,IF(ISNUMBER(O82),IF(O82>=25,Scoring!$C$42,IF(O82>=15,Scoring!$C$43,Scoring!$C$44)),Scoring!$C$44))) -> 8 | AH82: =IF(T82="Y",0,IF(W82="",Scoring!$C$49,IFERROR(VLOOKUP(W82,Scoring!$B$45:$C$48,2,FALSE()),Scoring!$C$49))) -> 5 | AI82: =C82+IF(ISNUMBER(J82),J82,0)/100000+(10000-ROW())/1000000000 -> 70.00021
A83: =RANK(AI83,$AI$2:$AI$755) -> 82 | B83: =IF(T83="Y","Superseded",IF(C83>=Scoring!$B$16,"Immediate",IF(C83>=Scoring!$B$17,"This week",IF(C83>=Scoring!$B$18,"Nurture","Low")))) -> This week | C83: =SUM(AC83:AH83) -> 70 | D83: =IF(T83="Y","Superseded record",IF(AND(U83<>"",AA83<0),"Expired (verified)",IF(AND(U83<>"",AA83<=Scoring!$B$5),"Expiring: notice window (verified)",IF(AND(U83<>"",AA83<=Scoring!$B$6),"Expiring: 10-yr horizon (verified)",IF(M83="No Longer Monitored","Out of program",IF(N83="","Unknown vintage",IF(N83<Scoring!$B$12,"Pre-1990, still listed",IF(AND(U83="",AA83<0),"Past 30-yr mark (verify)",IF(AND(U83="",AA83<=Scoring!$B$5),"30-yr mark: notice window (est.)",IF(AND(O83>=Scoring!$B$7,O83<=Scoring!$B$8),"Year-15 window",IF(O83>=Scoring!$B$9,"Recap window",IF(O83>=11,"Late compliance","Credit period")))))))))))) -> 30-yr mark: notice window (est.) | E83: ORA19990090 | F83: MINERVA PLAZA APTS | G83: 6633 N OBERLIN ST | H83: PORTLAND | I83: 97203 | J83: 15 | K83: 15 | L83: =IF(OR(J83="",K83=""),"",MAX(J83-K83,0)) -> 0 | M83: Not Indicated | N83: 1999 | O83: =IF(N83="","",Scoring!$B$4-N83) -> 27 | P83: =IF(N83="","",N83+14) -> 2013 | Q83: =IF(N83="","",IF(N83<Scoring!$B$12,"n/a (pre-1990)",N83+Scoring!$B$13)) -> 2028 | R83: =IF(J83="","Unknown",IF(J83>=5,"Yes","No (under 5 units)")) -> Yes | AA83: =IF(U83<>"",(U83-Scoring!$B$3)/365.25,IF(N83="","",IF(N83<Scoring!$B$12,"",(DATE(N83+Scoring!$B$13,12,31)-Scoring!$B$3)/365.25))) -> 2.2477755 | AB83: =IF(T83="Y",0,IF(OR(D83="Expired (verified)",D83="Expiring: notice window (verified)",D83="Expiring: 10-yr horizon (verified)",D83="Past 30-yr mark (verify)",D83="30-yr mark: notice window (est.)",D83="Year-15 window"),1,0)+IF(ISNUMBER(O83),IF(O83>=Scoring!$B$10,1,0),0)+IF(AND(ISNUMBER(L83),ISNUMBER(J83)),IF(J83>0,IF(L83/J83>=Scoring!$B$11,1,0),0),0)+IF(ISNUMBER(Z83),MIN(Z83,3),0)) -> 2 | AC83: =IF(AB83>=3,Scoring!$C$24,IF(AB83=2,Scoring!$C$23,IF(AB83=1,Scoring!$C$22,0))) -> 18 | AD83: =IF(T83="Y",0,IF(ISNUMBER(X83),IF(X83>0.7,Scoring!$C$25,IF(X83>=0.5,Scoring!$C$26,IF(X83>=0.3,Scoring!$C$27,Scoring!$C$28))),Scoring!$C$29)) -> 10 | AE83: =IF(D83="Expiring: notice window (verified)",Scoring!$C$30,IF(OR(D83="Expired (verified)",D83="30-yr mark: notice window (est.)",D83="Year-15 window"),Scoring!$C$31,IF(D83="Expiring: 10-yr horizon (verified)",Scoring!$C$32,IF(D83="Past 30-yr mark (verify)",Scoring!$C$33,IF(OR(D83="Credit period",D83="Superseded record"),Scoring!$C$35,Scoring!$C$34))))) -> 14 | AF83: =IF(T83="Y",0,IF(ISNUMBER(V83),IF(Scoring!$B$4-V83>15,Scoring!$C$36,IF(Scoring!$B$4-V83>=10,Scoring!$C$37,IF(Scoring!$B$4-V83>=5,Scoring!$C$38,Scoring!$C$39))),IF(OR(N83="",D83="Out of program"),Scoring!$C$40,IF(O83>15,Scoring!$C$36,IF(O83>=10,Scoring!$C$37,IF(O83>=5,Scoring!$C$38,Scoring!$C$39)))))) -> 15 | AG83: =IF(T83="Y",0,IF(Y83="Y",Scoring!$C$41,IF(ISNUMBER(O83),IF(O83>=25,Scoring!$C$42,IF(O83>=15,Scoring!$C$43,Scoring!$C$44)),Scoring!$C$44))) -> 8 | AH83: =IF(T83="Y",0,IF(W83="",Scoring!$C$49,IFERROR(VLOOKUP(W83,Scoring!$B$45:$C$48,2,FALSE()),Scoring!$C$49))) -> 5 | AI83: =C83+IF(ISNUMBER(J83),J83,0)/100000+(10000-ROW())/1000000000 -> 70.00016
A84: =RANK(AI84,$AI$2:$AI$755) -> 83 | B84: =IF(T84="Y","Superseded",IF(C84>=Scoring!$B$16,"Immediate",IF(C84>=Scoring!$B$17,"This week",IF(C84>=Scoring!$B$18,"Nurture","Low")))) -> This week | C84: =SUM(AC84:AH84) -> 70 | D84: =IF(T84="Y","Superseded record",IF(AND(U84<>"",AA84<0),"Expired (verified)",IF(AND(U84<>"",AA84<=Scoring!$B$5),"Expiring: notice window (verified)",IF(AND(U84<>"",AA84<=Scoring!$B$6),"Expiring: 10-yr horizon (verified)",IF(M84="No Longer Monitored","Out of program",IF(N84="","Unknown vintage",IF(N84<Scoring!$B$12,"Pre-1990, still listed",IF(AND(U84="",AA84<0),"Past 30-yr mark (verify)",IF(AND(U84="",AA84<=Scoring!$B$5),"30-yr mark: notice window (est.)",IF(AND(O84>=Scoring!$B$7,O84<=Scoring!$B$8),"Year-15 window",IF(O84>=Scoring!$B$9,"Recap window",IF(O84>=11,"Late compliance","Credit period")))))))))))) -> 30-yr mark: notice window (est.) | E84: ORA19990045 | F84: COTTONWOOD APTS | G84: 2 SW MILL ST | H84: JOSEPH | J84: 14 | K84: 14 | L84: =IF(OR(J84="",K84=""),"",MAX(J84-K84,0)) -> 0 | M84: Not Indicated | N84: 1999 | O84: =IF(N84="","",Scoring!$B$4-N84) -> 27 | P84: =IF(N84="","",N84+14) -> 2013 | Q84: =IF(N84="","",IF(N84<Scoring!$B$12,"n/a (pre-1990)",N84+Scoring!$B$13)) -> 2028 | R84: =IF(J84="","Unknown",IF(J84>=5,"Yes","No (under 5 units)")) -> Yes | AA84: =IF(U84<>"",(U84-Scoring!$B$3)/365.25,IF(N84="","",IF(N84<Scoring!$B$12,"",(DATE(N84+Scoring!$B$13,12,31)-Scoring!$B$3)/365.25))) -> 2.2477755 | AB84: =IF(T84="Y",0,IF(OR(D84="Expired (verified)",D84="Expiring: notice window (verified)",D84="Expiring: 10-yr horizon (verified)",D84="Past 30-yr mark (verify)",D84="30-yr mark: notice window (est.)",D84="Year-15 window"),1,0)+IF(ISNUMBER(O84),IF(O84>=Scoring!$B$10,1,0),0)+IF(AND(ISNUMBER(L84),ISNUMBER(J84)),IF(J84>0,IF(L84/J84>=Scoring!$B$11,1,0),0),0)+IF(ISNUMBER(Z84),MIN(Z84,3),0)) -> 2 | AC84: =IF(AB84>=3,Scoring!$C$24,IF(AB84=2,Scoring!$C$23,IF(AB84=1,Scoring!$C$22,0))) -> 18 | AD84: =IF(T84="Y",0,IF(ISNUMBER(X84),IF(X84>0.7,Scoring!$C$25,IF(X84>=0.5,Scoring!$C$26,IF(X84>=0.3,Scoring!$C$27,Scoring!$C$28))),Scoring!$C$29)) -> 10 | AE84: =IF(D84="Expiring: notice window (verified)",Scoring!$C$30,IF(OR(D84="Expired (verified)",D84="30-yr mark: notice window (est.)",D84="Year-15 window"),Scoring!$C$31,IF(D84="Expiring: 10-yr horizon (verified)",Scoring!$C$32,IF(D84="Past 30-yr mark (verify)",Scoring!$C$33,IF(OR(D84="Credit period",D84="Superseded record"),Scoring!$C$35,Scoring!$C$34))))) -> 14 | AF84: =IF(T84="Y",0,IF(ISNUMBER(V84),IF(Scoring!$B$4-V84>15,Scoring!$C$36,IF(Scoring!$B$4-V84>=10,Scoring!$C$37,IF(Scoring!$B$4-V84>=5,Scoring!$C$38,Scoring!$C$39))),IF(OR(N84="",D84="Out of program"),Scoring!$C$40,IF(O84>15,Scoring!$C$36,IF(O84>=10,Scoring!$C$37,IF(O84>=5,Scoring!$C$38,Scoring!$C$39)))))) -> 15 | AG84: =IF(T84="Y",0,IF(Y84="Y",Scoring!$C$41,IF(ISNUMBER(O84),IF(O84>=25,Scoring!$C$42,IF(O84>=15,Scoring!$C$43,Scoring!$C$44)),Scoring!$C$44))) -> 8 | AH84: =IF(T84="Y",0,IF(W84="",Scoring!$C$49,IFERROR(VLOOKUP(W84,Scoring!$B$45:$C$48,2,FALSE()),Scoring!$C$49))) -> 5 | AI84: =C84+IF(ISNUMBER(J84),J84,0)/100000+(10000-ROW())/1000000000 -> 70.00015
A85: =RANK(AI85,$AI$2:$AI$755) -> 84 | B85: =IF(T85="Y","Superseded",IF(C85>=Scoring!$B$16,"Immediate",IF(C85>=Scoring!$B$17,"This week",IF(C85>=Scoring!$B$18,"Nurture","Low")))) -> This week | C85: =SUM(AC85:AH85) -> 70 | D85: =IF(T85="Y","Superseded record",IF(AND(U85<>"",AA85<0),"Expired (verified)",IF(AND(U85<>"",AA85<=Scoring!$B$5),"Expiring: notice window (verified)",IF(AND(U85<>"",AA85<=Scoring!$B$6),"Expiring: 10-yr horizon (verified)",IF(M85="No Longer Monitored","Out of program",IF(N85="","Unknown vintage",IF(N85<Scoring!$B$12,"Pre-1990, still listed",IF(AND(U85="",AA85<0),"Past 30-yr mark (verify)",IF(AND(U85="",AA85<=Scoring!$B$5),"30-yr mark: notice window (est.)",IF(AND(O85>=Scoring!$B$7,O85<=Scoring!$B$8),"Year-15 window",IF(O85>=Scoring!$B$9,"Recap window",IF(O85>=11,"Late compliance","Credit period")))))))))))) -> 30-yr mark: notice window (est.) | E85: ORA19980030 | F85: BLUEBELLE DEVELOPMENT I | G85: 249 S 41ST PL | H85: SPRINGFIELD | I85: 97478 | J85: 10 | K85: 10 | L85: =IF(OR(J85="",K85=""),"",MAX(J85-K85,0)) -> 0 | M85: Not Indicated | N85: 1998 | O85: =IF(N85="","",Scoring!$B$4-N85) -> 28 | P85: =IF(N85="","",N85+14) -> 2012 | Q85: =IF(N85="","",IF(N85<Scoring!$B$12,"n/a (pre-1990)",N85+Scoring!$B$13)) -> 2027 | R85: =IF(J85="","Unknown",IF(J85>=5,"Yes","No (under 5 units)")) -> Yes | AA85: =IF(U85<>"",(U85-Scoring!$B$3)/365.25,IF(N85="","",IF(N85<Scoring!$B$12,"",(DATE(N85+Scoring!$B$13,12,31)-Scoring!$B$3)/365.25))) -> 1.2457221 | AB85: =IF(T85="Y",0,IF(OR(D85="Expired (verified)",D85="Expiring: notice window (verified)",D85="Expiring: 10-yr horizon (verified)",D85="Past 30-yr mark (verify)",D85="30-yr mark: notice window (est.)",D85="Year-15 window"),1,0)+IF(ISNUMBER(O85),IF(O85>=Scoring!$B$10,1,0),0)+IF(AND(ISNUMBER(L85),ISNUMBER(J85)),IF(J85>0,IF(L85/J85>=Scoring!$B$11,1,0),0),0)+IF(ISNUMBER(Z85),MIN(Z85,3),0)) -> 2 | AC85: =IF(AB85>=3,Scoring!$C$24,IF(AB85=2,Scoring!$C$23,IF(AB85=1,Scoring!$C$22,0))) -> 18 | AD85: =IF(T85="Y",0,IF(ISNUMBER(X85),IF(X85>0.7,Scoring!$C$25,IF(X85>=0.5,Scoring!$C$26,IF(X85>=0.3,Scoring!$C$27,Scoring!$C$28))),Scoring!$C$29)) -> 10 | AE85: =IF(D85="Expiring: notice window (verified)",Scoring!$C$30,IF(OR(D85="Expired (verified)",D85="30-yr mark: notice window (est.)",D85="Year-15 window"),Scoring!$C$31,IF(D85="Expiring: 10-yr horizon (verified)",Scoring!$C$32,IF(D85="Past 30-yr mark (verify)",Scoring!$C$33,IF(OR(D85="Credit period",D85="Superseded record"),Scoring!$C$35,Scoring!$C$34))))) -> 14 | AF85: =IF(T85="Y",0,IF(ISNUMBER(V85),IF(Scoring!$B$4-V85>15,Scoring!$C$36,IF(Scoring!$B$4-V85>=10,Scoring!$C$37,IF(Scoring!$B$4-V85>=5,Scoring!$C$38,Scoring!$C$39))),IF(OR(N85="",D85="Out of program"),Scoring!$C$40,IF(O85>15,Scoring!$C$36,IF(O85>=10,Scoring!$C$37,IF(O85>=5,Scoring!$C$38,Scoring!$C$39)))))) -> 15 | AG85: =IF(T85="Y",0,IF(Y85="Y",Scoring!$C$41,IF(ISNUMBER(O85),IF(O85>=25,Scoring!$C$42,IF(O85>=15,Scoring!$C$43,Scoring!$C$44)),Scoring!$C$44))) -> 8 | AH85: =IF(T85="Y",0,IF(W85="",Scoring!$C$49,IFERROR(VLOOKUP(W85,Scoring!$B$45:$C$48,2,FALSE()),Scoring!$C$49))) -> 5 | AI85: =C85+IF(ISNUMBER(J85),J85,0)/100000+(10000-ROW())/1000000000 -> 70.00011
A86: =RANK(AI86,$AI$2:$AI$755) -> 85 | B86: =IF(T86="Y","Superseded",IF(C86>=Scoring!$B$16,"Immediate",IF(C86>=Scoring!$B$17,"This week",IF(C86>=Scoring!$B$18,"Nurture","Low")))) -> This week | C86: =SUM(AC86:AH86) -> 70 | D86: =IF(T86="Y","Superseded record",IF(AND(U86<>"",AA86<0),"Expired (verified)",IF(AND(U86<>"",AA86<=Scoring!$B$5),"Expiring: notice window (verified)",IF(AND(U86<>"",AA86<=Scoring!$B$6),"Expiring: 10-yr horizon (verified)",IF(M86="No Longer Monitored","Out of program",IF(N86="","Unknown vintage",IF(N86<Scoring!$B$12,"Pre-1990, still listed",IF(AND(U86="",AA86<0),"Past 30-yr mark (verify)",IF(AND(U86="",AA86<=Scoring!$B$5),"30-yr mark: notice window (est.)",IF(AND(O86>=Scoring!$B$7,O86<=Scoring!$B$8),"Year-15 window",IF(O86>=Scoring!$B$9,"Recap window",IF(O86>=11,"Late compliance","Credit period")))))))))))) -> 30-yr mark: notice window (est.) | E86: ORA19970110 | F86: SUNSET APTS (ONTARIO) | G86: 82 SUNSET DR | H86: ONTARIO | I86: 97914 | J86: 9 | K86: 9 | L86: =IF(OR(J86="",K86=""),"",MAX(J86-K86,0)) -> 0 | M86: Not Indicated | N86: 1997 | O86: =IF(N86="","",Scoring!$B$4-N86) -> 29 | P86: =IF(N86="","",N86+14) -> 2011 | Q86: =IF(N86="","",IF(N86<Scoring!$B$12,"n/a (pre-1990)",N86+Scoring!$B$13)) -> 2026 | R86: =IF(J86="","Unknown",IF(J86>=5,"Yes","No (under 5 units)")) -> Yes | AA86: =IF(U86<>"",(U86-Scoring!$B$3)/365.25,IF(N86="","",IF(N86<Scoring!$B$12,"",(DATE(N86+Scoring!$B$13,12,31)-Scoring!$B$3)/365.25))) -> 0.24640657 | AB86: =IF(T86="Y",0,IF(OR(D86="Expired (verified)",D86="Expiring: notice window (verified)",D86="Expiring: 10-yr horizon (verified)",D86="Past 30-yr mark (verify)",D86="30-yr mark: notice window (est.)",D86="Year-15 window"),1,0)+IF(ISNUMBER(O86),IF(O86>=Scoring!$B$10,1,0),0)+IF(AND(ISNUMBER(L86),ISNUMBER(J86)),IF(J86>0,IF(L86/J86>=Scoring!$B$11,1,0),0),0)+IF(ISNUMBER(Z86),MIN(Z86,3),0)) -> 2 | AC86: =IF(AB86>=3,Scoring!$C$24,IF(AB86=2,Scoring!$C$23,IF(AB86=1,Scoring!$C$22,0))) -> 18 | AD86: =IF(T86="Y",0,IF(ISNUMBER(X86),IF(X86>0.7,Scoring!$C$25,IF(X86>=0.5,Scoring!$C$26,IF(X86>=0.3,Scoring!$C$27,Scoring!$C$28))),Scoring!$C$29)) -> 10 | AE86: =IF(D86="Expiring: notice window (verified)",Scoring!$C$30,IF(OR(D86="Expired (verified)",D86="30-yr mark: notice window (est.)",D86="Year-15 window"),Scoring!$C$31,IF(D86="Expiring: 10-yr horizon (verified)",Scoring!$C$32,IF(D86="Past 30-yr mark (verify)",Scoring!$C$33,IF(OR(D86="Credit period",D86="Superseded record"),Scoring!$C$35,Scoring!$C$34))))) -> 14 | AF86: =IF(T86="Y",0,IF(ISNUMBER(V86),IF(Scoring!$B$4-V86>15,Scoring!$C$36,IF(Scoring!$B$4-V86>=10,Scoring!$C$37,IF(Scoring!$B$4-V86>=5,Scoring!$C$38,Scoring!$C$39))),IF(OR(N86="",D86="Out of program"),Scoring!$C$40,IF(O86>15,Scoring!$C$36,IF(O86>=10,Scoring!$C$37,IF(O86>=5,Scoring!$C$38,Scoring!$C$39)))))) -> 15 | AG86: =IF(T86="Y",0,IF(Y86="Y",Scoring!$C$41,IF(ISNUMBER(O86),IF(O86>=25,Scoring!$C$42,IF(O86>=15,Scoring!$C$43,Scoring!$C$44)),Scoring!$C$44))) -> 8 | AH86: =IF(T86="Y",0,IF(W86="",Scoring!$C$49,IFERROR(VLOOKUP(W86,Scoring!$B$45:$C$48,2,FALSE()),Scoring!$C$49))) -> 5 | AI86: =C86+IF(ISNUMBER(J86),J86,0)/100000+(10000-ROW())/1000000000 -> 70.0001
A87: =RANK(AI87,$AI$2:$AI$755) -> 86 | B87: =IF(T87="Y","Superseded",IF(C87>=Scoring!$B$16,"Immediate",IF(C87>=Scoring!$B$17,"This week",IF(C87>=Scoring!$B$18,"Nurture","Low")))) -> This week | C87: =SUM(AC87:AH87) -> 70 | D87: =IF(T87="Y","Superseded record",IF(AND(U87<>"",AA87<0),"Expired (verified)",IF(AND(U87<>"",AA87<=Scoring!$B$5),"Expiring: notice window (verified)",IF(AND(U87<>"",AA87<=Scoring!$B$6),"Expiring: 10-yr horizon (verified)",IF(M87="No Longer Monitored","Out of program",IF(N87="","Unknown vintage",IF(N87<Scoring!$B$12,"Pre-1990, still listed",IF(AND(U87="",AA87<0),"Past 30-yr mark (verify)",IF(AND(U87="",AA87<=Scoring!$B$5),"30-yr mark: notice window (est.)",IF(AND(O87>=Scoring!$B$7,O87<=Scoring!$B$8),"Year-15 window",IF(O87>=Scoring!$B$9,"Recap window",IF(O87>=11,"Late compliance","Credit period")))))))))))) -> 30-yr mark: notice window (est.) | E87: ORA19980035 | F87: BLUEBELLE DEVELOPMENT II | G87: 1061 S ST | H87: SPRINGFIELD | I87: 97477 | J87: 3 | K87: 3 | L87: =IF(OR(J87="",K87=""),"",MAX(J87-K87,0)) -> 0 | M87: Not Indicated | N87: 1998 | O87: =IF(N87="","",Scoring!$B$4-N87) -> 28 | P87: =IF(N87="","",N87+14) -> 2012 | Q87: =IF(N87="","",IF(N87<Scoring!$B$12,"n/a (pre-1990)",N87+Scoring!$B$13)) -> 2027 | R87: =IF(J87="","Unknown",IF(J87>=5,"Yes","No (under 5 units)")) -> No (under 5 units) | AA87: =IF(U87<>"",(U87-Scoring!$B$3)/365.25,IF(N87="","",IF(N87<Scoring!$B$12,"",(DATE(N87+Scoring!$B$13,12,31)-Scoring!$B$3)/365.25))) -> 1.2457221 | AB87: =IF(T87="Y",0,IF(OR(D87="Expired (verified)",D87="Expiring: notice window (verified)",D87="Expiring: 10-yr horizon (verified)",D87="Past 30-yr mark (verify)",D87="30-yr mark: notice window (est.)",D87="Year-15 window"),1,0)+IF(ISNUMBER(O87),IF(O87>=Scoring!$B$10,1,0),0)+IF(AND(ISNUMBER(L87),ISNUMBER(J87)),IF(J87>0,IF(L87/J87>=Scoring!$B$11,1,0),0),0)+IF(ISNUMBER(Z87),MIN(Z87,3),0)) -> 2 | AC87: =IF(AB87>=3,Scoring!$C$24,IF(AB87=2,Scoring!$C$23,IF(AB87=1,Scoring!$C$22,0))) -> 18 | AD87: =IF(T87="Y",0,IF(ISNUMBER(X87),IF(X87>0.7,Scoring!$C$25,IF(X87>=0.5,Scoring!$C$26,IF(X87>=0.3,Scoring!$C$27,Scoring!$C$28))),Scoring!$C$29)) -> 10 | AE87: =IF(D87="Expiring: notice window (verified)",Scoring!$C$30,IF(OR(D87="Expired (verified)",D87="30-yr mark: notice window (est.)",D87="Year-15 window"),Scoring!$C$31,IF(D87="Expiring: 10-yr horizon (verified)",Scoring!$C$32,IF(D87="Past 30-yr mark (verify)",Scoring!$C$33,IF(OR(D87="Credit period",D87="Superseded record"),Scoring!$C$35,Scoring!$C$34))))) -> 14 | AF87: =IF(T87="Y",0,IF(ISNUMBER(V87),IF(Scoring!$B$4-V87>15,Scoring!$C$36,IF(Scoring!$B$4-V87>=10,Scoring!$C$37,IF(Scoring!$B$4-V87>=5,Scoring!$C$38,Scoring!$C$39))),IF(OR(N87="",D87="Out of program"),Scoring!$C$40,IF(O87>15,Scoring!$C$36,IF(O87>=10,Scoring!$C$37,IF(O87>=5,Scoring!$C$38,Scoring!$C$39)))))) -> 15 | AG87: =IF(T87="Y",0,IF(Y87="Y",Scoring!$C$41,IF(ISNUMBER(O87),IF(O87>=25,Scoring!$C$42,IF(O87>=15,Scoring!$C$43,Scoring!$C$44)),Scoring!$C$44))) -> 8 | AH87: =IF(T87="Y",0,IF(W87="",Scoring!$C$49,IFERROR(VLOOKUP(W87,Scoring!$B$45:$C$48,2,FALSE()),Scoring!$C$49))) -> 5 | AI87: =C87+IF(ISNUMBER(J87),J87,0)/100000+(10000-ROW())/1000000000 -> 70.00004
A88: =RANK(AI88,$AI$2:$AI$755) -> 87 | B88: =IF(T88="Y","Superseded",IF(C88>=Scoring!$B$16,"Immediate",IF(C88>=Scoring!$B$17,"This week",IF(C88>=Scoring!$B$18,"Nurture","Low")))) -> This week | C88: =SUM(AC88:AH88) -> 67 | D88: =IF(T88="Y","Superseded record",IF(AND(U88<>"",AA88<0),"Expired (verified)",IF(AND(U88<>"",AA88<=Scoring!$B$5),"Expiring: notice window (verified)",IF(AND(U88<>"",AA88<=Scoring!$B$6),"Expiring: 10-yr horizon (verified)",IF(M88="No Longer Monitored","Out of program",IF(N88="","Unknown vintage",IF(N88<Scoring!$B$12,"Pre-1990, still listed",IF(AND(U88="",AA88<0),"Past 30-yr mark (verify)",IF(AND(U88="",AA88<=Scoring!$B$5),"30-yr mark: notice window (est.)",IF(AND(O88>=Scoring!$B$7,O88<=Scoring!$B$8),"Year-15 window",IF(O88>=Scoring!$B$9,"Recap window",IF(O88>=11,"Late compliance","Credit period")))))))))))) -> Year-15 window | E88: ORA20100035 | F88: CREST BUTTE APTS | G88: 1695 NE PURCELL BLVD | H88: BEND | I88: 97701 | J88: 52 | K88: 41 | L88: =IF(OR(J88="",K88=""),"",MAX(J88-K88,0)) -> 11 | M88: Not Indicated | N88: 2010 | O88: =IF(N88="","",Scoring!$B$4-N88) -> 16 | P88: =IF(N88="","",N88+14) -> 2024 | Q88: =IF(N88="","",IF(N88<Scoring!$B$12,"n/a (pre-1990)",N88+Scoring!$B$13)) -> 2039 | R88: =IF(J88="","Unknown",IF(J88>=5,"Yes","No (under 5 units)")) -> Yes | AA88: =IF(U88<>"",(U88-Scoring!$B$3)/365.25,IF(N88="","",IF(N88<Scoring!$B$12,"",(DATE(N88+Scoring!$B$13,12,31)-Scoring!$B$3)/365.25))) -> 13.245722 | AB88: =IF(T88="Y",0,IF(OR(D88="Expired (verified)",D88="Expiring: notice window (verified)",D88="Expiring: 10-yr horizon (verified)",D88="Past 30-yr mark (verify)",D88="30-yr mark: notice window (est.)",D88="Year-15 window"),1,0)+IF(ISNUMBER(O88),IF(O88>=Scoring!$B$10,1,0),0)+IF(AND(ISNUMBER(L88),ISNUMBER(J88)),IF(J88>0,IF(L88/J88>=Scoring!$B$11,1,0),0),0)+IF(ISNUMBER(Z88),MIN(Z88,3),0)) -> 2 | AC88: =IF(AB88>=3,Scoring!$C$24,IF(AB88=2,Scoring!$C$23,IF(AB88=1,Scoring!$C$22,0))) -> 18 | AD88: =IF(T88="Y",0,IF(ISNUMBER(X88),IF(X88>0.7,Scoring!$C$25,IF(X88>=0.5,Scoring!$C$26,IF(X88>=0.3,Scoring!$C$27,Scoring!$C$28))),Scoring!$C$29)) -> 10 | AE88: =IF(D88="Expiring: notice window (verified)",Scoring!$C$30,IF(OR(D88="Expired (verified)",D88="30-yr mark: notice window (est.)",D88="Year-15 window"),Scoring!$C$31,IF(D88="Expiring: 10-yr horizon (verified)",Scoring!$C$32,IF(D88="Past 30-yr mark (verify)",Scoring!$C$33,IF(OR(D88="Credit period",D88="Superseded record"),Scoring!$C$35,Scoring!$C$34))))) -> 14 | AF88: =IF(T88="Y",0,IF(ISNUMBER(V88),IF(Scoring!$B$4-V88>15,Scoring!$C$36,IF(Scoring!$B$4-V88>=10,Scoring!$C$37,IF(Scoring!$B$4-V88>=5,Scoring!$C$38,Scoring!$C$39))),IF(OR(N88="",D88="Out of program"),Scoring!$C$40,IF(O88>15,Scoring!$C$36,IF(O88>=10,Scoring!$C$37,IF(O88>=5,Scoring!$C$38,Scoring!$C$39)))))) -> 15 | AG88: =IF(T88="Y",0,IF(Y88="Y",Scoring!$C$41,IF(ISNUMBER(O88),IF(O88>=25,Scoring!$C$42,IF(O88>=15,Scoring!$C$43,Scoring!$C$44)),Scoring!$C$44))) -> 5 | AH88: =IF(T88="Y",0,IF(W88="",Scoring!$C$49,IFERROR(VLOOKUP(W88,Scoring!$B$45:$C$48,2,FALSE()),Scoring!$C$49))) -> 5 | AI88: =C88+IF(ISNUMBER(J88),J88,0)/100000+(10000-ROW())/1000000000 -> 67.00053
